Workbook

Sheet Cover
I3: blog.lucidtext.com
C7: EB-5 Backlog Analysis and Backlog Data
C9: Updated as of: | D9: 46238
C10: Document link: | D10: https://www.dropbox.com/scl/fi/xkbkaox1hgepg6nn6v3l9/EB5-Backlog-Analysis.xlsx?rlkey=iwnaj84r7apd0matmr0vagkq2&dl=0 | K10: .
D11: https://blog.lucidtext.com/eb-5-timing/
C12: Table of Contents
C13: Orientation | D13: Summarize what's known and unknown related to EB-5 visa availability and timing
C14: Summary 1 | D14: One way of looking at the supply/demand balance for EB-5 set-aside visas (starting from data through March 2026, and including a priority date estimator)
C15: Unreserved | D15: A calculator for estimating pre-RIA legacy backlog status and progress
C16: Infra | D16: FYI: A collection of research on Infrastructure demand
C17: Progress | D17: FYI: Collection of data related to progress in issuing Reserved visas and advancing pipeline applicants to the visa stage
C18: Pre-RIA Data | D18: FYI: Collection of pre-RIA data with source links
C19: Post-RIA Data | D19: FYI: Collection of post-RIA data with source links
C20: VB Log | D20: FYI: Log of past visa bulletins
C21: Notes | D21: Log of major updates and revisions to the model.
C23: Supporting Article Link:
C24: https://blog.lucidtext.com/2026/03/05/eb-5-set-aside-visa-backlog-and-outlook-update-as-of-march-2026-set-aside-backlog-size-unreserved-visa-availability-infrastructure-visa-bulletin-outlook/ | K24: .
C26: Contact:
C27: Email suzanne@lucidtext.com with any corrections or suggestions to improve this model.
C28: If you'd like Suzanne to talk through analysis and data relevant to your specific questions, you're welcome to schedule a consultation using the meeting link below.
D29: https://calendly.com/suzanne-lucid
C31: Note:
C32: This workbook analyzes a volatile reality. The model is populated with assumptions that may not be realized, and it pieces together incomplete data. Despite the author's best efforts, there may be errors in formulas or reasoning. (Email suzanne@lucidtext.com if you identify any!) The model is subject to regular revision and updates, as the situation evolves and more information becomes available. The model is offered as a tool to help support your own analysis. Do not rely on the model's default assumptions or conclusions a primary basis for decision-making. This workbook was created and is maintained by Suzanne Lazicki of blog.lucidtext.com.

Sheet Orientation
A1: The Big Picture
A14: What's Known as of January 2026
B15: Unreserved visa demand
C16: Pending I-485 through October 2025, National Visa Center data as of May 2024
B17: Rural and High Unemployment visa demand
C18: I-526/I-526E receipts and approvals to July 2025
B19: Infrastructure visa demand
C20: anecdotal reports about projects (USCIS has reported no receipt or approval data)
B21: Past visa issuance through mid 2025
B22: Average future visa availability
B23: I-526/I-526E approval letters since 2022 list Unreserved as well as Reserved categories, NVC has published a process for consular applicants to select from the category options, and USCIS has not yet published a process for AOS to make the selection
A25: Major Questions as of January 2026
B26: Questions about demand
C27: Investor trend (How many more investors since last data report, in which categories?)
C28: Investors-to-future visas (Family size? Denials and attrition over time?)
B29: Questions about visa supply & allocation
C30: # set-aside visas issued to-date and before retrogression
D31: recent petition approval and visa issuance volumes
D32: when will Rural, HUA, and Infra retrogress?
C33: # set-aside visas potentially unused by Rest of World, available above country cap to China and India
D34: ROW investor volume
D35: ROW applicant option and willingness to choose Unreserved
D36: how unused visas set-asides shared between China/India above country caps
C37: # Unreserved visas available to set-aside investors
D38: when will pre-2022 Unreserved backlogs be clear
D39: how will Unreserved visas be divided between Rural, HUA, infra
D40: how much friction in the option for a set-aside investor to request an Unreserved visa
D41: whether a significant difference between consular and AOS ability to access Unreserved
D42: whether a non-TEA investor would have priority for an Unreserved visa over a set-aside investor with an earlier priority date

Sheet Summary1
B2: SUPPLY DETAIL
B3: Typical Annual EB-5 Visa Limits
C4: EB-5 Total | D4: Rural Set Aside | E4: High Unemployment Set Aside | F4: Infrastructure Set Aside | G4: Unreserved
C5: 1 | D5: 0.2 | E5: 0.1 | F5: 0.02 | G5: =C5-SUM(D5:F5) -> 0.68
B6: Base EB Limit | C6: 140000
B7: Total Base Annual EB-5 Visas (rounded) | C7: =ROUNDUP(C6*I7,-2) -> 10000 | D7: =$C$7*D5 -> 2000 | E7: =$C$7*E5 -> 1000 | F7: =$C$7*F5 -> 200 | G7: =C7-SUM(D7:F7) -> 6800 | I7: 0.071
B8: China Minimum (country cap 7%) | C8: =C$7*$H8 -> 700 | D8: =D$7*$H8 -> 140 | E8: =E$7*$H8 -> 70 | F8: =F$7*$H8 -> 14 | G8: =G$7*$H8 -> 476 | H8: 0.07
B9: India Minimum (country cap 7%) | C9: =C$7*$H9 -> 700 | D9: =D$7*$H9 -> 140 | E9: =E$7*$H9 -> 70 | F9: =F$7*$H9 -> 14 | G9: =G$7*$H9 -> 476 | H9: 0.07
B10: Rest of World (ROW) Maximum (86%) | C10: =C$7*$H10 -> 8600 | D10: =D$7*$H10 -> 1720 | E10: =E$7*$H10 -> 860 | F10: =F$7*$H10 -> 172 | G10: =G$7*$H10 -> 5848 | H10: =1-H8-H9 -> 0.86
B12: Scenario with large FB rollover | C12: 15000 | D12: =$C$12*D5 -> 3000 | E12: =$C$12*E5 -> 1500 | F12: =$C$12*F5 -> 300 | G12: =$C$12*G5 -> 10200
B14: Supply notes:
B15: The typical annual EB-5 visa allocation follows from the base annual 140,000 EB visas. The actual EB limit can be higher due to rollover of FB visas unused in the previous year.
B16: China and India may receive visas above the 7% country cap if ROW does not claim its maximum visas
B17: Actual annual visas can be slightly below or well above 10,000 depending on rollover from family-based in previous year, or carryover from unused Reserved EB-5
B18: Actual visas issued can be lower than the annual limit, due to lack of applicants or to government processing constraints
B19: When new set-aside visas are unused one year, they carry over in the same set aside category the next year
B20: When carried-over set-aside visas are unused for a second year, they carry to Unreserved for the 3rd year.
B21: In theory, set aside investors can qualify for a set-aside visa or an Unreserved visa.
B23: EB-5 Visa Issuance 2022-2025 | J23: Total 2022-2025
C24: EB-5 Total | D24: Rural Set Aside | E24: High Unemployment Set Aside | F24: Infrastructure Set Aside | G24: Unreserved | K24: Set-Aside Total | L24: Rural Set Aside | M24: High Unemployment Set Aside | N24: Infrastructure Set Aside
B25: FY2022 (actual) | C25: =SUM(D25:G25) -> 10885 | D25: =Progress!C120 -> 0 | E25: =Progress!C128 -> 0 | F25: =Progress!C137 -> 0 | G25: =Progress!C149 -> 10885 | J25: China | K25: =SUM(L25:N25) -> 1395 | L25: =Progress!K117 -> 1181 | M25: =Progress!K125 -> 214 | N25: =Progress!K134 -> 0
B26: FY2023 (actual) | C26: =SUM(D26:G26) -> 9817 | D26: =Progress!D120 -> 0 | E26: =Progress!D128 -> 0 | F26: =Progress!D137 -> 0 | G26: =Progress!C150 -> 9817 | J26: India | K26: =SUM(L26:N26) -> 1185 | L26: =Progress!K118 -> 833 | M26: =Progress!K126 -> 352 | N26: =Progress!K135 -> 0
B27: FY2024 (actual) | C27: =SUM(D27:G27) -> 14924 | D27: =Progress!E120 -> 332 | E27: =Progress!E128 -> 91 | F27: =Progress!E137 -> 0 | G27: =Progress!C151 -> 14501 | J27: ROW | K27: =SUM(L27:N27) -> 633 | L27: =Progress!K119 -> 248 | M27: =Progress!K127 -> 385 | N27: =Progress!K136 -> 0
B28: FY2025 (estimate) | C28: =SUM(D28:G28) -> 14260 | D28: =Progress!J120 -> 1930 | E28: =Progress!J128 -> 860 | F28: =Progress!J137 -> 0 | G28: =Progress!C152 -> 11470 | K28: =SUM(K25:K27) -> 3213 | L28: =SUM(L25:L27) -> 2262 | M28: =SUM(M25:M27) -> 951 | N28: =SUM(N25:N27) -> 0
B29: Total 2022-2025 | D29: =SUM(D25:D28) -> 2262 | E29: =SUM(E25:E28) -> 951 | F29: =SUM(F25:F28) -> 0
B30: In 2022-2025, set-aside visa issuance was limited by government processing constraints, while the available limit was expanded by rollover and carryover visas due to lack of usage in previous years.
B32: DEMAND | L32: Forecast another date | M32: 46266
B33: Actual INVESTORS with priority dates between April 1, 2022 and March 31, 2026 | L33: Months since 3/31/2026 | M33: =(M32-N33)/30.5 -> 5.0491803 | N33: 46112
B34: Total I-526/I-526E filings April 1, 2022 to March 31, 2026 | L34: Guess monthly demand compared previous 9 months average | M34: 1
C35: Total | D35: Rural | E35: High Unemployment | F35: Infrastructure | G35: Other** | H35: Total | I35: Rural | L35: Rural | M35: High Unemployment
B36: CHINA | C36: =SUM(D36:G36) -> 8580 | D36: ='Post-RIA'!P4 -> 4881 | E36: ='Post-RIA'!Q4 -> 3438 | F36: ='Post-RIA'!R4 -> 0 | G36: ='Post-RIA'!S4 -> 261 | H36: =C36/(C36+C37) -> 0.64931134 | I36: =D36/(D36+D37) -> 0.65728521 | K36: CHINA | L36: =D36+D42/6*$M$33*$M$34 -> 5600.5082 | M36: =E36+E42/6*$M$33*$M$34 -> 3778.8197
B37: INDIA | C37: =SUM(D37:G37) -> 4634 | D37: ='Post-RIA'!P5 -> 2545 | E37: ='Post-RIA'!Q5 -> 1806 | F37: ='Post-RIA'!R5 -> 0 | G37: ='Post-RIA'!S5 -> 283 | H37: =C37/(C37+C36) -> 0.35068866 | I37: =D37/(D37+D36) -> 0.34271479 | K37: INDIA | L37: =D37+D43/6*$M$33*$M$34 -> 3198.0273 | M37: =E37+E43/6*$M$33*$M$34 -> 2164.4918
B38: Rest of World | C38: =SUM(D38:G38) -> 4901 | D38: ='Post-RIA'!P6 -> 1380 | E38: ='Post-RIA'!Q6 -> 2971 | F38: ='Post-RIA'!R6 -> 0 | G38: ='Post-RIA'!S6 -> 550 | K38: Rest of World | L38: =D38+D44/6*$M$33*$M$34 -> 1604.6885 | M38: =E38+E44/6*$M$33*$M$34 -> 3338.7486
B39: Total | C39: =SUM(C36:C38) -> 18115 | D39: =SUM(D36:D38) -> 8806 | E39: =SUM(E36:E38) -> 8215 | F39: =SUM(F36:F38) -> 0 | G39: =SUM(G36:G38) -> 1094 | K39: Total | L39: =SUM(L36:L38) -> 10403.224 | M39: =SUM(M36:M38) -> 9282.0601
D40: =D39/C39 -> 0.48611648 | E40: =E39/C39 -> 0.45349158
B41: I-526/I-526E filings October 2025-March 2026 (6 months) | C41: Total | D41: Rural | E41: High Unemployment | F41: Infrastructure | G41: Other** | K41: CHINA | L41: =L36/M36 -> 1.4820787
B42: CHINA | C42: =SUM(D42:G42) -> 1361 | D42: ='Post-RIA'!P10 -> 855 | E42: ='Post-RIA'!Q10 -> 405 | F42: ='Post-RIA'!R10 -> 0 | G42: ='Post-RIA'!S10 -> 101 | H42: =C42/(C42+C43) -> 0.50314233 | I42: =D42/(D42+D43) -> 0.52421827 | K42: INDIA | L42: =L37/M37 -> 1.4774957
B43: INDIA | C43: =SUM(D43:G43) -> 1344 | D43: ='Post-RIA'!P11 -> 776 | E43: ='Post-RIA'!Q11 -> 426 | F43: ='Post-RIA'!R11 -> 0 | G43: ='Post-RIA'!S11 -> 142 | H43: =C43/(C43+C42) -> 0.49685767 | I43: =D43/(D43+D42) -> 0.47578173 | K43: Rest of World | L43: =L38/M38 -> 0.48062574
B44: Rest of World | C44: =SUM(D44:G44) -> 854 | D44: ='Post-RIA'!P12 -> 267 | E44: ='Post-RIA'!Q12 -> 437 | F44: ='Post-RIA'!R12 -> 0 | G44: ='Post-RIA'!S12 -> 150
B45: Total | C45: =SUM(C42:C44) -> 3559 | D45: =SUM(D42:D44) -> 1898 | E45: =SUM(E42:E44) -> 1268 | F45: =SUM(F42:F44) -> 0 | G45: =SUM(G42:G44) -> 393 | L45: 140 | M45: 70
D46: =D45/C45 -> 0.53329587 | E46: =E45/C45 -> 0.35627985 | F46: =F45/9 -> 0 | G46: =G45/9 -> 43.666667
B47: **Multiple categories, unknown category, or Unreserved
W49: Est visas not used by ROW | X49: 4500
B50: Estimated PIPELINE VISA APPLICANTS with priority dates between April 1, 2022 and March 31, 2026 | P50: TIMING ESTIMATE ASSUMES THAT AVAILABLE VISAS ARE ACTUALLY ISSUED -- which may not happen if the Trump admin is successful!
B51: Key Assumption: Estimate average visa demand per investor | E51: 2 | F51: (considering estimated family & denial/attrition--actual could be higher or lower)
B52: Estimated visa demand from documented investors with priority dates 4/1/2022-3/31/2026 | J52: Estimated visa demand from forecasted data above | M52: =M32 -> 46266 | P52: Estimated unaccomodated (less reserved visas issued 2022-2025) | W52: Rough India Time estimate -- optimistic IF available EB visas issued)
C53: Total | D53: Rural | E53: High Unemployment | F53: Infrastructure | G53: Other** | L53: Rural | M53: High Unemployment | Q53: Rural | R53: High Unemployment | S53: Infrastructure | T53: Unreserved | U53: Total EB-5 | W53: Years | X53: Annual Visas | Y53: All | Z53: Pre-RIA only
B54: CHINA | C54: =SUM(D54:G54) -> 17160 | D54: =D36*$E$51 -> 9762 | E54: =E36*$E$51 -> 6876 | F54: =F36*$E$51 -> 0 | G54: =G36*$E$51 -> 522 | K54: CHINA | L54: =L36*$E$51 -> 11201.016 | M54: =M36*$E$51 -> 7557.6393 | P54: CHINA | Q54: =L54-L25 -> 10020.016 | R54: =M54-M25 -> 7343.6393 | S54: =Summary2!I22 -> 423.2 | T54: =C75 -> 23200 | U54: =SUM(Q54:T54) -> 40986.856 | Y54: =U55 -> 11251.638 | Z54: =T55 -> 1500 | AA54: =Y54/700 -> 16.073769
B55: INDIA | C55: =SUM(D55:G55) -> 9268 | D55: =D37*$E$51 -> 5090 | E55: =E37*$E$51 -> 3612 | F55: =F37*$E$51 -> 0 | G55: =G37*$E$51 -> 566 | K55: INDIA | L55: =L37*$E$51 -> 6396.0546 | M55: =M37*$E$51 -> 4328.9836 | N55: =L55+M55 -> 10725.038 | P55: INDIA | Q55: =L55-L26 -> 5563.0546 | R55: =M55-M26 -> 3976.9836 | S55: =Summary2!L22 -> 211.6 | T55: =C76 -> 1500 | U55: =SUM(Q55:T55) -> 11251.638 | V55: =U55/700 -> 16.073769 | W55: 1 | X55: -1500 | Y55: =W55*X55 -> -1500 | Z55: =X55 -> -1500
B56: Rest of World | C56: =SUM(D56:G56) -> 9802 | D56: =D38*$E$51 -> 2760 | E56: =E38*$E$51 -> 5942 | F56: =F38*$E$51 -> 0 | G56: =G38*$E$51 -> 1100 | K56: Rest of World | L56: =L38*$E$51 -> 3209.377 | M56: =M38*$E$51 -> 6677.4973 | N56: =N55/700 -> 15.321483 | P56: ROW | Q56: =L56-L27 -> 2961.377 | R56: =M56-M27 -> 6292.4973 | S56: =Summary2!O22 -> 423.2 | T56: =C77 -> 900 | U56: =SUM(Q56:T56) -> 10577.074 | W56: 1 | X56: -1300 | Y56: =W56*X56 -> -1300
B57: Total pipeline demand | C57: =SUM(D57:G57) -> 36230 | D57: =SUM(D54:D56) -> 17612 | E57: =SUM(E54:E56) -> 16430 | F57: =SUM(F54:F56) -> 0 | G57: =SUM(G54:G56) -> 2188 | K57: Total Visa Demand to Date | L57: =L39*$E$51 -> 20806.448 | M57: =M39*$E$51 -> 18564.12 | P57: Total | Q57: =SUM(Q54:Q56) -> 18544.448 | R57: =SUM(R54:R56) -> 17613.12 | S57: =SUM(S54:S56) -> 1058 | T57: =SUM(T54:T56) -> 25600 | U57: =SUM(U54:U56) -> 62815.568 | W57: 2 | X57: -800 | Y57: =W57*X57 -> -1600
K58: Est Visas Issued to date | L58: =D29+D28*M33/12 -> 3074.0765 | M58: =E29+E28*M33/12 -> 1312.8579 | R58: =SUM(Q55:S55)/SUM(Q54:S55) -> 0.35410935 | S58: =SUM(Q57:S57) -> 37215.568 | U58: 10000 | W58: 4 | X58: =-X49*R58 -> -1593.4921 | Y58: =W58*X58 -> -6373.9683
B59: Additions to the visa pipeline in the last reported six months | C59: =SUM(D59:G59) -> 7118 | D59: =D45*$E$51 -> 3796 | E59: =E45*$E$51 -> 2536 | F59: =F45*$E$51 -> 0 | G59: =G45*$E$51 -> 786 | K59: Unaccommodated demand | L59: =L57-L58 -> 17732.372 | M59: =M57-M58 -> 17251.262 | W59: =SUM(W55:W58) -> 8 | Y59: =SUM(Y54:Y58) -> 477.66992 | Z59: =SUM(Z54:Z58) -> 0
C60: =C59/6 -> 1186.3333 | D60: =D59/6 -> 632.66667 | E60: =E59/6 -> 422.66667 | P60: Country cap supply | Q60: =Q61*$U$60 -> 140 | R60: =R61*$U$60 -> 70 | S60: =S61*$U$60 -> 14 | T60: =T61*$U$60 -> 476 | U60: 700
B61: Compare Estimated Visa Demand with Typical Annual EB-5 Visa Limits | L61: =L55/(140+300) -> 14.536488 | M61: =(L55+M55)/700 -> 15.321483 | P61: % Supply | Q61: 0.2 | R61: 0.1 | S61: 0.02 | T61: 0.68 | U61: =SUM(Q61:T61) -> 1
B62: Estimated visa demand from investors with priority dates 4/1/2022-12/31/2025 compared with base annual visas available | W62: Rough China Time estimate
C63: Total | D63: Rural | E63: High Unemployment | J63: REFERENCE: Approximate I-485 pending as of 4/3/2026 | P63: China % Demand | Q63: =Q54/$U$54 -> 0.24446902 | R63: =R54/$U$54 -> 0.1791706 | S63: =S54/$U$54 -> 0.010325261 | T63: =T54/$U$54 -> 0.56603512 | W63: Years | X63: Annual Visas | Y63: All | Z63: Pre-RIA only
B64: CHINA | C64: =C54/C8 -> 24.514286 | D64: =D54/D8 -> 69.728571 | E64: =E54/E8 -> 98.228571 | L64: Rural | M64: High Unemployment | N64: Infrastructure | P64: % Supply | Q64: 0.2 | R64: 0.1 | S64: 0.02 | T64: 0.68 | U64: =SUM(Q64:T64) -> 1 | Y64: =U54 -> 40986.856 | Z64: =T54 -> 23200
B65: INDIA | C65: =C55/C9 -> 13.24 | D65: =D55/D9 -> 36.357143 | E65: =E55/E9 -> 51.6 | K65: CHINA | L65: 3571 | M65: 3884 | W65: 1 | X65: -7100 | Y65: =W65*X65 -> -7100 | Z65: -7100
B66: Rest of World | C66: =C56/C10 -> 1.1397674 | D66: =D56/D10 -> 1.6046512 | E66: =E56/E10 -> 6.9093023 | K66: INDIA | L66: 3505 | M66: 2537 | P66: India % Demand | Q66: =Q55/$U$55 -> 0.49442175 | R66: =R55/$U$55 -> 0.35345818 | S66: =S55/$U$55 -> 0.01880615 | T66: =T55/$U$55 -> 0.13331392 | W66: 1 | X66: -8200 | Y66: =W66*X66 -> -8200 | Z66: -8200
B67: Total pipeline demand | C67: =C57/C7 -> 3.623 | D67: =D57/D7 -> 8.806 | E67: =E57/E7 -> 16.43 | K67: Rest of World | L67: 512 | M67: 1702 | P67: % Supply | Q67: 0.2 | R67: 0.1 | S67: 0.02 | T67: 0.68 | U67: =SUM(Q67:T67) -> 1 | W67: 1 | X67: -5000 | Y67: =W67*X67 -> -5000 | Z67: -5000
K68: Total | L68: =SUM(L65:L67) -> 7588 | M68: =SUM(M65:M67) -> 8123 | W68: 6.6 | X68: =-X49*(1-R58) -> -2906.5079 | Y68: =W68*X68 -> -19182.952 | Z68: -2900
B69: Additions to the visa pipeline in the last reported six months | C69: =C59/C7 -> 0.7118 | D69: =D59/D7 -> 1.898 | E69: =E59/E7 -> 2.536 | L69: =L68/D57 -> 0.43084261 | M69: =M68/E57 -> 0.49440049 | W69: =SUM(W64:W68) -> 9.6 | Y69: =SUM(Y64:Y68) -> 1503.9035 | Z69: =SUM(Z64:Z68) -> 0
B71: VISA APPLICANTS with priority dates before April 1, 2022
B72: Estimated pre-RIA applicants recorded as of 5/2024 who don't have visas yet at FY2026 start | J72: Estimated visa demand from forecasted date above compared with base annual visas available
C73: ESTIMATE (see the Unreserved page for calculation) | L73: Rural | M73: High Unemployment
C74: Unreserved | J74: CHINA | L74: =L54/D8 -> 80.00726 | M74: =M54/E8 -> 107.96628
B75: CHINA | C75: =Unreserved!C15 -> 23200 | J75: INDIA | L75: =L55/D9 -> 45.686105 | M75: =M55/E9 -> 61.842623
B76: INDIA | C76: =Unreserved!D15 -> 1500 | J76: Rest of World | L76: =L56/D10 -> 1.8659169 | M76: =M56/E10 -> 7.7645317
B77: Rest of World | C77: =Unreserved!E15 -> 900 | J77: Total pipeline | L77: =L57/D7 -> 10.403224 | M77: =M57/E7 -> 18.56412
B78: Total | C78: =SUM(C75:C77) -> 25600
J79: (if with extra rollover visas) | L79: =L57/D12 -> 6.9354827 | M79: =M57/E12 -> 12.37608

Sheet Summary2
B1: Estimated EB-5 Set-Aside Visa Backlog Size and Progress as of March 2026
D3: All Countries | G3: China | J3: India | M3: Rest of World
D4: Rural | E4: High Unemployment | F4: Infra-structure | G4: Rural | H4: High Unemployment | I4: Infra-structure | J4: Rural | K4: High Unemployment | L4: Infra-structure | M4: Rural | N4: High Unemployment | O4: Infra-structure
C5: USCIS data for I-526/I-526E (AIIA FOIA)
C6: (data from USCIS via AIIA FOIA)
C7: Total April 2022 to July 2025
B8: A | C8: I-526/I-526E Receipts Apr-2022 to Jul-2025 | D8: 6406 | E8: 6582 | F8: 0 | G8: 3845 | H8: 2926 | I8: 0 | J8: 1636 | K8: 1264 | L8: 0 | M8: 925 | N8: 2392 | O8: 0
B9: B | C9: I-526/I-526E Approvals Apr-2022 to Jul-2025 | D9: 2819 | E9: 545 | F9: 0 | G9: 1663 | H9: 98 | I9: 0 | J9: 725 | K9: 217 | L9: 0 | M9: 431 | N9: 230 | O9: 0
B10: C | C10: I-526/I-526E Denials Apr-2022 to Jul-2025 | D10: 62 | E10: 13 | F10: 0 | G10: 46 | H10: 6 | I10: 0 | J10: 5 | K10: 1 | L10: 0 | M10: 11 | N10: 6 | O10: 0
C11: Recent trend (previous reported 7 months)
B12: A.2⊂A | C12: I-526/I-526E Receipts Jan-2025 to Jul-2025 | D12: 2398 | E12: 1628 | F12: 0 | G12: 1269 | H12: 664 | I12: 0 | J12: 841 | K12: 415 | L12: 0 | M12: 288 | N12: 549 | O12: 0
B13: B.2⊂B | C13: I-526/I-526E Approvals Jan-2025 to Jul-2025 | D13: 1693 | E13: 194 | F13: 0 | G13: 934 | H13: 19 | I13: 0 | J13: 477 | K13: 105 | L13: 0 | M13: 282 | N13: 70 | O13: 0
C14: Estimated recent changes
C15: (Rural & HUA guess based on previous 7 months; Infra rough guess from project info online)
B16: D≈A.2 | C16: Estimated receipts Aug-25 to Feb-26 | D16: =ROUND(D12,-1) -> 2400 | E16: =ROUND(E12,-1) -> 1630 | F16: =Infra!M34 -> 529 | G16: =ROUND(G12,-1) -> 1270 | H16: =ROUND(H12,-1) -> 660 | I16: =Infra!M31 -> 211.6 | J16: =ROUND(J12,-1) -> 840 | K16: =ROUND(K12,-1) -> 420 | L16: =Infra!M32 -> 105.8 | M16: =ROUND(M12,-1) -> 290 | N16: =ROUND(N12,-1) -> 550 | O16: =Infra!M33 -> 211.6
B17: E≈B.2 | C17: Estimated approvals Aug-25 to Feb-26 | D17: =ROUND(D13,-1) -> 1690 | E17: =ROUND(E13,-1) -> 190 | F17: =Infra!N34 -> 130 | G17: =ROUND(G13,-1) -> 930 | H17: =ROUND(H13,-1) -> 20 | I17: =Infra!N31 -> 30 | J17: =ROUND(J13,-1) -> 480 | K17: =ROUND(K13,-1) -> 110 | L17: =Infra!N32 -> 20 | M17: =ROUND(M13,-1) -> 280 | N17: =ROUND(N13,-1) -> 70 | O17: =Infra!N33 -> 80
C18: Estimated total I-526/I-526E (rounded)
B19: F=A+D | C19: Estimated total receipts by March 2026 | D19: =ROUND(D8,-2)+D16 -> 8800 | E19: =ROUND(E8,-2)+E16 -> 8230 | F19: =ROUND(F8,-2)+F16 -> 529 | G19: =ROUND(G8,-2)+G16 -> 5070 | H19: =ROUND(H8,-2)+H16 -> 3560 | I19: =ROUND(I8,-2)+I16 -> 211.6 | J19: =ROUND(J8,-2)+J16 -> 2440 | K19: =ROUND(K8,-2)+K16 -> 1720 | ... O19: =ROUND(O8,-2)+O16 -> 211.6
B20: G=B+E | C20: Estimated total approvals by March 2026 | D20: =ROUND(D9,-2)+D17 -> 4490 | E20: =ROUND(E9,-2)+E17 -> 690 | F20: =ROUND(F9,-2)+F17 -> 130 | G20: =ROUND(G9,-2)+G17 -> 2630 | H20: =ROUND(H9,-2)+H17 -> 120 | I20: =ROUND(I9,-2)+I17 -> 30 | J20: =ROUND(J9,-2)+J17 -> 1180 | K20: =ROUND(K9,-2)+K17 -> 310 | ... O20: =ROUND(O9,-2)+O17 -> 80
C21: Estimated visa applicants up to March 2026
B22: H=(F-C)*2 | C22: Pipeline visa applicants | D22: =D19*2 -> 17600 | E22: =E19*2 -> 16460 | F22: =F19*2 -> 1058 | G22: =G19*2 -> 10140 | H22: =H19*2 -> 7120 | I22: =I19*2 -> 423.2 | J22: =J19*2 -> 4880 | K22: =K19*2 -> 3440 | ... O22: =O19*2 -> 423.2
B23: I=G*2 | C23: Qualified visa applicants | D23: =D20*2 -> 8980 | E23: =E20*2 -> 1380 | F23: =F20*2 -> 260 | G23: =G20*2 -> 5260 | H23: =H20*2 -> 240 | I23: =I20*2 -> 60 | J23: =J20*2 -> 2360 | K23: =K20*2 -> 620 | ... O23: =O20*2 -> 160
C24: Estimated visa issuance
C25: (assuming even trend since last 2025 data report)
B26: J | C26: Estimated visas issued 2022 to Oct 2025 | D26: =D56 -> 2300 | E26: =E56 -> 1000 | F26: =F56 -> 0 | I26: =I56 -> 0 | L26: =L56 -> 0 | O26: =O56 -> 0
B27: K | C27: Estimated visas issued 2022 to Feb 2026 | D27: =D57 -> 3100 | E27: =E57 -> 1400 | F27: =F57 -> 0 | I27: =I57 -> 0 | L27: =L57 -> 0 | O27: =O57 -> 0
C28: Estimated status as of March 2026
B29: L=H-K | C29: Est. pipeline applicants without visas as of Mar 26 | D29: =D22-D26 -> 15300 | E29: =E22-E26 -> 15460 | F29: =F22-F26 -> 1058 | G29: =G22-G26 -> 10140 | H29: =H22-H26 -> 7120 | I29: =I22-I26 -> 423.2 | J29: =J22-J26 -> 4880 | K29: =K22-K26 -> 3440 | ... O29: =O22-O26 -> 423.2
B30: M=I-J | C30: Est. qualified applicants without visas as of Oct 25 | D30: =D23-D26 -> 6680 | E30: =E23-E26 -> 380 | F30: =F23-F26 -> 260 | G30: =G23-G26 -> 5260 | H30: =H23-H26 -> 240 | I30: =I23-I26 -> 60 | J30: =J23-J26 -> 2360 | K30: =K23-K26 -> 620 | ... O30: =O23-O26 -> 160
C31: Visa Supply
B32: N | C32: Average annual set-aside visas (7% min or 86% max) | D32: 2000 | E32: 1000 | F32: 200 | G32: =D32*0.07 -> 140 | H32: =E32*0.07 -> 70 | I32: =$F$32*0.07 -> 14 | J32: =D32*0.07 -> 140 | K32: =E32*0.07 -> 70 | L32: =$F$32*0.07 -> 14 | M32: =D32-G32-J32 -> 1720 | N32: =E32-H32-K32 -> 860 | O32: =F32-I32-L32 -> 172
B33: O | C33: Estimated FY2026 visas | D33: 4000 | E33: 2000 | F33: 400
C34: Compare Demand with Supply
B35: P=L/N | C35: Compare pipeline applicants without visas with average annual visas | D35: =D29/D32 -> 7.65 | E35: =E29/E32 -> 15.46 | F35: =F29/F32 -> 5.29 | G35: =G29/G32 -> 72.428571 | H35: =H29/H32 -> 101.71429 | I35: =I29/I32 -> 30.228571 | J35: =J29/J32 -> 34.857143 | K35: =K29/K32 -> 49.142857 | ... O35: =O29/O32 -> 2.4604651
B36: Q=M/O | C36: Compare qualified applicants with FY2026 visas | D36: =D30/D33 -> 1.67 | E36: =E30/E33 -> 0.19 | F36: =F30/F33 -> 0.65
D38: All Countries | G38: China | J38: India | M38: Rest of World
C39: Compare Pre-RIA Unreserved Backlog
C40: Est. qualified applicants without visas as of Mar 26 | D40: =G40+J40+M40 -> 21800 | G40: =Unreserved!L15 -> 20200 | J40: =Unreserved!M15 -> 1100 | M40: =Unreserved!N15 -> 500
C42: Estimated total applicants without visas yet as of March 2026, Pre-RIA and Post-RIA | D42: =D40+(D29+E29+F29) -> 53618 | G42: =G40+(G29+H29+I29) -> 37883.2 | J42: =J40+(J29+K29+L29) -> 9631.6 | M42: =M40+(M29+N29+O29) -> 9203.2
B44: Sources:
B45: I-526/I-526E data to July 2025 from USCIS via FOIA requests by AIIA https://goaiia.org/blog/aiia-foia-series-updated-i-526e-inventory-statistics-for-july-2025/#
B46: Note that the estimate for I-526/I-526E filings and approvals since the last reported data is a guess -- welcome to replace with your guesses.
B47: Infrastructure demand guess for 2025 from Internet search -- see Infra tab for detail. Note that the division by country is a guess -- welcome to replace with your guesses.
B48: Visa estimate based on official data through 2024 and partial 2025 date -- see Progress tab for detail
C51: Visa Estimate Detail | D51: All Countries | G51: China | J51: India | M51: Rest of World
D52: Rural | E52: High Unemployment | F52: Infra-structure | G52: Rural | H52: High Unemployment | I52: Infra-structure | J52: Rural | K52: High Unemployment | L52: Infra-structure | M52: Rural | N52: High Unemployment | O52: Infra-structure
C53: Actual visas issued FY22-FY24 | D53: 332 | E53: 91 | F53: 0 | G53: 201 | H53: 34 | J53: 93 | K53: 12 | M53: =D53-G53-J53 -> 38 | N53: =E53-H53-K53 -> 45
C54: Estimated visas issued FY25 | D54: =Progress!J120 -> 1930 | E54: =Progress!J128 -> 860 | F54: 0 | G54: =Progress!J117 -> 980 | H54: =Progress!J125 -> 180 | J54: =Progress!J118 -> 740 | K54: =Progress!J126 -> 340 | M54: =D54-G54-J54 -> 210 | N54: =E54-H54-K54 -> 340
C55: Estmated visas issued FY26 to date (Oct-Feb) | D55: 800 | E55: 400 | F55: 0 | G55: =G54*5/12 -> 408.33333 | H55: =H54*5/12 -> 75 | J55: =J54*5/12 -> 308.33333 | K55: =K54*5/12 -> 141.66667 | M55: =D55-G55-J55 -> 83.333333 | N55: =E55-H55-K55 -> 183.33333
C56: Esimated total visas issued before Oct 2025 | D56: =ROUNDUP(D53+D54,-2) -> 2300 | E56: =ROUNDUP(E53+E54,-2) -> 1000 | F56: =ROUNDUP(F53+F54,-2) -> 0 | G56: =ROUNDUP(G53+G54,-2) -> 1200 | H56: =ROUNDUP(H53+H54,-2) -> 300 | J56: =ROUNDUP(J53+J54,-2) -> 900 | K56: =ROUNDUP(K53+K54,-2) -> 400 | M56: =D56-G56-J56 -> 200 | N56: =E56-H56-K56 -> 300
C57: Esimated total visas issued before Mar 2026 | D57: =ROUNDUP(D54+D55+D53,-2) -> 3100 | E57: =ROUNDUP(E54+E55+E53,-2) -> 1400 | F57: =ROUNDUP(F54+F55+F53,-2) -> 0 | G57: =ROUNDUP(G54+G55+G53,-2) -> 1600 | H57: =ROUNDUP(H54+H55+H53,-2) -> 300 | J57: =ROUNDUP(J54+J55+J53,-2) -> 1200 | K57: =ROUNDUP(K54+K55+K53,-2) -> 500 | M57: =D57-G57-J57 -> 300 | N57: =E57-H57-K57 -> 600
C59: Chart Summary
D60: Applicants | E60: Annual Visas
C61: Pre-RIA applicant pipeline estimate (Unreserved only) as of March 2026 | D61: =D40 -> 21800
C62: Unreserved visa supply (typical annual) | E62: 6800
C63: Post-RIA pipeline applicant estimate (mostly set-aside investors) as of March 2026 | D63: =SUM(D29:F29) -> 31818
C64: Set-Aside visa supply (typical annual) | E64: 3200
D65: =SUM(D61:D64) -> 53618 | E65: =SUM(E61:E64) -> 10000

Sheet Unreserved
B1: Pre-RIA Unreserved Backlog
B2: Available Data for Pre-RIA Unreserved Backlog (sources copied below)
C3: China Unreserved | F3: India Unreserved | I3: ROW Unreserved
B4: Data as of Date | C4: NVC waitlist registered applicants | D4: I-485 pending | E4: I-526 pending | F4: NVC waitlist registered applicants | G4: I-485 pending | H4: I-526 pending | I4: NVC waitlist registered applicants | J4: I-485 pending | K4: I-526 pending
C5: applicants | D5: applicants | E5: investors only | F5: applicants | G5: applicants | H5: investors only | I5: applicants | J5: applicants | K5: investors only
B6: as of 5/2024 | C6: 31255 | D6: 2571 | E6: 2974 | F6: 2541 | G6: 953 | H6: 473 | I6: 5774 | J6: 1367 | K6: 1049
B7: as of 10/2025 | C7: ? | D7: 4483 | E7: ? | F7: ? | G7: 721 | H7: ? | I7: ? | J7: 200 | K7: ?
B9: Estimated total pre-RIA Unreserved Backlog, and Backlog Progress | P9: Unreserved China VISA DEMAND ESTIMATE as of June 2024 | U9: Unreserved India VISA DEMAND ESTIMATE as of June 2024
C10: China Pre-RIA Unreserved | D10: India Pre-RIA Unreserved | E10: ROW Pre-RIA Unreserved | F10: Post-RIA Unreserved | G10: Total | H10: Refrence total on Supply tab Scenario 1 assuming large FB rollovers from visa blocks | J10: Refrence total on Supply tab Scenario 2 (minimal extra EB visas)
B11: Estimated total backlog as of May 2024 (estimated from data cited above, including assumptions about denials, attrition, and double counting) | C11: =(C6+D6*0.5+E6*0.5*2.5)*0.85 -> 30819.3 | D11: =(F6+G6*0.5+H6*0.7*2)*0.85 -> 3127.745 | E11: =(I6+J6*0.8+K6*0.7*2.5)*0.85 -> 7397.8475 | G11: =SUM(C11:E11) -> 41344.893 | P11: Priority Date | Q11: I-526 Filed (actual until 10/2020, estimate for 2021-2022) | R11: I-526 Pending as of 7/2024 (actual) | S11: Applicants registered at NVC as of 5/2024 (quarterly estimate from actual annual) | T11: I-485 Pending as of 6/2024 (actual) | U11: Priority Date | V11: I-526 Filed (actual) | W11: I-526 Pending as of 7/2024 (actual) | X11: Applicants registered at NVC as of 5/2024 (quarterly estimate from actual annual) | Y11: I-485 Pending as of 6/2024 (actual)
C12: China Unreserved | D12: India Unreserved | E12: ROW Unreserved | P12: Pre-2015 | R12: 6 | S12: 588 | T12: 0 | U12: Pre-FY2017 | W12: 0 | X12: 51
B13: Estimated visas issued in last 4 months of FY2024 | C13: =-Progress!D151*4/12 -> -3104 | D13: =-Progress!E151*4/12 -> -441 | E13: =-Progress!F151*4/12 -> -1288.6667 | G13: =SUM(C13:E13) -> -4833.6667 | H13: ='Visa Supply'!E67 -> 14207.109 | P13: 2015 Q1. Oct - Dec 2014 | Q13: 2783.0277 | R13: 1 | T13: 0 | U13: 2017 Q2. Jan - Mar 2017 | V13: 42 | W13: 0 | X13: 6.784217
B14: Estimated visas issued in FY2025 | C14: =-ROUNDUP(Progress!L106,-2) -> -4500 | D14: =-ROUNDUP(Progress!L107,-2) -> -1100 | E14: =-ROUNDUP(Progress!L108,-2) -> -5200 | G14: =SUM(C14:E14) -> -10800 | H14: ='Visa Supply'!F64 -> 11298.694 | P14: 2015 Q2. Jan - Mar 2015 | Q14: 2184.9748 | R14: 1 | S14: 1286.518 | T14: 0 | U14: 2017 Q3. April - June 2017 | V14: 261 | W14: 1 | X14: 42.159063
B15: Estimated pre-RIA applicants recorded as of 5/2024 who don't have visas yet at FY2026 start | C15: =ROUNDDOWN(C11+SUM(C13:C14),-2) -> 23200 | D15: =ROUNDDOWN(D11+SUM(D13:D14),-2) -> 1500 | E15: =ROUNDDOWN(E11+SUM(E13:E14),-2) -> 900 | G15: =SUM(C15:E15) -> 25600 | K15: Est as of 3/2026 | L15: =ROUND(C15+C16*5/12,-2) -> 20200 | M15: =ROUND(D15+D16*5/12,-2) -> 1100 | N15: =ROUND(E15+E16*5/12,-2) -> 500 | P15: 2015 Q3 Apr - Jun 2015 | Q15: 2340.1658 | R15: 3 | S15: 1377.8948 | T15: 14 | U15: 2017 Q4 Jul - Sep 2017 | V15: 127 | W15: 0 | X15: 20.51418
B16: Estimated visas issued FY2026 (optimistic assuming carryover and rollover from unused FB) | C16: -7100 | D16: -1000 | E16: -900 | G16: =SUM(C16:F16) -> -9000 | H16: ='Visa Supply'!G64 -> 9655.9715 | I16: =H16*0.07 -> 675.91801 | J16: ='Visa Supply'!R17 -> 9671.6142 | P16: 2015 Q4 Jul - Sep 2015 | Q16: 6221.8317 | R16: 28 | S16: 3663.4283 | T16: 89 | U16: 2018 Q1 Oct - Dec 2017 | V16: 381 | W16: 1 | X16: 61.54254
B17: Estimated visas issued FY2027 (optimistic assuming carryover and rollover from unused FB) | C17: -8200 | D17: -500 | F17: -1000 | G17: =SUM(C17:F17) -> -9700 | H17: ='Visa Supply'!H64 -> 9964.8406 | I17: =H17*0.07 -> 697.53884 | J17: ='Visa Supply'!S17 -> 7242 | P17: 2016 Q1 Oct - Dec 2015 | Q17: 3808 | R17: 33 | S17: 2242.1589 | T17: 118 | U17: 2018 Q2. Jan - Mar 2018 | V17: 283 | W17: 0 | X17: 179.41674
B18: FY2028 estimate (optimistic assuming rollover from unused FB) | C18: -5000 | F18: -4500 | G18: =SUM(C18:F18) -> -9500 | H18: ='Visa Supply'!I17 -> 9656 | I18: =H18*0.07 -> 675.92 | J18: ='Visa Supply'!T17 -> 6759.2 | P18: 2016 Q2 Jan - Mar 2016 | Q18: 391 | R18: 4 | S18: 545.90335 | T18: 98 | U18: 2018 Q3. April - June 2018 | V18: 127 | W18: 0 | X18: 80.515638
B19: FY2029 estimate | C19: -2900 | F19: -4500 | G19: =SUM(C19:F19) -> -7400 | H19: ='Visa Supply'!J17 -> 6759.2 | I19: =H19*0.07 -> 473.144 | J19: ='Visa Supply'!T17 -> 6759.2 | P19: 2016 Q3 April - June 2016 | Q19: 1415 | R19: 20 | S19: 1975.5837 | T19: 332 | U19: 2018 Q4 Jul - Sep 2018 | V19: 330 | W19: 3 | X19: 209.21386
B20: FY2030 estimate | G20: =SUM(C20:F20) -> 0 | P20: 2016 Q4 Jul - Sep 2016 | Q20: 5334 | R20: 79 | S20: 7447.1828 | T20: 1165 | U20: 2019 Q1 Oct - Dec 2018 | V20: 443 | W20: 1 | X20: 280.85376 | Y20: 45
B21: FY2031 estimate | P21: 2017 Q1 Oct - Dec 2016 | Q21: 3310 | R21: 87 | S21: 4621.3301 | T21: 782 | U21: 2019 Q2. Jan - Mar 2019 | V21: 155 | W21: 7 | X21: 93.769282 | Y21: 23
P22: 2017 Q2. Jan - Mar 2017 | Q22: 1172 | R22: 94 | S22: 1198.9144 | T22: 0 | U22: 2019 Q3. April - June 2019 | V22: 180 | W22: 3 | X22: 108.89336 | Y22: 44
B23: Balance of pre-RIA applicants | C23: =SUM(C15:C22) -> 0 | D23: =SUM(D15:D22) -> 0 | E23: =SUM(E15:E22) -> 0 | P23: 2017 Q3. April - June 2017 | Q23: 3280 | R23: 430 | S23: 3355.3236 | T23: 0 | U23: 2019 Q4 Jul - Sep 2019 | V23: 249 | W23: 9 | X23: 150.63581 | Y23: 99
B24: Estimated years from FY2026 to clear the Pre-RIA backlog | C24: =COUNTA(C16:C20) -> 4 | D24: =COUNTA(D16:D20) -> 2 | E24: =COUNTA(E16:E20) -> 1 | P24: 2017 Q4 Jul - Sep 2017 | Q24: 1009 | R24: 243 | S24: 1032.1712 | T24: 0 | U24: 2020 Q1 Oct - Dec 2019 | V24: 907 | W24: 153 | X24: 548.70154 | Y24: 404
P25: 2018 Q1 Oct - Dec 2017 | Q25: 1245 | R25: 326 | S25: 1273.5908 | T25: 0 | U25: 2020 Q2 Jan - Mar 2020 | V25: 6 | W25: 3 | X25: 0 | Y25: 0
C26: =SUM(C13:C14) -> -7604 | D26: =SUM(D13:D14) -> -1541 | E26: =SUM(E13:E14) -> -6488.6667 | G26: =SUM(G13:G14) -> -15633.667 | P26: 2018 Q2. Jan - Mar 2018 | Q26: 696 | R26: 358 | S26: 302 | T26: 0 | U26: 2020 Q3 Apr - Jun 2020 | V26: 11 | W26: 0 | X26: 2 | Y26: 0
B27: Data Sources | C27: https://www.uscis.gov/sites/default/files/document/data/eb_inventory_october_2025.xlsx | P27: 2018 Q3. April - June 2018 | Q27: 207 | R27: 154 | S27: 89.818966 | T27: 0 | U27: 2020 Q4 Jul - Sep 2020 | V27: 11 | W27: 2 | X27: 2 | Y27: 0
C28: https://www.uscis.gov/sites/default/files/document/reports/eb_inventory_may_2024_081324.xlsx | P28: 2018 Q4 Jul - Sep 2018 | Q28: 294 | R28: 277 | S28: 127.56897 | T28: 0 | U28: 2021 Q1 Oct - Dec 2020 | V28: 10 | W28: 2 | X28: 0 | Y28: 0
C29: https://iiusa.org/wp-content/uploads/2024/06/Insights-from-DOS-Recap-of-2024-IIUSA-EB-5-Forum-1.pdf | P29: 2019 Q1 Oct - Dec 2018 | Q29: 195 | R29: 144 | S29: 84.612069 | T29: 0 | U29: 2021 Q2 Jan - Mar 2021 | V29: 22 | W29: 6 | X29: 0 | Y29: 0
C30: https://goaiia.org/aiia-foia-series-pre-ria-i-526-data-as-of-july-2024/ | P30: 2019 Q2. Jan - Mar 2019 | Q30: 118 | R30: 99 | S30: 0 | T30: 0 | U30: 2021 Q3 Apr - Jun 2021 | V30: 180 | W30: 90 | X30: 44 | Y30: 94
C31: Report of the Visa Office 2024, and monthly visa issuance data through May 2025 | P31: 2019 Q3. April - June 2019 | Q31: 91 | R31: 80 | S31: 0 | T31: 0 | U31: 2021 Q4 Jul - Sep 2021 | V31: 37 | W31: 19 | X31: 0 | Y31: 22
C32: https://travel.state.gov/content/travel/en/legal/visa-law0/visa-statistics/ | P32: 2019 Q4 Jul - Sep 2019 | Q32: 118 | R32: 97 | S32: 0 | T32: 0 | U32: 2022 Q1 Oct - Dec 2021 | V32: 70 | W32: 25 | X32: 0 | Y32: 69
P33: 2020 Q1 Oct - Dec 2019 | Q33: 416 | R33: 369 | S33: 31 | T33: 0 | U33: 2022 Q2 Jan - Mar 2022 | V33: 195 | W33: 148 | Y33: 160
P34: 2020 Q2 Jan - Mar 2020 | Q34: 3 | R34: 2 | S34: 0 | T34: 0 | V34: =SUM(V12:V33) -> 4027 | W34: =SUM(W12:W33) -> 473 | X34: =SUM(X12:X33) -> 1882 | Y34: =SUM(Y12:Y33) -> 960
P35: 2020 Q3 Apr - Jun 2020 | Q35: 2 | R35: 2 | S35: 0 | T35: 0
P36: 2020 Q4 Jul - Sep 2020 | Q36: 7 | R36: 6 | S36: 0 | T36: 0
P37: 2021 Q1 Oct - Dec 2020 | Q37: =R37 -> 7 | R37: 7 | S37: 0 | T37: 0
P38: 2021 Q2 Jan - Mar 2021 | Q38: =R38 -> 6 | R38: 6 | S38: 0 | T38: 0
P39: 2021 Q3 Apr - Jun 2021 | Q39: =R39 -> 9 | R39: 9 | S39: 0 | T39: 0
P40: 2021 Q4 Jul - Sep 2021 | Q40: =R40 -> 0 | R40: 0 | S40: 0 | T40: 0
P41: 2022 Q1 Oct - Dec 2021 | Q41: =R41 -> 1 | R41: 1 | S41: 0 | T41: 0
P42: 2022 Q2 Jan - Mar 2022 | Q42: =R42 -> 8 | R42: 8 | T42: 0
S43: =SUM(S12:S42) -> 31243 | T43: =SUM(T12:T42) -> 2598
P45: Sources
P46: NVC applicants | Q46: https://iiusa.org/wp-content/uploads/2024/06/Insights-from-DOS-Recap-of-2024-IIUSA-EB-5-Forum-1.pdf
P47: I-485 pending | Q47: https://www.uscis.gov/sites/default/files/document/reports/eb_inventory_june_2024_081324.xlsx
P48: I-526 pending | Q48: https://goaiia.org/aiia-foia-series-pre-ria-i-526-data-as-of-july-2024/
P49: I-526 receipts | Q49: Multiple sources. See the Pre-RIA tab in my Key EB-5 Backlog data file https://www.dropbox.com/s/ua9g9iigru2z6u1/Key%20EB5%20Backlog%20Data.xlsx?dl=0
P52: History reference for number of EB-5 visas issued to Rest of World Countries
P53: Fiscal Year | Q53: China Visas Issued | R53: Total EB-5 visas issued | S53: ROW Visas Issued | T53: ROW applicants on NVC Wait List at FY start | U53: Difference between qualified applicants and visas issued | V53: ROW visas % Total visas
P54: FY2015 | Q54: 8156 | R54: 9764 | S54: 1497 | T54: 1832 | U54: =T54-S54 -> 335 | V54: =S54/R54 -> 0.15331831 | W54: Actual
P55: FY2016 | Q55: 7516 | R55: 9947 | S55: 2282 | T55: 1719 | U55: =T55-S55 -> -563 | V55: =S55/R55 -> 0.2294159 | W55: Actual
P56: FY2017 | Q56: 7567 | R56: 10090 | S56: 2349 | T56: 3227 | U56: =T56-S56 -> 878 | V56: =S56/R56 -> 0.23280476 | W56: Actual
P57: FY2018 | Q57: 4642 | R57: 9602 | S57: 4375 | T57: 4503 | U57: =T57-S57 -> 128 | V57: =S57/R57 -> 0.45563424 | W57: Actual
P58: FY2019 | Q58: 4327 | R58: 9478 | S58: 4391 | T58: 3362 | U58: =T58-S58 -> -1029 | V58: =S58/R58 -> 0.46328339 | W58: Actual
P59: FY2020 | Q59: 1686 | R59: 3596 | S59: 1454 | T59: 4420 | U59: =T59-S59 -> 2966 | V59: =S59/R59 -> 0.40433815 | W59: Actual
P60: FY2021 | Q60: 1567 | R60: 2949 | S60: 1171 | T60: 6050 | U60: =T60-S60 -> 4879 | V60: =S60/R60 -> 0.39708376 | W60: Actual
P61: FY2022 | Q61: 6125 | R61: 10885 | S61: 3379 | T61: 5262 | U61: =T61-S61 -> 1883 | V61: =S61/R61 -> 0.31042719 | W61: Actual
P62: FY2023 | Q62: 6262 | R62: 9817 | S62: 2740 | T62: 4555 | U62: =T62-S62 -> 1815 | V62: =S62/R62 -> 0.27910767 | W62: Actual
P63: FY2024 | Q63: 9312 | R63: 14501 | S63: 3866 | T63: 6129 | U63: =T63-S63 -> 2263 | V63: =S63/R63 -> 0.2666023 | W63: Actual
P64: FY2025 est | Q64: 6000 | R64: 11470 | S64: 4500 | V64: =S64/R64 -> 0.39232781

Sheet Infra
B1: Infrastructure
D2: China | E2: India | F2: ROW | G2: Total
B3: Base annual infrastructure visa supply | D3: (min) | E3: (min) | F3: (max) | G3: 10000
C4: Normal Year | D4: =G4*0.07 -> 14 | E4: =G4*0.07 -> 14 | F4: =G4-E4-D4 -> 172 | G4: =G3*H4 -> 200 | H4: 0.02
C5: Carryover Year | D5: =G5*0.07 -> 28 | E5: =G5*0.07 -> 28 | F5: =G5-E5-D5 -> 344 | G5: =G4*2 -> 400
B6: Infrastructure demand reported by USCIS
C7: https://www.uscis.gov/tools/reports-and-studies/immigration-and-citizenship-data
D8: China | E8: India | F8: ROW | G8: Total
C9: Infrastructure I-526E filed through 12/31/2025 | D9: 0 reported | E9: 0 reported | F9: 0 reported
C10: Infrastructure I-485 pending as of 5/3/2025 | D10: =J47*10 -> 40 | E10: =J51*10 -> 60 | F10: =J61*10 -> 120 | G10: =SUM(D10:F10) -> 220
C11: Infrastructure I-485 pending as of 4/3/2026 | D11: < 40 | E11: <190 | F11: < 80 | G11: <310
B13: Infrastructure Projects | D13: (from Internet research and personal communication as of February 2026-- email suzanne@lucidtext.com with any updates and additions)
C14: Regional Center | D14: Project | E14: Categories | F14: I-956F approval status | G14: When fundraising | H14: EB-5 Investor Slots | I14: I-526E subscription status | J14: guess at slots filled by 2/2026 | K14: I-526E approvals? | L14: Link 1 | M14: Link 2 | N14: Link 3
C15: American Lending Center | D15: UAB Medical West Hospital | E15: infra only | F15: 45597 | G15: early 2025 | H15: =88/8 -> 11 | I15: full | J15: =88/8 -> 11 | L15: https://usa-rc.com/press-release/american-lending-center-wins-certification-of-public-infrastructure-projects-for-visa-set-asides/ | M15: https://usa-rc.com/portfolio/no-84-medical-west-hospital/
C16: American Lending Center | D16: Samaritan Hospital | E16: infra only | F16: 45597 | G16: early 2025 | H16: =40/8 -> 5 | I16: full | J16: =40/8 -> 5 | L16: https://usa-rc.com/press-release/american-lending-center-wins-certification-of-public-infrastructure-projects-for-visa-set-asides/ | M16: https://usa-rc.com/portfolio/no-97-samaritan-public-hospital/
C17: American Lending Center | D17: No. 98 Harrison Hospital Infrastructure | E17: infra only | F17: 45627 | G17: early 2025 | H17: =104/8 -> 13 | I17: full | J17: =104/8 -> 13 | L17: https://www.businesswire.com/news/home/20241210605558/en/ALCs-Flexible-Financing-Approach-For-Rural-Hospital-Gets-Federal-Approval | M17: https://usa-rc.com/portfolio/no-98-harrison-county-community-hospital/
C18: Boston Regional Center | D18: Boston Suffolk Downs Redevelopment Project (US National Infrastructure Development Fund 2, LLC) | E18: Infrastructure & HUA | F18: 45674 | G18: 2024-2025 | H18: 57 | I18: Full | J18: 57 | K18: Yes | L18: https://www.sec.gov/Archives/edgar/data/2043439/000168316824007960/xslFormDX01/primary_doc.xml | M18: https://echelonseaport.com/ | N18: https://www.eb5-project.com/sfdowns | O18: http://www.e-min.co.kr/iminnews2020-2.asp?mnu_code=001&board_code=001&b_serl=5631
C19: New England Regional Center | D19: Boston Bunker Hill Public Housing Redevelopment (US National Infrastructure Development Fund 4, LLC) | E19: Infrastructure Only | F19: Sept-2025 | G19: 2025-2026 | H19: 127 | J19: 127 | K19: Yes | L19: https://www.eb5-project.com/bunkerhill | M19: http://www.e-min.co.kr/iminnews2020-2.asp?mnu_code=001&board_code=001&b_serl=5609 | N19: https://mp.weixin.qq.com/s/rJpO_SZq9p3CAfj9eB_rHA
C20: New England Regional Center | D20: Boston Bunker Hill Public Housing Redevelopment (US National Infrastructure Development Fund 5, LLC) | E20: Infrastructure Only | G20: 2026 | H20: 312 | J20: 150 | L20: https://www.eb5-project.com/bunkerhill2
C21: Behring | D21: Community Investment for Veterans’ Infrastructure and Care (“CIVIC”) Project | E21: infra & HUA | F21: 45838 | G21: late 2025 | H21: 32 | I21: full | J21: 32 | K21: 7 as of 11/2025 | L21: https://behringeb5.com/civic-eb5-project-956f-approved-infrastructure-designation/ | M21: https://behringeb5.com/civic-i526e-approvals/
C22: Behring | D22: CIVIC amendment | E22: infra & HUA | F22: 46129 | G22: 2026 | H22: =52-32 -> 20 | L22: https://behringeb5.com/uscis-approves-i956f-amendment-civic-1950-franklin/
C23: EB5 Group | D23: Brainerd CBOC (MN) | E23: infra & Rural | F23: 46014 | G23: 2025 | H23: 54 | I23: full | J23: 54 | L23: https://www.eb5group.com/ | M23: https://www.linkedin.com/posts/activity-7422356548976480256-ui9A?utm_source=share&utm_medium=member_desktop&rcm=ACoAAAWNJowBHB6o6iZGhL9Y9yDp6S82Tv_mNzg
C24: USIF | D24: Grand Central Rising | E24: infra & HUA | F24: pending | G24: 2026 | H24: 437 | L24: https://visaeb-5.com/project/grand-central-rising/
C25: EB5 Group | D25: VA Outpatient Clinic, Round Rock | E25: infra only | F25: pending | G25: early 2026 | H25: =560/8 -> 70 | L25: note to check: I-956F NOID?
C26: CanAm | D26: Pacific Port Logistics Center, California | E26: infra & HUA | F26: pending (filed 2/2026) | G26: early 2026 | H26: 225 | J26: 80
C27: EB5 Group | D27: Virginia Beach CBOC | E27: infra only | F27: to be filed | G27: late 2026 | H27: 175
C28: EB5 Group | D28: Salt Lake CBOC | E28: infra only | F28: to be filed | G28: late 2026 | H28: 95
L29: Guess at 2025 Infrastructure Project distribution by country
H30: Slots | J30: Investors | M30: Receipts | N30: Approvals
G31: Estimated total by 2025 end | H31: =SUM(H15:H23) -> 631 | J31: =SUM(J15:J28) -> 529 | L31: China | M31: =$M$34*O31 -> 211.6 | N31: 30 | O31: 0.4
G32: Estimated total by 2026 end | H32: =SUM(H15:H28) -> 1633 | L32: India | M32: =$M$34*O32 -> 105.8 | N32: 20 | O32: 0.2
C33: Not Infrastructure projects | L33: ROW | M33: =$M$34*O33 -> 211.6 | N33: 80 | O33: 0.4
C34: Regional Center | D34: Project | E34: Categories | L34: Total | M34: =J31 -> 529 | N34: =SUM(N31:N33) -> 130 | O34: =SUM(O31:O33) -> 1
C35: EB5 United | D35: Texas Infrastructure Holdings, Uvalde | E35: HUA, Rural | L35: (this is a total guess -- replace with your best guess!)
C36: CanAm | D36: 360 Broadband, TX | E36: Rural only
C37: CanAm | D37: Green Hydrogen Plant Infrastructure Expansion | E37: High Unemployment
C38: CMB | D38: Group 101 | E38: High Unemployment
B41: Form I-485, Application to Register Permanent Residence or Adjust Status
B42: Pending Application for Employment-Based Preference Categories
B43: As of May 5, 2025
B44: Country Of Chargeability | C44: Preference Category | D44: Visa Status | E44: Priority Date Month | F44: Priority Date Year - 2022 | G44: Priority Date Year - 2023 | H44: Priority Date Year - 2024 | I44: Priority Date Year - 2025
B45: China | C45: Employment-Based 5th Preference Category Set Aside: Infrastructure (2%) (EB5) | D45: Available | E45: May | F45: - | G45: D | H45: - | I45: -
B46: China | C46: Employment-Based 5th Preference Category Set Aside: Infrastructure (2%) (EB5) | D46: Available | E46: September | F46: - | G46: - | H46: D | I46: -
B47: China | C47: Employment-Based 5th Preference Category Set Aside: Infrastructure (2%) (EB5) | D47: Available | E47: December | F47: D | G47: D | H47: - | I47: - | J47: =COUNTIF(F45:I47,"D") -> 4
B48: India | C48: Employment-Based 5th Preference Category Set Aside: Infrastructure (2%) (EB5) | D48: Available | E48: February | F48: - | G48: D | H48: - | I48: D
B49: India | C49: Employment-Based 5th Preference Category Set Aside: Infrastructure (2%) (EB5) | D49: Available | E49: March | F49: - | G49: - | H49: D | I49: D
B50: India | C50: Employment-Based 5th Preference Category Set Aside: Infrastructure (2%) (EB5) | D50: Available | E50: September | F50: - | G50: D | H50: - | I50: -
B51: India | C51: Employment-Based 5th Preference Category Set Aside: Infrastructure (2%) (EB5) | D51: Available | E51: November | F51: - | G51: - | H51: D | I51: - | J51: =COUNTIF(F48:I51,"D") -> 6
B52: Mexico | C52: Employment-Based 5th Preference Category Set Aside: Infrastructure (2%) (EB5) | D52: Available | E52: March | F52: - | G52: - | H52: D | I52: -
B53: Mexico | C53: Employment-Based 5th Preference Category Set Aside: Infrastructure (2%) (EB5) | D53: Available | E53: July | F53: - | G53: - | H53: D | I53: -
B54: Mexico | C54: Employment-Based 5th Preference Category Set Aside: Infrastructure (2%) (EB5) | D54: Available | E54: November | F54: - | G54: - | H54: D | I54: -
B55: Rest of the World | C55: Employment-Based 5th Preference Category Set Aside: Infrastructure (2%) (EB5) | D55: Available | E55: January | F55: - | G55: D | H55: - | I55: -
B56: Rest of the World | C56: Employment-Based 5th Preference Category Set Aside: Infrastructure (2%) (EB5) | D56: Available | E56: February | F56: - | G56: D | H56: - | I56: D
B57: Rest of the World | C57: Employment-Based 5th Preference Category Set Aside: Infrastructure (2%) (EB5) | D57: Available | E57: March | F57: - | G57: - | H57: D | I57: -
B58: Rest of the World | C58: Employment-Based 5th Preference Category Set Aside: Infrastructure (2%) (EB5) | D58: Available | E58: April | F58: - | G58: D | H58: D | I58: -
B59: Rest of the World | C59: Employment-Based 5th Preference Category Set Aside: Infrastructure (2%) (EB5) | D59: Available | E59: June | F59: - | G59: D | H59: - | I59: -
B60: Rest of the World | C60: Employment-Based 5th Preference Category Set Aside: Infrastructure (2%) (EB5) | D60: Available | E60: July | F60: - | G60: - | H60: D | I60: -
B61: Rest of the World | C61: Employment-Based 5th Preference Category Set Aside: Infrastructure (2%) (EB5) | D61: Available | E61: October | F61: - | G61: - | H61: D | I61: - | J61: =COUNTIF(F52:I61,"D") -> 12
B62: D Disclosure standards not met.
B63: [Redacts a number <11]
B65: Form I-485, Application to Register Permanent Residence or Adjust Status
B66: Pending Application for Employment-Based Preference Categories for Rest of the World (Priority Date Years 2017 - 2026)
B67: As of April 3, 2026
B69: Country Of Chargeability | C69: Preference Category | D69: Visa Status | E69: Priority Date Month | F69: Priority Date Year - 2022 | G69: Priority Date Year - 2023 | H69: Priority Date Year - 2024 | I69: Priority Date Year - 2025 | J69: Priority Date Year - 2026
B70: China | C70: Employment-Based 5th Preference Category Set Aside: Infrastructure (2%) (EB5) | D70: Available | E70: February | F70: 0 | G70: 0 | H70: 0 | I70: 0 | J70: D
B71: China | C71: Employment-Based 5th Preference Category Set Aside: Infrastructure (2%) (EB5) | D71: Available | E71: March | F71: 0 | G71: 0 | H71: 0 | I71: 0 | J71: D
B72: China | C72: Employment-Based 5th Preference Category Set Aside: Infrastructure (2%) (EB5) | D72: Available | E72: July | F72: 0 | G72: 0 | H72: 0 | I72: D | J72: 0
B73: China | C73: Employment-Based 5th Preference Category Set Aside: Infrastructure (2%) (EB5) | D73: Available | E73: December | F73: 0 | G73: 0 | H73: 0 | I73: D | J73: 0
B74: India | C74: Employment-Based 5th Preference Category Set Aside: Infrastructure (2%) (EB5) | D74: Available | E74: February | F74: 0 | G74: 0 | H74: 0 | I74: 0 | J74: 13
B75: India | C75: Employment-Based 5th Preference Category Set Aside: Infrastructure (2%) (EB5) | D75: Available | E75: March | F75: 0 | G75: 0 | H75: 0 | I75: 0 | J75: D
B76: India | C76: Employment-Based 5th Preference Category Set Aside: Infrastructure (2%) (EB5) | D76: Available | E76: April | F76: 0 | G76: 0 | H76: 0 | I76: D | J76: 0
B77: India | C77: Employment-Based 5th Preference Category Set Aside: Infrastructure (2%) (EB5) | D77: Available | E77: May | F77: 0 | G77: 0 | H77: 0 | I77: D | J77: 0
B78: India | C78: Employment-Based 5th Preference Category Set Aside: Infrastructure (2%) (EB5) | D78: Available | E78: June | F78: 0 | G78: 0 | H78: 0 | I78: D | J78: 0
B79: India | C79: Employment-Based 5th Preference Category Set Aside: Infrastructure (2%) (EB5) | D79: Available | E79: October | F79: 0 | G79: 0 | H79: 0 | I79: D | J79: 0
B80: India | C80: Employment-Based 5th Preference Category Set Aside: Infrastructure (2%) (EB5) | D80: Available | E80: December | F80: 0 | G80: 0 | H80: D | I80: 0 | J80: 0
B81: Rest of the World | C81: Employment-Based 5th Preference Category Set Aside: Infrastructure (2%) (EB5) | D81: Available | E81: January | F81: 0 | G81: 0 | H81: 0 | I81: 0 | J81: D
B82: Rest of the World | C82: Employment-Based 5th Preference Category Set Aside: Infrastructure (2%) (EB5) | D82: Available | E82: February | F82: 0 | G82: 0 | H82: 0 | I82: 0 | J82: D
B83: Rest of the World | C83: Employment-Based 5th Preference Category Set Aside: Infrastructure (2%) (EB5) | D83: Available | E83: March | F83: 0 | G83: 0 | H83: 0 | I83: D | J83: D
B84: Rest of the World | C84: Employment-Based 5th Preference Category Set Aside: Infrastructure (2%) (EB5) | D84: Available | E84: August | F84: 0 | G84: 0 | H84: 0 | I84: D | J84: 0
B85: Rest of the World | C85: Employment-Based 5th Preference Category Set Aside: Infrastructure (2%) (EB5) | D85: Available | E85: September | F85: 0 | G85: 0 | H85: 0 | I85: D | J85: 0
B86: Rest of the World | C86: Employment-Based 5th Preference Category Set Aside: Infrastructure (2%) (EB5) | D86: Available | E86: October | F86: 0 | G86: 0 | H86: 0 | I86: D | J86: 0
B87: Rest of the World | C87: Employment-Based 5th Preference Category Set Aside: Infrastructure (2%) (EB5) | D87: Available | E87: December | F87: 0 | G87: 0 | H87: 0 | I87: D | J87: 0
B89: Source:
B90: Department of Homeland Security, U.S. Citizenship and Immigration Services, Office of Performance and Quality, CLAIMS 3, ELIS, queried May 2025 and updated May 20, 2025.
B91: https://www.uscis.gov/sites/default/files/document/data/eb_inventory_may_2025.xlsx

Sheet Progress
B1: Data related to progress in issuing Reserved visas, and advancing pipeline applicants to the visa stage
B3: Post-RIA Petition Filings and Adjudications
B4: http://www.uscis.gov/tools/reports-studies/immigration-forms-data
B5: Date | C5: I-956F Approved | D5: I-526/I-526E Filed | E5: I-526/I-526E Approved | F5: I-526/I-526E Denied | G5: Total Post-RIA I-526/I-526E Processed | H5: Period-End Post-RIA I-526/I-526E Pending | I5: Period-end Net Backlog
B6: 2022 Q3 Apr - Jun 2022 | D6: 32 | G6: 0
B7: 2022 Q4 Jul - Sep 2022 | D7: 188 | G7: 0
B8: 2023 Q1 Oct - Dec 2022 | D8: 453 | G8: 0
B9: 2023 Q2 Jan - Mar 2023 | C9: D | D9: 535 | G9: 0 | H9: 1127
B10: 2023 Q3 Apr - Jun 2023 | C10: D | D10: 699 | G10: 0 | H10: 1761
B11: 2023 Q4 Jul - Sep 2023 | C11: D | D11: 945 | E11: 63 | G11: 63 | H11: 2431
B12: 2024 Q1 Oct - Dec 2023 | C12: H | D12: 613 | E12: 194 | G12: 194 | H12: 2667
B13: 2024 Q2 Jan - Mar 2024 | C13: 60 | D13: 1879 | E13: H | F13: D | G13: 172 | H13: 3672
B14: 2024 Q3 Apr - Jun 2024 | C14: 88 | D14: 264 | E14: H | F14: D | G14: 332 | H14: 4685
B15: 2024 Q4 Jul - Sep 2024 | C15: 94 | D15: 1081 | E15: 396 | F15: 25 | G15: 421 | H15: 5850
B16: 2025 Q1 Oct - Dec 2024 | C16: 30 | D16: 1422 | E16: 267 | F16: 18 | G16: 303 | H16: 6924
B17: 2025 Q2 Jan - Mar 2025 | C17: H | D17: 1918 | E17: 208 | F17: 11 | G17: 219 | H17: 8856
B18: 2025 Q3 Apr - Jun 2025 | C18: 37 | D18: 1739 | E18: 1047 | F18: 66 | G18: 1113 | H18: 9539
B19: 2025 Q4 Jul - Sep 2025 | C19: 61 | D19: 1569 | E19: 1349 | F19: 81 | G19: 1430 | H19: 9669 | I19: 6400
B20: 2026 Q1 Oct - Dec 2025 | C20: 39 | D20: 1765 | E20: 764 | F20: 176 | G20: 940 | H20: 10470 | I20: 7300
B21: 2026 Q2 Jan - Mar 2026 | C21: 47 | D21: 1772 | E21: 781 | F21: 199 | G21: 980 | H21: 11229 | I21: 7900
C22: =SUM(C18:C21) -> 184 | D22: =SUM(D6:D21) -> 16874 | E22: =SUM(E6:E21) -> 5069 | F22: =SUM(F6:F21) -> 576 | G22: =SUM(G6:G21) -> 6167
B25: I-526/I-526E Receipts, Approvals, and Denials April 1, 2022 to January 31, 2025
B26: AIIA January 2025 FOIA
B27: https://goaiia.org/aiia-foia-series-updated-i-526e-inventory-statistics-for-january-2025/
D29: I-526/I-526E completions 2022 to Jan 31, 2025
C30: Receipts | D30: Approvals | E30: Denials | F30: Total Adjudicated | G30: % Total Adjudicated | H30: % of Receipts Adjudicated as of 1/25
B31: High Unemployment Area | C31: 5191 | D31: 351 | E31: 10 | F31: =SUM(D31:E31) -> 361 | G31: =F31/$F$36 -> 0.22848101 | H31: =F31/C31 -> 0.069543441
B32: Rural | C32: 4329 | D32: 1126 | E32: 30 | F32: =SUM(D32:E32) -> 1156 | G32: =F32/$F$36 -> 0.73164557 | H32: =F32/C32 -> 0.26703627
B33: Rural and HUA | D33: 7 | E33: 0 | F33: =SUM(D33:E33) -> 7 | G33: =F33/$F$36 -> 0.0044303797
B34: Infrastructure | D34: 0 | E34: 0 | F34: 0 | G34: =F34/$F$36 -> 0
B35: Unreserved and Unknown | D35: 35 | E35: 21 | F35: =SUM(D35:E35) -> 56 | G35: =F35/$F$36 -> 0.035443038
B36: Total All Categories | D36: =SUM(D31:D35) -> 1519 | E36: =SUM(E31:E35) -> 61 | F36: =SUM(F31:F35) -> 1580 | G36: =F36/$F$36 -> 1
B38: I-526/I-526E Receipts, Approvals, and Denials April 1, 2022 to July 31, 2025, by TEA category
B39: AIIA July 2025 FOIA
B40: https://goaiia.org/blog/aiia-foia-series-updated-i-526e-inventory-statistics-for-july-2025/#
C41: Receipts | D41: Approvals | E41: Denials | F41: Total Adjudicated | G41: % Total Adjudicated | H41: % of Receipts Adjudicated as of 7/25 | W41: Data Source: https://travel.state.gov/content/travel/en/legal/visa-law0/visa-statistics/immigrant-visa-statistics/monthly-immigrant-visa-issuances.html
B42: High Unemployment Area | C42: 6582 | D42: 545 | E42: 13 | F42: =SUM(D42:E42) -> 558 | G42: =F42/$F$47 -> 0.15696203 | H42: =F42/C42 -> 0.084776664
B43: Rural Area | C43: 6406 | D43: 2819 | E43: 62 | F43: =SUM(D43:E43) -> 2881 | G43: =F43/$F$47 -> 0.81040788 | H43: =F43/C43 -> 0.44973462 | W43: Data Source: http://www.uscis.gov/tools/reports-studies/immigration-forms-data
B44: Rural Area and HUA | C44: 99 | D44: 29 | E44: 1 | F44: =SUM(D44:E44) -> 30 | G44: =F44/$F$47 -> 0.0084388186
B45: Infrastructure | C45: 0 | D45: 0 | E45: 0 | F45: =SUM(D45:E45) -> 0 | G45: =F45/$F$47 -> 0
B46: Unreserved & Unknown | C46: 433 | D46: 49 | E46: 37 | F46: =SUM(D46:E46) -> 86 | G46: =F46/$F$47 -> 0.02419128
B47: Total All Categories | C47: =SUM(C42:C46) -> 13520 | D47: =SUM(D42:D46) -> 3442 | E47: =SUM(E42:E46) -> 113 | F47: =SUM(D47:E47) -> 3555 | G47: =F47/$F$47 -> 1
B49: I-526/I-526E Receipts and Adjudications, April 1, 2022 to July 31, 2025, by Country and TEA
B50: AIIA July 2025 FOIA
B51: https://goaiia.org/blog/aiia-foia-series-updated-i-526e-inventory-statistics-for-july-2025/#
C52: High Unemployment Receipts | D52: High Unemployment Approvals + Denials | E52: % HUA receipts adjudicated as of 7/31/2025 | F52: Rural Receipts | G52: Rural Approvals + Denials | H52: % Rural receipts adjudicated as of 7/31/2025
B53: China | C53: 2926 | D53: 104 | E53: =D53/C53 -> 0.035543404 | F53: 3845 | G53: 1709 | H53: =G53/F53 -> 0.44447334
B54: India | C54: 1264 | D54: 218 | E54: =D54/C54 -> 0.17246835 | F54: 1636 | G54: 730 | H54: =G54/F54 -> 0.44621027
B55: Rest of World | C55: 2392 | D55: 236 | E55: =D55/C55 -> 0.098662207 | F55: 925 | G55: 431 | H55: =G55/F55 -> 0.46594595
B56: Total | C56: =SUM(C53:C55) -> 6582 | D56: =SUM(D53:D55) -> 558 | E56: =D56/C56 -> 0.084776664 | F56: =SUM(F53:F55) -> 6406 | G56: =SUM(G53:G55) -> 2870 | H56: =G56/F56 -> 0.44801748
B58: I-526/I-526E Receipts and Adjudications for April 1, 2022 to July 31, 2025, by filing date and TEA
B59: AIIA July 2025 FOIA | J59: I-526/I-526E Receipts and Adjudications for April 1, 2022 to July 31, 2025, by filing date and TEA
B60: Petition Filing Date | C60: HUA Receipts | D60: HUA Adjudications by 8/2025 | E60: % HUA Adjudicated by 8/2025 | F60: Rural Receipts | G60: Rural Adjudications by 8/2025 | H60: % Rural Adjudicated by 8/2025 | J60: Petition Filing Date | K60: China Rural | L60: China HUA | M60: India Rural | N60: India HUA | O60: ROW Rural | P60: ROW HUA
B61: Apr-Jun 2022 | C61: 6 | D61: 6 | E61: =D61/C61 -> 1 | F61: 2 | G61: 2 | H61: =G61/F61 -> 1 | J61: 2022-2023 | K61: 711 | L61: 102 | M61: 179 | N61: 143 | O61: =SUM(G61:G67)-M61-K61 -> 169 | P61: =SUM(D61:D67)-N61-L61 -> 221
B62: Jul-Sep 2022 | C62: 237 | D62: 217 | E62: =D62/C62 -> 0.91561181 | F62: 82 | G62: 78 | H62: =G62/F62 -> 0.95121951 | J62: 2024 | K62: 920 | L62: 1 | M62: 408 | N62: 74 | O62: =SUM(G68:G71)-M62-K62 -> 308 | P62: =SUM(D68:D71)-N62-L62 -> 13
B63: Oct-Dec 2022 | C63: 313 | D63: 87 | E63: =D63/C63 -> 0.27795527 | F63: 110 | G63: 86 | H63: =G63/F63 -> 0.78181818 | J63: 2025 | K63: 78 | L63: 1 | M63: 109 | N63: 1 | O63: 0 | P63: =SUM(D72:D74)-N63-L63 -> 2
B64: Jan-Mar 2023 | C64: 379 | D64: 51 | E64: =D64/C64 -> 0.13456464 | F64: 114 | G64: 99 | H64: =G64/F64 -> 0.86842105
B65: Apr-Jun 2023 | C65: 436 | D65: 36 | E65: =D65/C65 -> 0.082568807 | F65: 222 | G65: 182 | H65: =G65/F65 -> 0.81981982
B66: Jul-Sep 2023 | C66: 546 | D66: 41 | E66: =D66/C66 -> 0.075091575 | F66: 374 | G66: 288 | H66: =G66/F66 -> 0.77005348
B67: Oct-Dec 2023 | C67: 531 | D67: 28 | E67: =D67/C67 -> 0.052730697 | F67: 421 | G67: 324 | H67: =G67/F67 -> 0.7695962
B68: Jan-Mar 2024 | C68: 997 | D68: 45 | E68: =D68/C68 -> 0.045135406 | F68: 970 | G68: 695 | H68: =G68/F68 -> 0.71649485
B69: Apr-Jun 2024 | C69: 380 | D69: 9 | E69: =D69/C69 -> 0.023684211 | F69: 346 | G69: 225 | H69: =G69/F69 -> 0.65028902
B70: Jul-Sep 2024 | C70: 481 | D70: 15 | E70: =D70/C70 -> 0.031185031 | F70: 627 | G70: 341 | H70: =G70/F70 -> 0.54385965
B71: Oct-Dec 2024 | C71: 648 | D71: 19 | E71: =D71/C71 -> 0.029320988 | F71: 740 | G71: 375 | H71: =G71/F71 -> 0.50675676
B72: Jan-Mar 2025 | C72: 794 | D72: 4 | E72: =D72/C72 -> 0.0050377834 | F72: 1041 | G72: 185 | H72: =G72/F72 -> 0.17771374 | I72: =SUM(F61:F72) -> 5049 | J72: =SUM(G61:G72) -> 2880
B73: Apr-Jun 2025 | C73: 637 | D73: 0 | E73: =D73/C73 -> 0 | F73: 1034 | G73: 1 | H73: =G73/F73 -> 0.00096711799 | J73: =J72/I72 -> 0.57040998
B74: 45839 | C74: 197 | D74: 0 | E74: =D74/C74 -> 0 | F74: 323 | H74: =G74/F74 -> 0
B75: Total | C75: =SUM(C61:C74) -> 6582 | D75: =SUM(D61:D74) -> 558 | E75: =D75/C75 -> 0.084776664 | F75: =SUM(F61:F74) -> 6406 | G75: =SUM(G61:G74) -> 2881 | H75: =G75/F75 -> 0.44973462
G76: =G75/(D75+G75) -> 0.83774353
B78: Composition of the I-526/I-526E pending inventory in July 2025, by number of months that the petitions had been pending
B79: Number of months that petitions had been pending so far to date as of July 2025 | C79: Number of Petitions
C80: Rural I-526/I-526E | E80: High Unemployment I-526/I-526E | G80: All I-526/I-526E
B81: 0-6 months | C81: 2212 | D81: =C81/$C$88 -> 0.62751773 | E81: 1624 | F81: =E81/$E$88 -> 0.26958831 | G81: =C81+E81 -> 3836 | H81: =G81/$G$88 -> 0.40171746
B82: 6-12 months | C82: 651 | D82: =C82/$C$88 -> 0.18468085 | E82: 1095 | F82: =E82/$E$88 -> 0.18177291 | G82: =C82+E82 -> 1746 | H82: =G82/$G$88 -> 0.18284637
B83: 12-18 months | C83: 396 | D83: =C83/$C$88 -> 0.11234043 | E83: 1323 | F83: =E83/$E$88 -> 0.21962151 | G83: =C83+E83 -> 1719 | H83: =G83/$G$88 -> 0.18001885
B84: 18-24 months | C84: 183 | D84: =C84/$C$88 -> 0.051914894 | E84: 1008 | F84: =E84/$E$88 -> 0.16733068 | G84: =C84+E84 -> 1191 | H84: =G84/$G$88 -> 0.1247251
B85: 24-30 months | C85: 55 | D85: =C85/$C$88 -> 0.015602837 | E85: 728 | F85: =E85/$E$88 -> 0.12084993 | G85: =C85+E85 -> 783 | H85: =G85/$G$88 -> 0.081998115
B86: 30-36 months | C86: 28 | D86: =C86/$C$88 -> 0.0079432624 | E86: 246 | F86: =E86/$E$88 -> 0.040836653 | G86: =C86+E86 -> 274 | H86: =G86/$G$88 -> 0.028694104
B87: 36-42 months | C87: 0 | D87: =C87/$C$88 -> 0 | E87: 0 | F87: =E87/$E$88 -> 0 | G87: =C87+E87 -> 0 | H87: =G87/$G$88 -> 0
C88: =SUM(C81:C87) -> 3525 | D88: =C88/$C$88 -> 1 | E88: =SUM(E81:E87) -> 6024 | F88: =E88/$E$88 -> 1 | G88: =C88+E88 -> 9549 | H88: =G88/$G$88 -> 1
B89: Data source: USCIS via FOIA request by AIIA
B90: https://goaiia.org/blog/aiia-foia-series-updated-i-526e-inventory-statistics-for-july-2025/#
B92: FY2025 Reserved Visa Issuance
B93: Monthly visa issuance through consular processing
B94: https://travel.state.gov/content/travel/en/legal/visa-law0/visa-statistics/immigrant-visa-statistics/monthly-immigrant-visa-issuances.html
B95: All Countries
C96: 45566 | D96: 45597 | E96: 45627 | F96: 45658 | G96: 45689 | H96: 45717 | I96: 45748 | J96: 45778 | K96: 45809 | L96: 45839 | M96: 45870 | N96: 45901 | O96: Total
B97: High Unemployment visas issued | C97: 3 | E97: 21 | F97: 24 | G97: 42 | H97: 37 | I97: 9 | J97: 15 | K97: 30 | L97: 20 | M97: 1 | N97: 2 | O97: =SUM(C97:N97) -> 204
B98: Rural visas issued | C98: 2 | D98: 4 | E98: 15 | F98: 20 | G98: 51 | H98: 195 | I98: 53 | J98: 56 | K98: 20 | L98: 159 | M98: 91 | N98: 28 | O98: =SUM(C98:N98) -> 694
B99: Infrastructure | N99: 3 | O99: =SUM(C99:N99) -> 3
B100: Unreserved (Post-RIA) | C100: 1 | D100: 1 | E100: 10 | F100: 13 | G100: 38 | H100: 10 | J100: 1 | K100: 5 | L100: 11 | M100: 1 | N100: 4 | O100: =SUM(C100:N100) -> 95
B101: Unreserved (Pre-RIA) visas issued | C101: 1883 | D101: 1535 | E101: 1112 | F101: 832 | G101: 735 | H101: 1372 | I101: 478 | J101: 380 | K101: 325 | L101: 328 | M101: 419 | N101: 335 | O101: =SUM(C101:N101) -> 9734
C102: =SUM(C97:C101) -> 1889 | D102: =SUM(D97:D101) -> 1540 | E102: =SUM(E97:E101) -> 1158 | F102: =SUM(F97:F101) -> 889 | G102: =SUM(G97:G101) -> 866 | H102: =SUM(H97:H101) -> 1614 | I102: =SUM(I97:I101) -> 540 | J102: =SUM(J97:J101) -> 452 | ... M102: =SUM(M97:M101) -> 512 | O102: =SUM(C102:N102) -> 10358
C104: Total | D104: China | E104: India | F104: ROW | G104: Symbol | J104: Estimated total Unreserved FY2025
B105: High Unemployment | C105: =O97 -> 204 | D105: 53 | E105: 32 | F105: =C105-D105-E105 -> 119 | G105: RH, NH | J105: Consular | K105: AOS | L105: Total
B106: Rural | C106: =O98 -> 694 | D106: 513 | E106: 93 | F106: =C106-D106-E106 -> 88 | G106: RR, NR | I106: China | J106: =D108 -> 4223 | K106: 200 | L106: =SUM(J106:K106) -> 4423
B107: Unreserved (Post-RIA) | C107: =O100 -> 95 | F107: =C107-D107-E107 -> 95 | G107: RU, NU | I107: India | J107: =E108 -> 738 | K107: 300 | L107: =SUM(J107:K107) -> 1038
B108: Unreserved (Pre-RIA) | C108: =O101 -> 9734 | D108: 4223 | E108: 738 | F108: =C108-D108-E108 -> 4773 | G108: I5, R5, C5, T5 | I108: ROW | J108: =F108 -> 4773 | K108: 400 | L108: =SUM(J108:K108) -> 5173
B109: Infrastructure | C109: =O99 -> 3 | E109: 3 | G109: RI | I109: Total | J109: =SUM(J106:J108) -> 9734 | K109: =SUM(K106:K108) -> 900 | L109: =SUM(J109:K109) -> 10634
B110: Total Consular visas issued | C110: =SUM(C105:C109) -> 10730 | D110: =SUM(D105:D109) -> 4789 | E110: =SUM(E105:E109) -> 866 | F110: =SUM(F105:F109) -> 5075
...

Sheet Visa Supply
B1: EB-5 Visa Supply Projection 1 -- Scenario with significant FB rollover usage | M1: EB-5 Visa Supply Projection 2 -- scenario with minimal FB rollover | Z1: References
B3: Last updated: | C3: 46118 | M3: Last updated: | N3: 46118 | Z3: https://www.canamenterprises.com/about-eb-5/faq/
Z4: https://www.canamenterprises.com/2025/08/13/white-paper-2025-visa-backlog/
B5: Summary: Estimated Total EB-5 Visas | M5: Summary: Estimated Total EB-5 Visas | Z5: https://travel.state.gov/content/travel/en/legal/visa-law0/visa-statistics/immigrant-visa-statistics.html
B6: EB-5 visas available in theory | C6: Actual | D6: Actual | E6: Actual | F6: Actual | G6: Estimate | H6: Estimate | I6: Estimate | J6: Estimate | M6: EB-5 visas available in theory | N6: Actual | O6: Actual | P6: Actual | Q6: Estimate | R6: Estimate | S6: Estimate | T6: Estimate | U6: Estimate | Z6: https://blog.lucidtext.com/ina-203b/#b-designations-and-reserved-visas
C7: 2022 | D7: 2023 | E7: 2024 | F7: 2025 | G7: 2026 | H7: 2027 | I7: 2028 | J7: 2029 | N7: 2022 | O7: 2023 | P7: 2024 | Q7: 2025 | R7: 2026 | S7: 2027 | T7: 2028 | U7: 2029
B8: Unreserved | C8: =C64 -> 13591.158 | D8: =D64 -> 9515.5535 | E8: =E64 -> 14207.109 | F8: =F64 -> 11298.694 | G8: =G64 -> 9655.9715 | H8: =H64 -> 9964.8406 | I8: =I64 -> 9656 | J8: =J64 -> 6759.2 | M8: Unreserved | N8: =N64 -> 13591.158 | O8: =O64 -> 9515.5535 | P8: =P64 -> 14207.109 | Q8: =Q64 -> 11298.694 | R8: =R64 -> 9671.6142 | S8: =S64 -> 7550.8406 | T8: =T64 -> 6759.2 | U8: =U64 -> 6759.2
B9: Rural | C9: =C48 -> 3997.3994 | D9: =D48 -> 6796.0916 | E9: =E48 -> 5096.1244 | F9: =F48 -> 4427.9576 | G9: =G48 -> 4771 | H9: =H48 -> 5481.2 | I9: =I48 -> 2982.2 | J9: =J48 -> 2229.7 | M9: Rural | N9: =N48 -> 3997.3994 | O9: =O48 -> 6796.0916 | P9: =P48 -> 5096.1244 | Q9: =Q48 -> 4427.9576 | R9: =R48 -> 4776 | S9: =S48 -> 4775.8008 | T9: =T48 -> 2503.8008 | U9: =U48 -> 2503.8008
B10: High Unemployment | C10: =C51 -> 1998.6997 | D10: =D51 -> 3398.0458 | E10: =E51 -> 2548.0622 | F10: =F51 -> 2213.9788 | G10: =G51 -> 2385.8627 | H10: =H51 -> 2740.6 | I10: =I51 -> 1490.6 | J10: =J51 -> 1114.6 | M10: High Unemployment | N10: =N51 -> 1998.6997 | O10: =O51 -> 3398.0458 | P10: =P51 -> 2548.0622 | Q10: =Q51 -> 2213.9788 | R10: =R51 -> 2388.1631 | S10: =S51 -> 2387.9004 | T10: =T51 -> 1251.9004 | U10: =U51 -> 1251.9004
B11: Infrastructure | C11: =C54 -> 399.73994 | D11: =D54 -> 679.60916 | E11: =E54 -> 509.61244 | F11: =F54 -> 442.79576 | G11: =G54 -> 477.17254 | H11: =H54 -> 548.12 | I11: =I54 -> 298.12 | J11: =J54 -> 222.92 | M11: Infrastructure | N11: =N54 -> 399.73994 | O11: =O54 -> 679.60916 | P11: =P54 -> 509.61244 | Q11: =Q54 -> 442.79576 | R11: =R54 -> 477.63262 | S11: =S54 -> 477.58008 | T11: =T54 -> 250.38008 | U11: =U54 -> 250.18008
B12: TOTAL Visas Available | C12: =SUM(C8:C11) -> 19986.997 | D12: =SUM(D8:D11) -> 20389.3 | E12: =SUM(E8:E11) -> 22360.908 | F12: =SUM(F8:F11) -> 18383.426 | G12: =SUM(G8:G11) -> 17290.007 | H12: =SUM(H8:H11) -> 18734.761 | I12: =SUM(I8:I11) -> 14426.92 | J12: =SUM(J8:J11) -> 10326.42 | M12: TOTAL Visas Available | N12: =SUM(N8:N11) -> 19986.997 | O12: =SUM(O8:O11) -> 20389.3 | P12: =SUM(P8:P11) -> 22360.908 | Q12: =SUM(Q8:Q11) -> 18383.426 | R12: =SUM(R8:R11) -> 17313.41 | S12: =SUM(S8:S11) -> 15192.122 | T12: =SUM(T8:T11) -> 10765.281 | U12: =SUM(U8:U11) -> 10765.081
B14: Estimated actual EB-5 visas issued (considering demand/processing constraints and carryover) | M14: Estimated actual EB-5 visas issued (considering demand/processing constraints and carryover)
C15: Actual | D15: Actual | E15: Actual | F15: Estimate | G15: Estimate | H15: Estimate | I15: Estimate | J15: Estimate | N15: Actual | O15: Actual | P15: Actual | Q15: Estimate | R15: Estimate | S15: Estimate | T15: Estimate | U15: Estimate
C16: 2022 | D16: 2023 | E16: 2024 | F16: 2025 | G16: 2026 | H16: 2027 | I16: 2028 | J16: 2029 | K16: Normal Year | N16: 2022 | O16: 2023 | P16: 2024 | Q16: 2025 | R16: 2026 | S16: 2027 | T16: 2028 | U16: 2029 | V16: Normal Year
B17: Unreserved | C17: 10885 | D17: 9817 | E17: 14501 | F17: =Progress!C152 -> 11470 | G17: =G64 -> 9655.9715 | H17: =H29 -> 9656 | I17: =I29 -> 9656 | J17: =J29 -> 6759.2 | K17: =K21*0.68 -> 6759.2 | M17: Unreserved | N17: 10885 | O17: 9817 | P17: 14501 | Q17: =Progress!C152 -> 11470 | R17: =R64 -> 9671.6142 | S17: =S29 -> 7242 | T17: =T29 -> 6759.2 | U17: =U29 -> 6759.2 | V17: =V21*0.68 -> 6759.2
B18: Rural | C18: =C36 -> 0 | D18: =D36 -> 0 | E18: 332 | F18: =F36 -> 2000 | G18: =G36 -> 2000 | H18: =H36 -> 5339 | I18: =I36 -> 2740.5 | J18: =J36 -> 2130 | K18: =K21*0.2 -> 1988 | M18: Rural | N18: =N36 -> 0 | O18: =O36 -> 0 | P18: 332 | Q18: =Q36 -> 2000 | R18: =R36 -> 2000 | S18: =S36 -> 4260 | T18: =T36 -> 1988 | U18: =U36 -> 1988 | V18: =V21*0.2 -> 1988
B19: High Unemployment | C19: =C38 -> 0 | D19: =D38 -> 0 | E19: 91 | F19: =F38 -> 1000 | G19: =G38 -> 1000 | H19: =H38 -> 2670 | I19: =I38 -> 1370 | J19: =J38 -> 1150 | K19: =K21*0.1 -> 994 | M19: High Unemployment | N19: =N38 -> 0 | O19: =O38 -> 0 | P19: 91 | Q19: =Q38 -> 1000 | R19: =R38 -> 1000 | S19: =S38 -> 2130 | T19: =T38 -> 994 | U19: =U38 -> 994 | V19: =V21*0.1 -> 994
B20: Infrastructure | C20: =C40 -> 0 | D20: =D40 -> 0 | E20: =E40 -> 0 | F20: =F40 -> 0 | G20: =G40 -> 100 | H20: =H40 -> 534 | I20: =I40 -> 274 | J20: =J40 -> 230 | K20: =K21*0.02 -> 198.8 | M20: Infrastructure | N20: =N40 -> 0 | O20: =O40 -> 0 | P20: =P40 -> 0 | Q20: =Q40 -> 0 | R20: =R40 -> 100 | S20: =S40 -> 426 | T20: =T40 -> 199 | U20: =U40 -> 199 | V20: =V21*0.02 -> 198.8
B21: TOTAL Visas Issued | C21: =SUM(C17:C20) -> 10885 | D21: =SUM(D17:D20) -> 9817 | E21: =SUM(E17:E20) -> 14924 | F21: =SUM(F17:F20) -> 14470 | G21: =SUM(G17:G20) -> 12755.972 | H21: =SUM(H17:H20) -> 18199 | I21: =SUM(I17:I20) -> 14040.5 | J21: =SUM(J17:J20) -> 10269.2 | K21: =140000*0.071 -> 9940 | M21: TOTAL Visas Issued | N21: =SUM(N17:N20) -> 10885 | O21: =SUM(O17:O20) -> 9817 | P21: =SUM(P17:P20) -> 14924 | Q21: =SUM(Q17:Q20) -> 14470 | R21: =SUM(R17:R20) -> 12771.614 | S21: =SUM(S17:S20) -> 14058 | T21: =SUM(T17:T20) -> 9940.2 | U21: =SUM(U17:U20) -> 9940.2 | V21: =140000*0.071 -> 9940
B23: Derivation of visa number estimates, including carryover | M23: Derivation of visa number estimates, including carryover
H24: Cells with input guesses -- ACTUAL VALUES COULD VARY | S24: Cells with input guesses -- ACTUAL VALUES COULD VARY
B25: New issue visas available | M25: New issue visas available
B26: Annual Limits (newly available pool) | C26: 2022 | D26: 2023 | E26: 2024 | F26: 2025 | G26: 2026 | H26: 2027 | I26: 2028 | J26: 2029 | M26: Annual Limits (newly available pool) | N26: 2022 | O26: 2023 | P26: 2024 | Q26: 2025 | R26: 2026 | S26: 2027 | T26: 2028 | U26: 2029
B27: Worldwide Employment Limit | C27: 281507 | D27: 197091 | E27: 161791 | F27: 150037 | G27: 186000 | H27: =140000+60000 -> 200000 | I27: 200000 | J27: 140000 | M27: Worldwide Employment Limit | N27: 281507 | O27: 197091 | P27: 161791 | Q27: 150037 | R27: 186324 | S27: 150000 | T27: 140000 | U27: 140000
B28: EB-5 Newly-Available Pool (7.1%) | C28: =C27*0.071 -> 19986.997 | D28: =D27*0.071 -> 13993.461 | E28: =E27*0.071 -> 11487.161 | F28: =F27*0.071 -> 10652.627 | G28: =G27*0.071 -> 13206 | H28: =H27*0.071 -> 14200 | I28: =I27*0.071 -> 14200 | J28: =J27*0.071 -> 9940 | M28: EB-5 Newly-Available Pool (7.1%) | N28: =N27*0.071 -> 19986.997 | O28: =O27*0.071 -> 13993.461 | P28: =P27*0.071 -> 11487.161 | Q28: =Q27*0.071 -> 10652.627 | R28: =R27*0.071 -> 13229.004 | S28: =S27*0.071 -> 10650 | T28: =T27*0.071 -> 9940 | U28: =U27*0.071 -> 9940
B29: Unreserved (68%) | C29: =C28*0.68 -> 13591.158 | D29: =D28*0.68 -> 9515.5535 | E29: =E28*0.68 -> 7811.2695 | F29: =F28*0.68 -> 7243.7864 | G29: =G28*0.68 -> 8980.08 | H29: =H28*0.68 -> 9656 | I29: =I28*0.68 -> 9656 | J29: =J28*0.68 -> 6759.2 | M29: Unreserved (68%) | N29: =N28*0.68 -> 13591.158 | O29: =O28*0.68 -> 9515.5535 | P29: =P28*0.68 -> 7811.2695 | Q29: =Q28*0.68 -> 7243.7864 | R29: =R28*0.68 -> 8995.7227 | S29: =S28*0.68 -> 7242 | T29: =T28*0.68 -> 6759.2 | U29: =U28*0.68 -> 6759.2
B30: Rural (20%) | C30: =C28*0.2 -> 3997.3994 | D30: =D28*0.2 -> 2798.6922 | E30: =E28*0.2 -> 2297.4322 | F30: =F28*0.2 -> 2130.5254 | G30: =G28*0.2 -> 2641.2 | H30: =H28*0.2 -> 2840 | I30: =I28*0.2 -> 2840 | J30: =J28*0.2 -> 1988 | M30: Rural (20%) | N30: =N28*0.2 -> 3997.3994 | O30: =O28*0.2 -> 2798.6922 | P30: =P28*0.2 -> 2297.4322 | Q30: =Q28*0.2 -> 2130.5254 | R30: =R28*0.2 -> 2645.8008 | S30: =S28*0.2 -> 2130 | T30: =T28*0.2 -> 1988 | U30: =U28*0.2 -> 1988
B31: High Unemployment (10%) | C31: =C28*0.1 -> 1998.6997 | D31: =D28*0.1 -> 1399.3461 | E31: =E28*0.1 -> 1148.7161 | F31: =F28*0.1 -> 1065.2627 | G31: =G28*0.1 -> 1320.6 | H31: =H28*0.1 -> 1420 | I31: =I28*0.1 -> 1420 | J31: =J28*0.1 -> 994 | M31: High Unemployment (10%) | N31: =N28*0.1 -> 1998.6997 | O31: =O28*0.1 -> 1399.3461 | P31: =P28*0.1 -> 1148.7161 | Q31: =Q28*0.1 -> 1065.2627 | R31: =R28*0.1 -> 1322.9004 | S31: =S28*0.1 -> 1065 | T31: =T28*0.1 -> 994 | U31: =U28*0.1 -> 994
B32: Infrastructure (2%) | C32: =C28*0.02 -> 399.73994 | D32: =D28*0.02 -> 279.86922 | E32: =E28*0.02 -> 229.74322 | F32: =F28*0.02 -> 213.05254 | G32: =G28*0.02 -> 264.12 | H32: =H28*0.02 -> 284 | I32: =I28*0.02 -> 284 | J32: =J28*0.02 -> 198.8 | M32: Infrastructure (2%) | N32: =N28*0.02 -> 399.73994 | O32: =O28*0.02 -> 279.86922 | P32: =P28*0.02 -> 229.74322 | Q32: =Q28*0.02 -> 213.05254 | R32: =R28*0.02 -> 264.58008 | S32: =S28*0.02 -> 213 | T32: =T28*0.02 -> 198.8 | U32: =U28*0.02 -> 198.8
F33: =SUM(F30:F32) -> 3408.8406 | Q33: =SUM(Q30:Q32) -> 3408.8406
B34: Assumptions affecting carryover | M34: Assumptions affecting carryover
B35: Enter Usage Guesses | C35: 2022 | D35: 2023 | E35: 2024 | F35: 2025 | G35: 2026 | H35: 2027 | I35: 2028 | J35: 2029 | M35: Enter Usage Guesses | N35: 2022 | O35: 2023 | P35: 2024 | Q35: 2025 | R35: 2026 | S35: 2027 | T35: 2028 | U35: 2029
B36: Rural visas issued | C36: 0 | D36: 0 | E36: 332 | F36: =ROUNDUP(Progress!J120,-3) -> 2000 | G36: 2000 | H36: 5339 | I36: 2740.5 | J36: 2130 | M36: Rural visas issued | N36: 0 | O36: 0 | P36: 332 | Q36: =F36 -> 2000 | R36: 2000 | S36: 4260 | T36: 1988 | U36: 1988
B37: issued ≤ availability? | F37: =IF(F36<=F48,"yes","NO") -> yes | G37: =IF(G36<=G48,"yes","NO") -> yes | H37: =IF(H36<=H48,"yes","NO") -> yes | I37: =IF(I36<=I48,"yes","NO") -> yes | J37: =IF(J36<=J48,"yes","NO") -> yes | M37: issued ≤ availability? | Q37: =IF(Q36<=Q48,"yes","NO") -> yes | R37: =IF(R36<=R48,"yes","NO") -> yes | S37: =IF(S36<=S48,"yes","NO") -> yes | T37: =IF(T36<=T48,"yes","NO") -> yes | U37: =IF(U36<=U48,"yes","NO") -> yes
B38: HU visas issued | C38: 0 | D38: 0 | E38: 91 | F38: =ROUNDUP(Progress!J128,-3) -> 1000 | G38: 1000 | H38: 2670 | I38: 1370 | J38: 1150 | M38: HU visas issued | N38: 0 | O38: 0 | P38: 91 | Q38: =F38 -> 1000 | R38: 1000 | S38: 2130 | T38: 994 | U38: 994
B39: issued ≤ availability? | F39: =IF(F38<=F51,"yes","NO") -> yes | G39: =IF(G38<=G51,"yes","NO") -> yes | H39: =IF(H38<=H51,"yes","NO") -> yes | I39: =IF(I38<=I51,"yes","NO") -> yes | J39: =IF(J38<=J51,"yes","NO") -> NO | M39: issued ≤ availability? | Q39: =IF(Q38<=Q51,"yes","NO") -> yes | R39: =IF(R38<=R51,"yes","NO") -> yes | S39: =IF(S38<=S51,"yes","NO") -> yes | T39: =IF(T38<=T51,"yes","NO") -> yes | U39: =IF(U38<=U51,"yes","NO") -> yes
B40: Infrastructure visas issued | C40: 0 | D40: 0 | E40: 0 | F40: 0 | G40: 100 | H40: 534 | I40: 274 | J40: 230 | M40: Infrastructure visas issued | N40: 0 | O40: 0 | P40: 0 | Q40: 0 | R40: 100 | S40: 426 | T40: 199 | U40: 199
B41: issued ≤ availability? | F41: =IF(F40<=F54,"yes","NO") -> yes | G41: =IF(G40<=G54,"yes","NO") -> yes | H41: =IF(H40<=H54,"yes","NO") -> yes | I41: =IF(I40<=I54,"yes","NO") -> yes | J41: =IF(J40<=J54,"yes","NO") -> NO | M41: issued ≤ availability? | Q41: =IF(Q40<=Q54,"yes","NO") -> yes | R41: =IF(R40<=R54,"yes","NO") -> yes | S41: =IF(S40<=S54,"yes","NO") -> yes | T41: =IF(T40<=T54,"yes","NO") -> yes | U41: =IF(U40<=U54,"yes","NO") -> yes
B42: Total reserved visas issued | C42: =SUM(C36:C40) -> 0 | D42: =SUM(D36:D40) -> 0 | E42: =SUM(E36:E40) -> 423 | F42: =SUM(F36:F40) -> 3000 | G42: =SUM(G36:G40) -> 3100 | H42: =SUM(H36:H40) -> 8543 | I42: =SUM(I36:I40) -> 4384.5 | J42: =SUM(J36:J40) -> 3510 | M42: Total reserved visas issued | N42: =SUM(N36:N40) -> 0 | O42: =SUM(O36:O40) -> 0 | P42: =SUM(P36:P40) -> 423 | Q42: =SUM(Q36:Q40) -> 3000 | R42: =SUM(R36:R40) -> 3100 | S42: =SUM(S36:S40) -> 6816 | T42: =SUM(T36:T40) -> 3181 | U42: =SUM(U36:U40) -> 3181
B44: Calculate total EB-5 visas available with carryover | M44: Calculate total EB-5 visas available with carryover
B45: Reserved + Carryover | C45: 2022 | D45: 2023 | E45: 2024 | F45: 2025 | G45: 2026 | H45: 2027 | I45: 2028 | J45: 2029 | M45: Reserved + Carryover | N45: 2022 | O45: 2023 | P45: 2024 | Q45: 2025 | R45: 2026 | S45: 2027 | T45: 2028 | U45: 2029
B46: Rural (20% new EB-5 pool) | C46: =C30 -> 3997.3994 | D46: =D30 -> 2798.6922 | E46: =E30 -> 2297.4322 | F46: =F30 -> 2130.5254 | G46: =G30 -> 2641.2 | H46: =H30 -> 2840 | I46: =I30 -> 2840 | J46: =J30 -> 1988 | M46: Rural (20% new EB-5 pool) | N46: =N30 -> 3997.3994 | O46: =O30 -> 2798.6922 | P46: =P30 -> 2297.4322 | Q46: =Q30 -> 2130.5254 | R46: =R30 -> 2645.8008 | S46: =S30 -> 2130 | T46: =T30 -> 1988 | U46: =U30 -> 1988
B47: Carryover unused new from previous FY | C47: 0 | D47: =C46 -> 3997.3994 | E47: =D46 -> 2798.6922 | F47: =IF(E47>E36,E46,E48-E36) -> 2297.4322 | G47: =IF(F47>F36,F46,F48-F36) -> 2130.5254 | H47: =IF(G47>G36,G46,G48-G36) -> 2641.2 | I47: =IF(H47>H36,H46,H48-H36) -> 142.2 | J47: =IF(I47>I36,I46,I48-I36) -> 241.7 | M47: Carryover unused new from previous FY | N47: 0 | O47: =N46 -> 3997.3994 | P47: =O46 -> 2798.6922 | Q47: =IF(P47>P36,P46,P48-P36) -> 2297.4322 | R47: =IF(Q47>Q36,Q46,Q48-Q36) -> 2130.5254 | S47: =IF(R47>R36,R46,R48-R36) -> 2645.8008 | T47: =IF(S47>S36,S46,S48-S36) -> 515.8008 | U47: =IF(T47>T36,T46,T48-T36) -> 515.8008
B48: Rural Total Available | C48: =SUM(C46:C47) -> 3997.3994 | D48: =SUM(D46:D47) -> 6796.0916 | E48: =SUM(E46:E47) -> 5096.1244 | F48: =SUM(F46:F47) -> 4427.9576 | G48: =ROUNDDOWN(SUM(G46:G47),0) -> 4771 | H48: =SUM(H46:H47) -> 5481.2 | I48: =SUM(I46:I47) -> 2982.2 | J48: =SUM(J46:J47) -> 2229.7 | M48: Rural Total Available | N48: =SUM(N46:N47) -> 3997.3994 | O48: =SUM(O46:O47) -> 6796.0916 | P48: =SUM(P46:P47) -> 5096.1244 | Q48: =SUM(Q46:Q47) -> 4427.9576 | R48: =ROUNDDOWN(SUM(R46:R47),0) -> 4776 | S48: =SUM(S46:S47) -> 4775.8008 | T48: =SUM(T46:T47) -> 2503.8008 | U48: =SUM(U46:U47) -> 2503.8008
B49: High Unemployment (10% new EB-5 pool) | C49: =C31 -> 1998.6997 | D49: =D31 -> 1399.3461 | E49: =E31 -> 1148.7161 | F49: =F31 -> 1065.2627 | G49: =G31 -> 1320.6 | H49: =H31 -> 1420 | I49: =I31 -> 1420 | J49: =J31 -> 994 | M49: High Unemployment (10% new EB-5 pool) | N49: =N31 -> 1998.6997 | O49: =O31 -> 1399.3461 | P49: =P31 -> 1148.7161 | Q49: =Q31 -> 1065.2627 | R49: =R31 -> 1322.9004 | S49: =S31 -> 1065 | T49: =T31 -> 994 | U49: =U31 -> 994
B50: Carryover unused new from previous FY | C50: 0 | D50: =C49 -> 1998.6997 | E50: =D49 -> 1399.3461 | F50: =IF(E50>E38,E49,E51-E38) -> 1148.7161 | G50: =IF(F50>F38,F49,F51-F38) -> 1065.2627 | H50: =IF(G50>G38,G49,G51-G38) -> 1320.6 | I50: =IF(H50>H38,H49,H51-H38) -> 70.6 | J50: =IF(I50>I38,I49,I51-I38) -> 120.6 | M50: Carryover unused new from previous FY | N50: 0 | O50: =N49 -> 1998.6997 | P50: =O49 -> 1399.3461 | Q50: =IF(P50>P38,P49,P51-P38) -> 1148.7161 | R50: =IF(Q50>Q38,Q49,Q51-Q38) -> 1065.2627 | S50: =IF(R50>R38,R49,R51-R38) -> 1322.9004 | T50: =IF(S50>S38,S49,S51-S38) -> 257.9004 | U50: =IF(T50>T38,T49,T51-T38) -> 257.9004
B51: HU Total Available | C51: =SUM(C49:C50) -> 1998.6997 | D51: =SUM(D49:D50) -> 3398.0458 | E51: =SUM(E49:E50) -> 2548.0622 | F51: =SUM(F49:F50) -> 2213.9788 | G51: =SUM(G49:G50) -> 2385.8627 | H51: =SUM(H49:H50) -> 2740.6 | I51: =SUM(I49:I50) -> 1490.6 | J51: =SUM(J49:J50) -> 1114.6 | M51: HU Total Available | N51: =SUM(N49:N50) -> 1998.6997 | O51: =SUM(O49:O50) -> 3398.0458 | P51: =SUM(P49:P50) -> 2548.0622 | Q51: =SUM(Q49:Q50) -> 2213.9788 | R51: =SUM(R49:R50) -> 2388.1631 | S51: =SUM(S49:S50) -> 2387.9004 | T51: =SUM(T49:T50) -> 1251.9004 | U51: =SUM(U49:U50) -> 1251.9004
B52: Infrastructure (2% new EB-5 pool) | C52: =C32 -> 399.73994 | D52: =D32 -> 279.86922 | E52: =E32 -> 229.74322 | F52: =F32 -> 213.05254 | G52: =G32 -> 264.12 | H52: =H32 -> 284 | I52: =I32 -> 284 | J52: =J32 -> 198.8 | M52: Infrastructure (2% new EB-5 pool) | N52: =N32 -> 399.73994 | O52: =O32 -> 279.86922 | P52: =P32 -> 229.74322 | Q52: =Q32 -> 213.05254 | R52: =R32 -> 264.58008 | S52: =S32 -> 213 | T52: =T32 -> 198.8 | U52: =U32 -> 198.8
B53: Carryover unused new from previous FY | C53: 0 | D53: =C52 -> 399.73994 | E53: =D52 -> 279.86922 | F53: =IF(E53>E40,E52,E54-E40) -> 229.74322 | G53: =IF(F53>F40,F52,F54-F40) -> 213.05254 | H53: =IF(G53>G40,G52,G54-G40) -> 264.12 | I53: =IF(H53>H40,H52,H54-H40) -> 14.12 | J53: =IF(I53>I40,I52,I54-I40) -> 24.12 | M53: Carryover unused new from previous FY | N53: 0 | O53: =N52 -> 399.73994 | P53: =O52 -> 279.86922 | Q53: =IF(P53>P40,P52,P54-P40) -> 229.74322 | R53: =IF(Q53>Q40,Q52,Q54-Q40) -> 213.05254 | S53: =IF(R53>R40,R52,R54-R40) -> 264.58008 | T53: =IF(S53>S40,S52,S54-S40) -> 51.58008 | U53: =IF(T53>T40,T52,T54-T40) -> 51.38008
B54: Infrastructure Total Available | C54: =SUM(C52:C53) -> 399.73994 | D54: =SUM(D52:D53) -> 679.60916 | E54: =SUM(E52:E53) -> 509.61244 | F54: =SUM(F52:F53) -> 442.79576 | G54: =SUM(G52:G53) -> 477.17254 | H54: =SUM(H52:H53) -> 548.12 | I54: =SUM(I52:I53) -> 298.12 | J54: =SUM(J52:J53) -> 222.92 | M54: Infrastructure Total Available | N54: =SUM(N52:N53) -> 399.73994 | O54: =SUM(O52:O53) -> 679.60916 | P54: =SUM(P52:P53) -> 509.61244 | Q54: =SUM(Q52:Q53) -> 442.79576 | R54: =SUM(R52:R53) -> 477.63262 | S54: =SUM(S52:S53) -> 477.58008 | T54: =SUM(T52:T53) -> 250.38008 | U54: =SUM(U52:U53) -> 250.18008
B55: Reserved Total With Carryover | C55: =C48+C51+C54 -> 6395.839 | D55: =D48+D51+D54 -> 10873.747 | E55: =E48+E51+E54 -> 8153.799 | F55: =F48+F51+F54 -> 7084.7322 | G55: =G48+G51+G54 -> 7634.0352 | H55: =H48+H51+H54 -> 8769.92 | I55: =I48+I51+I54 -> 4770.92 | J55: =J48+J51+J54 -> 3567.22 | M55: Reserved Total With Carryover | N55: =N48+N51+N54 -> 6395.839 | O55: =O48+O51+O54 -> 10873.747 | P55: =P48+P51+P54 -> 8153.799 | Q55: =Q48+Q51+Q54 -> 7084.7322 | R55: =R48+R51+R54 -> 7641.7957 | S55: =S48+S51+S54 -> 7641.2813 | T55: =T48+T51+T54 -> 4006.0813 | U55: =U48+U51+U54 -> 4005.8813
B56: Reserved Total New Issue | F56: =F46+F49+F52 -> 3408.8406 | M56: Reserved Total New Issue | Q56: =Q46+Q49+Q52 -> 3408.8406
B58: Total Reserve Carryover Available | C58: =C47+C50+C53 -> 0 | D58: =D47+D50+D53 -> 6395.839 | E58: =E47+E50+E53 -> 4477.9075 | F58: =F47+F50+F53 -> 3675.8915 | G58: =G47+G50+G53 -> 3408.8406 | H58: =H47+H50+H53 -> 4225.92 | I58: =I47+I50+I53 -> 226.92 | J58: =J47+J50+J53 -> 386.42 | M58: Total Reserve Carryover Available | N58: =N47+N50+N53 -> 0 | O58: =O47+O50+O53 -> 6395.839 | P58: =P47+P50+P53 -> 4477.9075 | Q58: =Q47+Q50+Q53 -> 3675.8915 | R58: =R47+R50+R53 -> 3408.8406 | S58: =S47+S50+S53 -> 4233.2813 | T58: =T47+T50+T53 -> 825.28128 | U58: =U47+U50+U53 -> 825.08128
B59: Unused Reserved Carryover | C59: =IF(C47-C36>0,C47-C36,0)+IF(C50-C38>0,C50-C38,0)+IF(C53-C40>0,C53-C40,0) -> 0 | D59: =IF(D47-D36>0,D47-D36,0)+IF(D50-D38>0,D50-D38,0)+IF(D53-D40>0,D53-D40,0) -> 6395.839 | E59: =IF(E47-E36>0,E47-E36,0)+IF(E50-E38>0,E50-E38,0)+IF(E53-E40>0,E53-E40,0) -> 4054.9075 | F59: =IF(F47-F36>0,F47-F36,0)+IF(F50-F38>0,F50-F38,0)+IF(F53-F40>0,F53-F40,0) -> 675.89152 | G59: =IF(G47-G36>0,G47-G36,0)+IF(G50-G38>0,G50-G38,0)+IF(G53-G40>0,G53-G40,0) -> 308.84064 | H59: =IF(H47-H36>0,H47-H36,0)+IF(H50-H38>0,H50-H38,0)+IF(H53-H40>0,H53-H40,0) -> 0 | I59: =IF(I47-I36>0,I47-I36,0)+IF(I50-I38>0,I50-I38,0)+IF(I53-I40>0,I53-I40,0) -> 0 | J59: =IF(J47-J36>0,J47-J36,0)+IF(J50-J38>0,J50-J38,0)+IF(J53-J40>0,J53-J40,0) -> 0 | M59: Unused Reserved Carryover | N59: =IF(N47-N36>0,N47-N36,0)+IF(N50-N38>0,N50-N38,0)+IF(N53-N40>0,N53-N40,0) -> 0 | O59: =IF(O47-O36>0,O47-O36,0)+IF(O50-O38>0,O50-O38,0)+IF(O53-O40>0,O53-O40,0) -> 6395.839 | P59: =IF(P47-P36>0,P47-P36,0)+IF(P50-P38>0,P50-P38,0)+IF(P53-P40>0,P53-P40,0) -> 4054.9075 | Q59: =IF(Q47-Q36>0,Q47-Q36,0)+IF(Q50-Q38>0,Q50-Q38,0)+IF(Q53-Q40>0,Q53-Q40,0) -> 675.89152 | R59: =IF(R47-R36>0,R47-R36,0)+IF(R50-R38>0,R50-R38,0)+IF(R53-R40>0,R53-R40,0) -> 308.84064 | S59: =IF(S47-S36>0,S47-S36,0)+IF(S50-S38>0,S50-S38,0)+IF(S53-S40>0,S53-S40,0) -> 0 | T59: =IF(T47-T36>0,T47-T36,0)+IF(T50-T38>0,T50-T38,0)+IF(T53-T40>0,T53-T40,0) -> 0 | U59: =IF(U47-U36>0,U47-U36,0)+IF(U50-U38>0,U50-U38,0)+IF(U53-U40>0,U53-U40,0) -> 0
E60: =E59+E53+E50+E47 -> 8532.815 | F60: =F59+F53+F50+F47 -> 4351.783 | G60: =G59+G53+G50+G47 -> 3717.6813 | H60: =H59+H53+H50+H47 -> 4225.92 | I60: =I59+I53+I50+I47 -> 226.92 | J60: =J59+J53+J50+J47 -> 386.42 | P60: =P59+P53+P50+P47 -> 8532.815 | Q60: =Q59+Q53+Q50+Q47 -> 4351.783 | R60: =R59+R53+R50+R47 -> 3717.6813 | S60: =S59+S53+S50+S47 -> 4233.2813 | T60: =T59+T53+T50+T47 -> 825.28128 | U60: =U59+U53+U50+U47 -> 825.08128
B61: Unreserved + Carryover | C61: 2022 | D61: 2023 | E61: 2024 | F61: 2025 | G61: 2026 | H61: 2027 | I61: 2028 | J61: 2029 | M61: Unreserved + Carryover | N61: 2022 | O61: 2023 | P61: 2024 | Q61: 2025 | R61: 2026 | S61: 2027 | T61: 2028 | U61: 2029
B62: Unreserved (68% new EB-5 pool) | C62: =C29 -> 13591.158 | D62: =D29 -> 9515.5535 | E62: =E29 -> 7811.2695 | F62: =F29 -> 7243.7864 | G62: =G29 -> 8980.08 | H62: =H29 -> 9656 | I62: =I29 -> 9656 | J62: =J29 -> 6759.2 | M62: Unreserved (68% new EB-5 pool) | N62: =N29 -> 13591.158 | O62: =O29 -> 9515.5535 | P62: =P29 -> 7811.2695 | Q62: =Q29 -> 7243.7864 | R62: =R29 -> 8995.7227 | S62: =S29 -> 7242 | T62: =T29 -> 6759.2 | U62: =U29 -> 6759.2
B63: Carryover from Unused Reserved Carryover | D63: =C59 -> 0 | E63: =D59 -> 6395.839 | F63: =E59 -> 4054.9075 | G63: =F59 -> 675.89152 | H63: =G59 -> 308.84064 | I63: =H59 -> 0 | J63: =I59 -> 0 | M63: Carryover from Unused Reserved Carryover | O63: =N59 -> 0 | P63: =O59 -> 6395.839 | Q63: =P59 -> 4054.9075 | R63: =Q59 -> 675.89152 | S63: =R59 -> 308.84064 | T63: =S59 -> 0 | U63: =T59 -> 0
B64: Unreserved Total Available | C64: =SUM(C62:C63) -> 13591.158 | D64: =SUM(D62:D63) -> 9515.5535 | E64: =SUM(E62:E63) -> 14207.109 | F64: =SUM(F62:F63) -> 11298.694 | G64: =SUM(G62:G63) -> 9655.9715 | H64: =SUM(H62:H63) -> 9964.8406 | I64: =SUM(I62:I63) -> 9656 | J64: =SUM(J62:J63) -> 6759.2 | M64: Unreserved Total Available | N64: =SUM(N62:N63) -> 13591.158 | O64: =SUM(O62:O63) -> 9515.5535 | P64: =SUM(P62:P63) -> 14207.109 | Q64: =SUM(Q62:Q63) -> 11298.694 | R64: =SUM(R62:R63) -> 9671.6142 | S64: =SUM(S62:S63) -> 7550.8406 | T64: =SUM(T62:T63) -> 6759.2 | U64: =SUM(U62:U63) -> 6759.2
B66: Total EB-5 Visas Actually Issued | C66: 2022 | D66: 2023 | E66: 2024 | F66: 2025 | G66: 2026 | H66: 2027 | I66: 2028 | J66: 2029 | M66: Total EB-5 Visas Actually Issued | N66: 2022 | O66: 2023 | P66: 2024 | Q66: 2025 | R66: 2026 | S66: 2027 | T66: 2028 | U66: 2029
B67: Unreserved | C67: 10885 | D67: 9817 | E67: =E8 -> 14207.109 | M67: Unreserved | N67: 10885 | O67: 9817 | P67: =P8 -> 14207.109
B75: Unreserved by Country | C75: 2022 | D75: 2023 | E75: 2024 | F75: 2025 | G75: 2026 | H75: 2027
B76: Available to India and China (each) | C76: 0.07 | E76: =E8*0.07 -> 994.4976 | F76: =F8*0.07 -> 790.90857 | G76: =G8*0.07 -> 675.91801 | H76: =H8*0.07 -> 697.53884
B77: Available to ROW, then China extra | C77: =1-0.07*2 -> 0.86 | E77: =E8*$C77 -> 12218.113 | F77: =F8*$C77 -> 9716.8767 | G77: =G8*$C77 -> 8304.1355 | H77: =H8*$C77 -> 8569.763
E78: =SUM(E76:E77) -> 13212.611 | F78: =SUM(F76:F77) -> 10507.785 | G78: =SUM(G76:G77) -> 8980.0535 | H78: =SUM(H76:H77) -> 9267.3018
B79: Rural Set Aside by Country
B80: Available to India and China (each) | C80: 0.07 | E80: =E$9*$C80 -> 356.72871 | F80: =F$9*$C80 -> 309.95703 | G80: =G$9*$C80 -> 333.97 | H80: =H$9*$C80 -> 383.684 | I80: =SUM(F80:H80) -> 1027.611
B81: Available to ROW, then China and India extra | C81: =1-0.07*2 -> 0.86 | E81: =E$9*$C81 -> 4382.667 | F81: =F$9*$C81 -> 3808.0435 | G81: =G$9*$C81 -> 4103.06 | H81: =H$9*$C81 -> 4713.832 | I81: =SUM(F81:H81) -> 12624.936
E82: =E80*2+E81 -> 5096.1244 | F82: =F80*2+F81 -> 4427.9576 | G82: =G80*2+G81 -> 4771 | H82: =H80*2+H81 -> 5481.2 | I82: =I80*2+I81 -> 14680.158
B83: HU Set Aside by Country
B84: Available to India and China (each) | C84: 0.07 | E84: =E$10*$C84 -> 178.36435 | F84: =F$10*$C84 -> 154.97852 | G84: =G$10*$C84 -> 167.01039 | H84: =H$10*$C84 -> 191.842 | I84: =SUM(F84:H84) -> 513.83091
B85: Available to ROW, then China and India extra | C85: =1-0.07*2 -> 0.86 | E85: =E$10*$C85 -> 2191.3335 | F85: =F$10*$C85 -> 1904.0218 | G85: =G$10*$C85 -> 2051.8419 | H85: =H$10*$C85 -> 2356.916 | I85: =SUM(F85:H85) -> 6312.7797
E86: =E84*2+E85 -> 2548.0622 | F86: =F84*2+F85 -> 2213.9788 | G86: =G84*2+G85 -> 2385.8627 | H86: =H84*2+H85 -> 2740.6 | I86: =I84*2+I85 -> 7340.4415
B92: Reserved Carryover | D92: =C30 -> 3997.3994 | E92: =D30 -> 2798.6922 | F92: =E30 -> 2297.4322 | G92: =F30 -> 2130.5254
B93: Unreserved Carryover | E93: =D92 -> 3997.3994 | F93: =E92 -> 2798.6922 | G93: =F92 -> 2297.4322
B94: Unreserved Total | C94: =C29+C93 -> 13591.158 | D94: =D29+D93 -> 9515.5535 | E94: =E29+E93 -> 11808.669 | F94: =F29+F93 -> 10042.479 | G94: =G29+G93 -> 11277.512
B95: Reserved Total | C95: =C30+C92 -> 3997.3994 | D95: =D30+D92 -> 6796.0916 | E95: =E30+E92 -> 5096.1244 | F95: =F30+F92 -> 4427.9576 | G95: =G30+G92 -> 4771.7254
B96: All EB-5 Visas Available | C96: =C94+C95 -> 17588.557 | D96: =D94+D95 -> 16311.645 | E96: =E94+E95 -> 16904.793 | F96: =F94+F95 -> 14470.436 | G96: =G94+G95 -> 16049.238

Sheet Pre-RIA China
B1: Visa Timing ESTIMATE -- CHINA Unreserved
B3: Background
B4: Estimated total Pre-RIA EB-5 Unreserved pipeline backlog
C5: China | D5: India | E5: ROW | F5: Total
B6: as of June 2025
C8: 0.4 | D8: Average pre-RIA I-526 approval rate in 2024 for China
C9: 2.5359256 | D9: Average visas per investor applicant in 2021-2023 (worldwide, AOS+consular)
C11: China | D11: China
B12: Visa Bulletin | C12: Chart A | D12: Chart B
B13: 44835 | C13: 42085 | D13: 42370
B14: 45200 | C14: 42278 | D14: 42736
B15: 45566 | C15: 42566 | D15: 42644
B16: 45931 | C16: 42346 | D16: 42552
B18: Unreserved China VISA DEMAND ESTIMATE as of June 2024 | G18: =C8*C9 -> 1.0143702 | M18: Unreserved VISA SUPPLY ESTIMATE from June 2024
E19: A | F19: B | G19: C | H19: D=A+B+C | I19: E | K19: MATCH DEMAND to SUPPLY | N19: A | O19: B | P19: C | Q19: D | R19: E | S19: F=A-B-C-D-E
B20: Priority Date | C20: I-526 Filed (actual until 10/2020, estimate for 2021-2022) | D20: I-526 Pending as of 7/2024 (actual) | E20: Applicants registered at NVC as of 5/2024 (quarterly estimate from actual annual) | F20: I-485 Pending as of 6/2024 (actual) | G20: Estimate of future visa applicants from pending I-526 as of 7/2024 | H20: Estimated Total Visa Applicants as of June 2024 | I20: Estimated Cumulative Visa Applicants | J20: Visa availability per Oct 24 Visa Bulletin | K20: Date of visa availability per supply-demand ESTIMATE | M20: Date of visa issuance | N20: Total Unreserved visas (est.) | O20: Visas issued to Pre-RIA India up to cap | P20: Visas issued to Post-RIA India up to cap | Q20: Estimated visas issued to Pre-RIA ROW | R20: Post-RIA ROW (GUESS)* | S20: Estimated total visas issued to Pre-RIA China | T20: Cumulative Total to China
B21: Pre-2015 | D21: 6 | E21: 588 | F21: 0 | G21: =D21*G$18 -> 6.0862215 | H21: =SUM(E21:G21) -> 594.08622 | I21: =H21 -> 594.08622 | J21: current | K21: =_xlfn.XLOOKUP(I21,$T$22:$T$30,$U$22:$U$30,"FY25 and earlier",-1) -> FY25 and earlier | M21: 2024 June-Sept | O21: 130 | Q21: 1300 | S21: 4470 | T21: =S21 -> 4470
B22: 2015 Q1. Oct - Dec 2014 | C22: 2783.0277 | D22: 1 | F22: 0 | G22: =D22*G$18 -> 1.0143702 | H22: =SUM(E22:G22) -> 1.0143702 | I22: =H22+I21 -> 595.10059 | J22: current | K22: =_xlfn.XLOOKUP(I22,$T$22:$T$30,$U$22:$U$30,"FY25 and earlier",-1) -> FY25 and earlier | M22: FY2025 | N22: 11469.908 | O22: =N22*0.07 -> 802.89353 | Q22: 5000 | R22: 50 | S22: =N22-O22-P22-Q22-R22 -> 5617.014 | T22: =T21+S22 -> 10087.014 | U22: FY2025
B23: 2015 Q2. Jan - Mar 2015 | C23: 2184.9748 | D23: 1 | E23: 1286.518 | F23: 0 | G23: =D23*G$18 -> 1.0143702 | H23: =SUM(E23:G23) -> 1287.5324 | I23: =H23+I22 -> 1882.633 | J23: current | K23: =_xlfn.XLOOKUP(I23,$T$22:$T$30,$U$22:$U$30,"FY25 and earlier",-1) -> FY25 and earlier | M23: FY2026 | N23: 12000 | O23: =N23*0.07 -> 840 | Q23: 3300 | R23: 700 | S23: =N23-O23-P23-Q23-R23 -> 7160 | T23: =T22+S23 -> 17247.014 | U23: FY2026
B24: 2015 Q3 Apr - Jun 2015 | C24: 2340.1658 | D24: 3 | E24: 1377.8948 | F24: 14 | G24: =D24*G$18 -> 3.0431107 | H24: =SUM(E24:G24) -> 1394.9379 | I24: =H24+I23 -> 3277.5709 | J24: current | K24: =_xlfn.XLOOKUP(I24,$T$22:$T$30,$U$22:$U$30,"FY25 and earlier",-1) -> FY25 and earlier | M24: FY2027 | N24: 10000 | O24: =N24*0.07 -> 700 | R24: 3500 | S24: =N24-O24-P24-Q24-R24 -> 5800 | T24: =T23+S24 -> 23047.014 | U24: FY2027
B25: 2015 Q4 Jul - Sep 2015 | C25: 6221.8317 | D25: 28 | E25: 3663.4283 | F25: 89 | G25: =D25*G$18 -> 28.402367 | H25: =SUM(E25:G25) -> 3780.8307 | I25: =H25+I24 -> 7058.4016 | J25: current | K25: =_xlfn.XLOOKUP(I25,$T$22:$T$30,$U$22:$U$30,"FY25 and earlier",-1) -> FY25 and earlier | M25: FY2028 | N25: 6800 | O25: =N25*0.07 -> 476 | R25: 3500 | S25: =N25-O25-P25-Q25-R25 -> 2824 | T25: =T24+S25 -> 25871.014 | U25: FY2028
B26: 2016 Q1 Oct - Dec 2015 | C26: 3808 | D26: 33 | E26: 2242.1589 | F26: 118 | G26: =D26*G$18 -> 33.474218 | H26: =SUM(E26:G26) -> 2393.6331 | I26: =H26+I25 -> 9452.0347 | J26: current | K26: =_xlfn.XLOOKUP(I26,$T$22:$T$30,$U$22:$U$30,"FY25 and earlier",-1) -> FY25 and earlier | M26: FY2029 | N26: 6800 | O26: =N26*0.07 -> 476 | R26: =R25 -> 3500 | S26: =N26-O26-P26-Q26-R26 -> 2824 | T26: =T25+S26 -> 28695.014 | U26: FY2029
B27: 2016 Q2 Jan - Mar 2016 | C27: 391 | D27: 4 | E27: 545.90335 | F27: 98 | G27: =D27*G$18 -> 4.057481 | H27: =SUM(E27:G27) -> 647.96083 | I27: =H27+I26 -> 10099.995 | J27: current | K27: =_xlfn.XLOOKUP(I27,$T$22:$T$30,$U$22:$U$30,"FY25 and earlier",-1) -> FY2025 | M27: FY2030 | N27: 6800 | O27: 363 | P27: 113 | R27: =R26 -> 3500 | S27: =N27-O27-P27-Q27-R27 -> 2824 | T27: =T26+S27 -> 31519.014 | U27: FY2030
B28: 2016 Q3 April - June 2016 | C28: 1415 | D28: 20 | E28: 1975.5837 | F28: 332 | G28: =D28*G$18 -> 20.287405 | H28: =SUM(E28:G28) -> 2327.8711 | I28: =H28+I27 -> 12427.867 | J28: current | K28: =_xlfn.XLOOKUP(I28,$T$22:$T$30,$U$22:$U$30,"FY25 and earlier",-1) -> FY2025 | M28: FY2031 | N28: 6800 | P28: =N28*0.07 -> 476 | R28: =R27 -> 3500 | S28: =N28-O28-P28-Q28-R28 -> 2824 | T28: =T27+S28 -> 34343.014 | U28: FY2031
B29: 2016 Q4 Jul - Sep 2016 | C29: 5334 | D29: 79 | E29: 7447.1828 | F29: 1165 | G29: =D29*G$18 -> 80.135249 | H29: =SUM(E29:G29) -> 8692.318 | I29: =H29+I28 -> 21120.185 | J29: 2025/2026 | K29: =_xlfn.XLOOKUP(I29,$T$22:$T$30,$U$22:$U$30,"FY25 and earlier",-1) -> FY2026 | M29: FY2032 | N29: 6800 | P29: =N29*0.07 -> 476 | R29: =R28 -> 3500 | S29: =N29-O29-P29-Q29-R29 -> 2824 | T29: =T28+S29 -> 37167.014 | U29: FY2032
B30: 2017 Q1 Oct - Dec 2016 | C30: 3310 | D30: 87 | E30: 4621.3301 | F30: 782 | G30: =D30*G$18 -> 88.250211 | H30: =SUM(E30:G30) -> 5491.5804 | I30: =H30+I29 -> 26611.765 | K30: =_xlfn.XLOOKUP(I30,$T$22:$T$30,$U$22:$U$30,"FY25 and earlier",-1) -> FY2028 | M30: FY2033 | N30: 6800 | P30: =N30*0.07 -> 476 | R30: =R29 -> 3500 | S30: =N30-O30-P30-Q30-R30 -> 2824 | T30: =T29+S30 -> 39991.014 | U30: FY2033
B31: 2017 Q2. Jan - Mar 2017 | C31: 1172 | D31: 94 | E31: 1198.9144 | F31: 0 | G31: =D31*G$18 -> 95.350803 | H31: =SUM(E31:G31) -> 1294.2652 | I31: =H31+I30 -> 27906.03 | K31: =_xlfn.XLOOKUP(I31,$T$22:$T$30,$U$22:$U$30,"FY25 and earlier",-1) -> FY2028 | M31: Total | O31: =SUM(O21:O30) -> 3787.8935 | Q31: =SUM(Q21:Q30) -> 9600
B32: 2017 Q3. April - June 2017 | C32: 3280 | D32: 430 | E32: 3355.3236 | F32: 0 | G32: =D32*G$18 -> 436.17921 | H32: =SUM(E32:G32) -> 3791.5028 | I32: =H32+I31 -> 31697.533 | K32: =_xlfn.XLOOKUP(I32,$T$22:$T$30,$U$22:$U$30,"FY25 and earlier",-1) -> FY2030 | O32: =D6 | Q32: =E6
B33: 2017 Q4 Jul - Sep 2017 | C33: 1009 | D33: 243 | E33: 1032.1712 | F33: 0 | G33: =D33*G$18 -> 246.49197 | H33: =SUM(E33:G33) -> 1278.6632 | I33: =H33+I32 -> 32976.196 | K33: =_xlfn.XLOOKUP(I33,$T$22:$T$30,$U$22:$U$30,"FY25 and earlier",-1) -> FY2030 | M33: *Guess assumes that post-RIA ROW applicants will increasingly choose to be assigned Unreserved visas
B34: 2018 Q1 Oct - Dec 2017 | C34: 1245 | D34: 326 | E34: 1273.5908 | F34: 0 | G34: =D34*G$18 -> 330.6847 | H34: =SUM(E34:G34) -> 1604.2755 | I34: =H34+I33 -> 34580.472 | K34: =_xlfn.XLOOKUP(I34,$T$22:$T$30,$U$22:$U$30,"FY25 and earlier",-1) -> FY2031 | M34: and that 2024 ROW demand was/will be typical
B35: 2018 Q2. Jan - Mar 2018 | C35: 696 | D35: 358 | E35: 302 | F35: 0 | G35: =D35*G$18 -> 363.14455 | H35: =SUM(E35:G35) -> 665.14455 | I35: =H35+I34 -> 35245.616 | K35: =_xlfn.XLOOKUP(I35,$T$22:$T$30,$U$22:$U$30,"FY25 and earlier",-1) -> FY2031 | M35: Estimated Status of Chinese investors with October 2014+ priority dates, as of October 2024
B36: 2018 Q3. April - June 2018 | C36: 207 | D36: 154 | E36: 89.818966 | F36: 0 | G36: =D36*G$18 -> 156.21302 | H36: =SUM(E36:G36) -> 246.03198 | I36: =H36+I35 -> 35491.648 | K36: =_xlfn.XLOOKUP(I36,$T$22:$T$30,$U$22:$U$30,"FY25 and earlier",-1) -> FY2031 | M36: Visas issued to date to China-born applicants with priority dates since Oct 2014*
B37: 2018 Q4 Jul - Sep 2018 | C37: 294 | D37: 277 | E37: 127.56897 | F37: 0 | G37: =D37*G$18 -> 280.98056 | H37: =SUM(E37:G37) -> 408.54952 | I37: =H37+I36 -> 35900.198 | K37: =_xlfn.XLOOKUP(I37,$T$22:$T$30,$U$22:$U$30,"FY25 and earlier",-1) -> FY2031 | R37: Year visa issued | S37: EB-5 Visas Issued to China
B38: 2019 Q1 Oct - Dec 2018 | C38: 195 | D38: 144 | E38: 84.612069 | F38: 0 | G38: =D38*G$18 -> 146.06932 | H38: =SUM(E38:G38) -> 230.68138 | I38: =H38+I37 -> 36130.879 | K38: =_xlfn.XLOOKUP(I38,$T$22:$T$30,$U$22:$U$30,"FY25 and earlier",-1) -> FY2031 | R38: FY2020 | S38: 1686
B39: 2019 Q2. Jan - Mar 2019 | C39: 118 | D39: 99 | E39: 0 | F39: 0 | G39: =D39*G$18 -> 100.42265 | H39: =SUM(E39:G39) -> 100.42265 | I39: =H39+I38 -> 36231.302 | K39: =_xlfn.XLOOKUP(I39,$T$22:$T$30,$U$22:$U$30,"FY25 and earlier",-1) -> FY2031 | R39: FY2021 | S39: 1567
B40: 2019 Q3. April - June 2019 | C40: 91 | D40: 80 | E40: 0 | F40: 0 | G40: =D40*G$18 -> 81.14962 | H40: =SUM(E40:G40) -> 81.14962 | I40: =H40+I39 -> 36312.451 | K40: =_xlfn.XLOOKUP(I40,$T$22:$T$30,$U$22:$U$30,"FY25 and earlier",-1) -> FY2031 | R40: FY2022 | S40: 6125
B41: 2019 Q4 Jul - Sep 2019 | C41: 118 | D41: 97 | E41: 0 | F41: 0 | G41: =D41*G$18 -> 98.393914 | H41: =SUM(E41:G41) -> 98.393914 | I41: =H41+I40 -> 36410.845 | K41: =_xlfn.XLOOKUP(I41,$T$22:$T$30,$U$22:$U$30,"FY25 and earlier",-1) -> FY2031 | R41: FY2023 | S41: 6262
B42: 2020 Q1 Oct - Dec 2019 | C42: 416 | D42: 369 | E42: 31 | F42: 0 | G42: =D42*G$18 -> 374.30262 | H42: =SUM(E42:G42) -> 405.30262 | I42: =H42+I41 -> 36816.148 | K42: =_xlfn.XLOOKUP(I42,$T$22:$T$30,$U$22:$U$30,"FY25 and earlier",-1) -> FY2031 | R42: FY2024 | S42: 9312
B43: 2020 Q2 Jan - Mar 2020 | C43: 3 | D43: 2 | E43: 0 | F43: 0 | G43: =D43*G$18 -> 2.0287405 | H43: =SUM(E43:G43) -> 2.0287405 | I43: =H43+I42 -> 36818.177 | K43: =_xlfn.XLOOKUP(I43,$T$22:$T$30,$U$22:$U$30,"FY25 and earlier",-1) -> FY2031 | S43: =SUM(S38:S42) -> 24952
B44: 2020 Q3 Apr - Jun 2020 | C44: 2 | D44: 2 | E44: 0 | F44: 0 | G44: =D44*G$18 -> 2.0287405 | H44: =SUM(E44:G44) -> 2.0287405 | I44: =H44+I43 -> 36820.205 | K44: =_xlfn.XLOOKUP(I44,$T$22:$T$30,$U$22:$U$30,"FY25 and earlier",-1) -> FY2031 | M44: *The Visa Bulletin first moved the China final action date past Oct 1, 2014 at the end of FY2019 (August 2019).
B45: 2020 Q4 Jul - Sep 2020 | C45: 7 | D45: 6 | E45: 0 | F45: 0 | G45: =D45*G$18 -> 6.0862215 | H45: =SUM(E45:G45) -> 6.0862215 | I45: =H45+I44 -> 36826.292 | K45: =_xlfn.XLOOKUP(I45,$T$22:$T$30,$U$22:$U$30,"FY25 and earlier",-1) -> FY2031 | M45: Therefore, China EB-5 visas issued since FY2020 may have gone to FY2014 and later priority dates.
B46: 2021 Q1 Oct - Dec 2020 | C46: =D46 -> 7 | D46: 7 | E46: 0 | F46: 0 | G46: =D46*G$18 -> 7.1005917 | H46: =SUM(E46:G46) -> 7.1005917 | I46: =H46+I45 -> 36833.392 | K46: =_xlfn.XLOOKUP(I46,$T$22:$T$30,$U$22:$U$30,"FY25 and earlier",-1) -> FY2031 | M46: Average % of visas to investors 2021-2023 | R46: =1/C9 -> 0.39433333
B47: 2021 Q2 Jan - Mar 2021 | C47: =D47 -> 6 | D47: 6 | E47: 0 | F47: 0 | G47: =D47*G$18 -> 6.0862215 | H47: =SUM(E47:G47) -> 6.0862215 | I47: =H47+I46 -> 36839.478 | K47: =_xlfn.XLOOKUP(I47,$T$22:$T$30,$U$22:$U$30,"FY25 and earlier",-1) -> FY2031
B48: 2021 Q3 Apr - Jun 2021 | C48: =D48 -> 9 | D48: 9 | E48: 0 | F48: 0 | G48: =D48*G$18 -> 9.1293322 | H48: =SUM(E48:G48) -> 9.1293322 | I48: =H48+I47 -> 36848.608 | K48: =_xlfn.XLOOKUP(I48,$T$22:$T$30,$U$22:$U$30,"FY25 and earlier",-1) -> FY2031 | M48: Estimated Chinese with priority dates from Oct 2014… | R48: Investors Only | S48: Investors + family
B49: 2021 Q4 Jul - Sep 2021 | C49: =D49 -> 0 | D49: 0 | E49: 0 | F49: 0 | G49: =D49*G$18 -> 0 | H49: =SUM(E49:G49) -> 0 | I49: =H49+I48 -> 36848.608 | K49: =_xlfn.XLOOKUP(I49,$T$22:$T$30,$U$22:$U$30,"FY25 and earlier",-1) -> FY2031 | Q49: …who started the process by filing I-526 | R49: =SUM(C22:C51) -> 36672 | S49: =R49/R46 -> 92997.464 | T49: =S49/S$49 -> 1
B50: 2022 Q1 Oct - Dec 2021 | C50: =D50 -> 1 | D50: 1 | E50: 0 | F50: 0 | G50: =D50*G$18 -> 1.0143702 | H50: =SUM(E50:G50) -> 1.0143702 | I50: =H50+I49 -> 36849.622 | K50: =_xlfn.XLOOKUP(I50,$T$22:$T$30,$U$22:$U$30,"FY25 and earlier",-1) -> FY2031 | Q50: …who have visas by Oct 2024 | R50: =S50*R46 -> 9839.4053 | S50: =S43 -> 24952 | T50: =S50/S$49 -> 0.26830839
B51: 2022 Q2 Jan - Mar 2022 | C51: =D51 -> 8 | D51: 8 | F51: 0 | G51: =D51*G$18 -> 8.114962 | H51: =SUM(E51:G51) -> 8.114962 | I51: =H51+I50 -> 36857.737 | K51: =_xlfn.XLOOKUP(I51,$T$22:$T$30,$U$22:$U$30,"FY25 and earlier",-1) -> FY2031 | Q51: …who are still waiting for visas in Oct 2024 | R51: =S51*R46 -> 14534.234 | S51: =SUM(H21:H51) -> 36857.737 | T51: =S51/S$49 -> 0.39633056
E52: =SUM(E21:E51) -> 31243 | F52: =SUM(F21:F51) -> 2598 | G52: =SUM(G21:G51) -> 3016.7371 | Q52: …who withdrew/were denied by Oct 2024 | R52: =R49-R50-R51 -> 12298.36 | S52: =S49-S50-S51 -> 31187.727 | T52: =S52/S$49 -> 0.33536105
B54: Sources
B55: NVC applicants | C55: https://iiusa.org/wp-content/uploads/2024/06/Insights-from-DOS-Recap-of-2024-IIUSA-EB-5-Forum-1.pdf
B56: I-485 pending | C56: https://www.uscis.gov/sites/default/files/document/reports/eb_inventory_june_2024_081324.xlsx
B57: I-526 pending | C57: https://goaiia.org/aiia-foia-series-pre-ria-i-526-data-as-of-july-2024/
B58: I-526 receipts | C58: Multiple sources. See the Pre-RIA tab in my Key EB-5 Backlog data file https://www.dropbox.com/s/ua9g9iigru2z6u1/Key%20EB5%20Backlog%20Data.xlsx?dl=0

Sheet Pre-RIA India
B1: Visa Timing ESTIMATE -- INDIA Unreserved
B3: Background
B4: Estimated total Pre-RIA EB-5 Unreserved pipeline backlog
C5: China | D5: India | E5: ROW | F5: Total
B6: as of June 2025
D8: 0.82 | E8: Average pre-RIA I-526 approval rate in 2024
D9: 2.5359256 | E9: Average visas per investor applicant in 2021-2023 (worldwide, AOS+consular)
D10: 0.55 | E10: Average % of visas issued through consulates (2018-2023)
C12: India | D12: India
B13: Visa Bulletin | C13: Chart A | D13: Chart B
B14: 44835 | C14: 43777 | D14: 43807
B15: 45200 | C15: 43449 | D15: 44652
B16: 45566 | C16: 44562 | D16: 44652
B17: 45931 | C17: 44228 | D17: 44652
B19: Unreserved India VISA DEMAND ESTIMATE as of June 2024 | G19: =D8*D9*D10 -> 1.1437025 | M19: VISA SUPPLY ESTIMATE from June 2024
B20: data as of date | E20: A | F20: B | G20: C | H20: D=A+B+C | K20: MATCH DEMAND to SUPPLY | O20: 0.07
B21: Priority Date | C21: I-526 Filed (actual) | D21: I-526 Pending as of 7/2024 (actual) | E21: Applicants registered at NVC as of 5/2024 (quarterly estimate from actual annual) | F21: I-485 Pending as of 6/2024 (actual) | G21: Estimate of future consular visa applicants from pending I-526 as of 7/2024 | H21: Estimated Total Visa Applicants as of June 2024 | I21: Estimated Cumulative Visa Applicants | J21: Visa availability per Oct 24 Visa Bulletin | K21: Date of visa availability per supply-demand ESTIMATE | M21: Date of visa issuance | N21: Total Unreserved visas (est.) | O21: Visas issued to India (estimated total)* | P21: Estimated Cumulative Total to India
B22: Pre-FY2017 | D22: 0 | E22: 51 | G22: =D22*G$19 -> 0 | H22: =SUM(E22:G22) -> 51 | I22: =H22 -> 51 | J22: current | K22: =_xlfn.XLOOKUP(I22,$P$22:$P$29,$Q$22:$Q$29,"FY24 and earlier",-1) -> FY24 and earlier | M22: 2024 June-Sept | O22: 130.35 | P22: =O22 -> 130.35 | Q22: FY2024
B23: 2017 Q2. Jan - Mar 2017 | C23: 42 | D23: 0 | E23: 6.784217 | G23: =D23*G$19 -> 0 | H23: =SUM(E23:G23) -> 6.784217 | I23: =I22+H23 -> 57.784217 | J23: current | K23: =_xlfn.XLOOKUP(I23,$P$22:$P$29,$Q$22:$Q$29,"FY24 and earlier",-1) -> FY24 and earlier | M23: FY2025 | N23: 11470 | O23: 900 | P23: =P22+O23 -> 1030.35 | Q23: FY2025
B24: 2017 Q3. April - June 2017 | C24: 261 | D24: 1 | E24: 42.159063 | G24: =D24*G$19 -> 1.1437025 | H24: =SUM(E24:G24) -> 43.302765 | I24: =I23+H24 -> 101.08698 | J24: current | K24: =_xlfn.XLOOKUP(I24,$P$22:$P$29,$Q$22:$Q$29,"FY24 and earlier",-1) -> FY24 and earlier | M24: FY2026 | N24: 7300 | O24: =N24*O$20 -> 511 | P24: =P23+O24 -> 1541.35 | Q24: FY2026
B25: 2017 Q4 Jul - Sep 2017 | C25: 127 | D25: 0 | E25: 20.51418 | G25: =D25*G$19 -> 0 | H25: =SUM(E25:G25) -> 20.51418 | I25: =I24+H25 -> 121.60116 | J25: current | K25: =_xlfn.XLOOKUP(I25,$P$22:$P$29,$Q$22:$Q$29,"FY24 and earlier",-1) -> FY24 and earlier | M25: FY2027 | N25: 6800 | O25: =N25*O$20 -> 476 | P25: =P24+O25 -> 2017.35 | Q25: FY2027
B26: 2018 Q1 Oct - Dec 2017 | C26: 381 | D26: 1 | E26: 61.54254 | G26: =D26*G$19 -> 1.1437025 | H26: =SUM(E26:G26) -> 62.686243 | I26: =I25+H26 -> 184.2874 | J26: current | K26: =_xlfn.XLOOKUP(I26,$P$22:$P$29,$Q$22:$Q$29,"FY24 and earlier",-1) -> FY2024 | M26: FY2028 | N26: 6800 | O26: =N26*O$20 -> 476 | P26: =P25+O26 -> 2493.35 | Q26: FY2028
B27: 2018 Q2. Jan - Mar 2018 | C27: 283 | D27: 0 | E27: 179.41674 | G27: =D27*G$19 -> 0 | H27: =SUM(E27:G27) -> 179.41674 | I27: =I26+H27 -> 363.70414 | J27: current | K27: =_xlfn.XLOOKUP(I27,$P$22:$P$29,$Q$22:$Q$29,"FY24 and earlier",-1) -> FY2024 | M27: FY2029 | N27: 6800 | O27: =N27*O$20 -> 476 | P27: =P26+O27 -> 2969.35 | Q27: FY2029
B28: 2018 Q3. April - June 2018 | C28: 127 | D28: 0 | E28: 80.515638 | G28: =D28*G$19 -> 0 | H28: =SUM(E28:G28) -> 80.515638 | I28: =I27+H28 -> 444.21978 | J28: current | K28: =_xlfn.XLOOKUP(I28,$P$22:$P$29,$Q$22:$Q$29,"FY24 and earlier",-1) -> FY2024 | M28: FY2030 | N28: 6800 | O28: =N28*O$20 -> 476 | P28: =P27+O28 -> 3445.35 | Q28: FY2030
B29: 2018 Q4 Jul - Sep 2018 | C29: 330 | D29: 3 | E29: 209.21386 | G29: =D29*G$19 -> 3.4311074 | H29: =SUM(E29:G29) -> 212.64497 | I29: =I28+H29 -> 656.86475 | J29: current | K29: =_xlfn.XLOOKUP(I29,$P$22:$P$29,$Q$22:$Q$29,"FY24 and earlier",-1) -> FY2024 | M29: FY2031 | N29: 6800 | O29: =N29*O$20 -> 476 | P29: =P28+O29 -> 3921.35 | Q29: FY2031
B30: 2019 Q1 Oct - Dec 2018 | C30: 443 | D30: 1 | E30: 280.85376 | F30: 45 | G30: =D30*G$19 -> 1.1437025 | H30: =SUM(E30:G30) -> 326.99746 | I30: =I29+H30 -> 983.86221 | J30: current | K30: =_xlfn.XLOOKUP(I30,$P$22:$P$29,$Q$22:$Q$29,"FY24 and earlier",-1) -> FY2024
B31: 2019 Q2. Jan - Mar 2019 | C31: 155 | D31: 7 | E31: 93.769282 | F31: 23 | G31: =D31*G$19 -> 8.0059172 | H31: =SUM(E31:G31) -> 124.7752 | I31: =I30+H31 -> 1108.6374 | J31: current | K31: =_xlfn.XLOOKUP(I31,$P$22:$P$29,$Q$22:$Q$29,"FY24 and earlier",-1) -> FY2025
B32: 2019 Q3. April - June 2019 | C32: 180 | D32: 3 | E32: 108.89336 | F32: 44 | G32: =D32*G$19 -> 3.4311074 | H32: =SUM(E32:G32) -> 156.32447 | I32: =I31+H32 -> 1264.9619 | J32: current | K32: =_xlfn.XLOOKUP(I32,$P$22:$P$29,$Q$22:$Q$29,"FY24 and earlier",-1) -> FY2025 | M32: *Assumes India limited to 7% of visas for this period -- considering that the earlier China backlog has priority for any extra Unreserved visas, and is not predicted to clear until after 2031
B33: 2019 Q4 Jul - Sep 2019 | C33: 249 | D33: 9 | E33: 150.63581 | F33: 99 | G33: =D33*G$19 -> 10.293322 | H33: =SUM(E33:G33) -> 259.92914 | I33: =I32+H33 -> 1524.891 | J33: current | K33: =_xlfn.XLOOKUP(I33,$P$22:$P$29,$Q$22:$Q$29,"FY24 and earlier",-1) -> FY2025
B34: 2020 Q1 Oct - Dec 2019 | C34: 907 | D34: 153 | E34: 548.70154 | F34: 404 | G34: =D34*G$19 -> 174.98648 | H34: =SUM(E34:G34) -> 1127.688 | I34: =I33+H34 -> 2652.579 | J34: current | K34: =_xlfn.XLOOKUP(I34,$P$22:$P$29,$Q$22:$Q$29,"FY24 and earlier",-1) -> FY2028
B35: 2020 Q2 Jan - Mar 2020 | C35: 6 | D35: 3 | E35: 0 | F35: 0 | G35: =D35*G$19 -> 3.4311074 | H35: =SUM(E35:G35) -> 3.4311074 | I35: =I34+H35 -> 2656.0101 | J35: current | K35: =_xlfn.XLOOKUP(I35,$P$22:$P$29,$Q$22:$Q$29,"FY24 and earlier",-1) -> FY2028
B36: 2020 Q3 Apr - Jun 2020 | C36: 11 | D36: 0 | E36: 2 | F36: 0 | G36: =D36*G$19 -> 0 | H36: =SUM(E36:G36) -> 2 | I36: =I35+H36 -> 2658.0101 | J36: current | K36: =_xlfn.XLOOKUP(I36,$P$22:$P$29,$Q$22:$Q$29,"FY24 and earlier",-1) -> FY2028 | R36: =SUM(R23:R34) -> 0
B37: 2020 Q4 Jul - Sep 2020 | C37: 11 | D37: 2 | E37: 2 | F37: 0 | G37: =D37*G$19 -> 2.2874049 | H37: =SUM(E37:G37) -> 4.2874049 | I37: =I36+H37 -> 2662.2975 | J37: current | K37: =_xlfn.XLOOKUP(I37,$P$22:$P$29,$Q$22:$Q$29,"FY24 and earlier",-1) -> FY2028
B38: 2021 Q1 Oct - Dec 2020 | C38: 10 | D38: 2 | E38: 0 | F38: 0 | G38: =D38*G$19 -> 2.2874049 | H38: =SUM(E38:G38) -> 2.2874049 | I38: =I37+H38 -> 2664.585 | J38: current | K38: =_xlfn.XLOOKUP(I38,$P$22:$P$29,$Q$22:$Q$29,"FY24 and earlier",-1) -> FY2028
B39: 2021 Q2 Jan - Mar 2021 | C39: 22 | D39: 6 | E39: 0 | F39: 0 | G39: =D39*G$19 -> 6.8622147 | H39: =SUM(E39:G39) -> 6.8622147 | I39: =I38+H39 -> 2671.4472 | J39: current | K39: =_xlfn.XLOOKUP(I39,$P$22:$P$29,$Q$22:$Q$29,"FY24 and earlier",-1) -> FY2028
B40: 2021 Q3 Apr - Jun 2021 | C40: 180 | D40: 90 | E40: 44 | F40: 94 | G40: =D40*G$19 -> 102.93322 | H40: =SUM(E40:G40) -> 240.93322 | I40: =I39+H40 -> 2912.3804 | J40: current | K40: =_xlfn.XLOOKUP(I40,$P$22:$P$29,$Q$22:$Q$29,"FY24 and earlier",-1) -> FY2028
B41: 2021 Q4 Jul - Sep 2021 | C41: 37 | D41: 19 | E41: 0 | F41: 22 | G41: =D41*G$19 -> 21.730347 | H41: =SUM(E41:G41) -> 43.730347 | I41: =I40+H41 -> 2956.1107 | J41: current | K41: =_xlfn.XLOOKUP(I41,$P$22:$P$29,$Q$22:$Q$29,"FY24 and earlier",-1) -> FY2028
B42: 2022 Q1 Oct - Dec 2021 | C42: 70 | D42: 25 | E42: 0 | F42: 69 | G42: =D42*G$19 -> 28.592561 | H42: =SUM(E42:G42) -> 97.592561 | I42: =I41+H42 -> 3053.7033 | J42: current | K42: =_xlfn.XLOOKUP(I42,$P$22:$P$29,$Q$22:$Q$29,"FY24 and earlier",-1) -> FY2029
B43: 2022 Q2 Jan - Mar 2022 | C43: 195 | D43: 148 | F43: 160 | G43: =D43*G$19 -> 169.26796 | H43: =SUM(E43:G43) -> 329.26796 | I43: =I42+H43 -> 3382.9713 | J43: 2025/2026 | K43: =_xlfn.XLOOKUP(I43,$P$22:$P$29,$Q$22:$Q$29,"FY24 and earlier",-1) -> FY2029
C44: =SUM(C22:C43) -> 4027 | D44: =SUM(D22:D43) -> 473 | E44: =SUM(E22:E43) -> 1882 | F44: =SUM(F22:F43) -> 960 | G44: =SUM(G22:G43) -> 540.97126

Sheet Derivatives
A1: Data for EB-5 Derivatives
A3: Summary
B4: % principals | E4: Average visas per principal
B5: Average 2017-2024 | E5: Average 2017-2024
B6: Consular | C6: AOS | D6: Total | E6: Consular | F6: AOS | G6: All
A7: China | B7: =AVERAGE(B16:B22) -> 0.38128571 | E7: =1/B7 -> 2.6227051
A8: India | B8: =AVERAGE(D16:D22) -> 0.39428571 | E8: =1/B8 -> 2.5362319
A9: ROW / Total | B9: =AVERAGE(B32:B38) -> 0.3444115 | C9: =AVERAGE(C32:C38) -> 0.46686981 | D9: =D40 -> 0.38232276 | E9: =1/B9 -> 2.9035035 | F9: =1/C9 -> 2.1419247 | G9: =H40 -> 2.6309666
A12: Data
A14: Percentage of EB-5 Principal Applicants at State | I14: % derivatives at State
B15: China - Mainland | C15: Vietnam | D15: India | E15: South Korea | F15: Brazil | G15: China – Taiwan | H15: Rest of World | I15: China - Mainland | J15: Vietnam | K15: India | L15: South Korea | M15: Brazil | N15: China – Taiwan | O15: Rest of World
A16: FYTD 2024 | B16: 0.375 | C16: 0.257 | D16: 0.359 | E16: 0.408 | F16: 0.5 | G16: 0.35 | H16: 0.305 | I16: =1-B16 -> 0.625 | J16: =1-C16 -> 0.743 | K16: =1-D16 -> 0.641 | L16: =1-E16 -> 0.592 | M16: =1-F16 -> 0.5 | N16: =1-G16 -> 0.65 | O16: =1-H16 -> 0.695
A17: FY 2023 | B17: 0.386 | C17: 0.337 | D17: 0.353 | E17: 0.366 | F17: 0.363 | G17: 0.345 | H17: 0.333 | I17: =1-B17 -> 0.614 | J17: =1-C17 -> 0.663 | K17: =1-D17 -> 0.647 | L17: =1-E17 -> 0.634 | M17: =1-F17 -> 0.637 | N17: =1-G17 -> 0.655 | O17: =1-H17 -> 0.667
A18: FY 2022 | B18: 0.422 | C18: 0.276 | D18: 0.357 | E18: 0.363 | F18: 0.294 | G18: 0.346 | H18: 0.286 | I18: =1-B18 -> 0.578 | J18: =1-C18 -> 0.724 | K18: =1-D18 -> 0.643 | L18: =1-E18 -> 0.637 | M18: =1-F18 -> 0.706 | N18: =1-G18 -> 0.654 | O18: =1-H18 -> 0.714
A19: FY 2021 | B19: 0.388 | C19: 0.286 | D19: 0.416 | E19: 0.354 | F19: 0.355 | G19: 0.358 | H19: 0.333 | I19: =1-B19 -> 0.612 | J19: =1-C19 -> 0.714 | K19: =1-D19 -> 0.584 | L19: =1-E19 -> 0.646 | M19: =1-F19 -> 0.645 | N19: =1-G19 -> 0.642 | O19: =1-H19 -> 0.667
A20: FY2019 | B20: 0.369 | C20: 0.254 | D20: 0.443 | E20: 0.38 | F20: 0.3 | G20: 0.37 | H20: 0.36 | I20: =1-B20 -> 0.631 | J20: =1-C20 -> 0.746 | K20: =1-D20 -> 0.557 | L20: =1-E20 -> 0.62 | M20: =1-F20 -> 0.7 | N20: =1-G20 -> 0.63 | O20: =1-H20 -> 0.64
A21: FY2018 | B21: 0.368 | C21: 0.263 | D21: 0.412 | E21: 0.358 | F21: 0.327 | G21: 0.369 | H21: 0.336 | I21: =1-B21 -> 0.632 | J21: =1-C21 -> 0.737 | K21: =1-D21 -> 0.588 | L21: =1-E21 -> 0.642 | M21: =1-F21 -> 0.673 | N21: =1-G21 -> 0.631 | O21: =1-H21 -> 0.664
A22: FY2017 | B22: 0.361 | C22: 0.272 | D22: 0.42 | E22: 0.359 | F22: 0.294 | G22: 0.394 | H22: 0.34 | I22: =1-B22 -> 0.639 | J22: =1-C22 -> 0.728 | K22: =1-D22 -> 0.58 | L22: =1-E22 -> 0.641 | M22: =1-F22 -> 0.706 | N22: =1-G22 -> 0.606 | O22: =1-H22 -> 0.66
A23: Sources: | B23: EB-5 Visa Updates, Michael Hanley, Ph.D FYTD-2024 and FY-2025 Outlook
B24: https://iiusa.org/wp-content/uploads/2024/05/3_EB-5-IIUSA-Conference-May-2024.pdf
B25: PART ONE: A DISCUSSION WITH CHARLES OPPENHEIM (Nov 20, 2019)
B26: https://iiusa.org/wp-content/uploads/2020/11/Virutal-Industry-Forum-Visa-Update.pdf
A28: Percentage of Investors in total EB-5 visas issued from Yearbook of Immigration Statistics
F30: Average visas per investor
B31: New Arrivals | C31: Status Adjustment | D31: Total | F31: New Arrivals | G31: Status Adjustment | H31: All
A32: FY2017 | B32: 0.33830665 | C32: 0.44110429 | D32: 0.35527648 | E32: FY2017 | F32: =1/B32 -> 2.9558982 | G32: =1/C32 -> 2.2670376 | H32: =1/D32 -> 2.8147092
A33: FY2018 | B33: 0.33118768 | C33: 0.4352179 | D33: 0.34954786 | E33: FY2018 | F33: =1/B33 -> 3.019436 | G33: =1/C33 -> 2.2976996 | H33: =1/D33 -> 2.8608385
A34: FY2019 | B34: 0.3416332 | C34: 0.45471464 | D34: 0.36170447 | E34: FY2019 | F34: =1/B34 -> 2.927116 | G34: =1/C34 -> 2.1991814 | H34: =1/D34 -> 2.764688
A35: FY2020 | B35: 0.33658713 | C35: 0.50083333 | D35: 0.38628341 | E35: FY2020 | F35: =1/B35 -> 2.9709989 | G35: =1/C35 -> 1.9966722 | H35: =1/D35 -> 2.5887728
A36: FY2021 | B36: 0.33849821 | C36: 0.53814002 | D36: 0.41100569 | E36: FY2021 | F36: =1/B36 -> 2.9542254 | G36: =1/C36 -> 1.8582524 | H36: =1/D36 -> 2.4330563
A37: FY2022 | B37: 0.35074627 | C37: 0.52392884 | D37: 0.43849181 | E37: FY2022 | F37: =1/B37 -> 2.8510638 | G37: =1/C37 -> 1.9086561 | H37: =1/D37 -> 2.2805443
A38: FY2023 | B38: 0.37392138 | C38: 0.37414966 | D38: 0.37394958 | E38: FY2023 | F38: =1/B38 -> 2.674359 | G38: =1/C38 -> 2.6727273 | H38: =1/D38 -> 2.6741573
A39: FY2024
A40: Average | B40: =AVERAGE(B32:B38) -> 0.3444115 | C40: =AVERAGE(C32:C38) -> 0.46686981 | D40: =AVERAGE(D32:D38) -> 0.38232276 | F40: =AVERAGE(F32:F38) -> 2.9075853 | G40: =1/C40 -> 2.1419247 | H40: =AVERAGE(H32:H38) -> 2.6309666
A42: Source: | B42: Yearbook of Immigration Statistics
B43: https://ohss.dhs.gov/topics/immigration/yearbook
A45: Detail of visas by immigration path in FY2023
B46: New Arrivals | C46: Status Adjustments | D46: Total | E46: New Arrivals | F46: Status Adjustments | G46: Total
A47: Investor | B47: 3900 | C47: 550 | D47: =SUM(B47:C47) -> 4450 | E47: =B47/B$50 -> 0.37392138 | F47: =C47/C$50 -> 0.37414966 | G47: =D47/D$50 -> 0.37394958
A48: Spouse | B48: 2310 | C48: 330 | D48: =SUM(B48:C48) -> 2640 | E48: =B48/B$50 -> 0.22147651 | F48: =C48/C$50 -> 0.2244898 | G48: =D48/D$50 -> 0.22184874
A49: Child | B49: 4220 | C49: 590 | D49: =SUM(B49:C49) -> 4810 | E49: =B49/B$50 -> 0.40460211 | F49: =C49/C$50 -> 0.40136054 | G49: =D49/D$50 -> 0.40420168
B50: =SUM(B47:B49) -> 10430 | C50: =SUM(C47:C49) -> 1470 | D50: =SUM(B50:C50) -> 11900
A52: Source: | B52: Lawful Permanent Residents Table 7
B53: https://ohss.dhs.gov/topics/immigration/yearbook-immigration-statistics/yearbook-2023

Sheet Post-RIA
B1: Post-RIA Receipt Data
N2: Total I-526/I-526E filings April 1, 2022 to March 31, 2026
B3: All Post-RIA Receipt and Approval Data | O3: Total | P3: Rural | Q3: High Unemployment | R3: Infrastructure | S3: Other**
B4: Source | C4: Data release date | D4: Data Query Date | E4: Content | F4: Link | N4: CHINA | O4: 8580 | P4: 4881 | Q4: 3438 | R4: 0 | S4: =O4-SUM(P4:R4) -> 261
B5: AIIA FOIA | C5: 45351 | E5: 2022-2023 monthly, select countries | F5: https://goaiia.org/aiia-foia-series-2023-inventory-statistics/ | N5: INDIA | O5: 4634 | P5: 2545 | Q5: 1806 | R5: 0 | S5: =O5-SUM(P5:R5) -> 283
B6: WR Immigration FOIA | C6: 45551 | D6: NPD, queried 04/2024 | E6: 2022 to Feb/Mar 2024 annual, all countries | F6: https://wolfsdorf.com/exclusive-new-eb-5-data-on-rural-vs-hua/ | N6: Rest of World | O6: 4901 | P6: 1380 | Q6: 2971 | R6: 0 | S6: =O6-SUM(P6:R6) -> 550
B7: IIUSA FOIA | C7: 45565 | D7: NPD, queried 07/2024 | E7: 2022 to June/July 2024 annual, select countries, receipts and adjudications | F7: https://iiusa.org/blog/iiusa-new-data-analysis-on-the-latest-i-526e-and-i-526-filings-adjudications-and-withdrawals-country-specific-trends-in-eb-5-demand-investment-preferences-case-processing-and-reserved-visa-wait/ | N7: Total | O7: =SUM(O4:O6) -> 18115 | P7: =SUM(P4:P6) -> 8806 | Q7: =SUM(Q4:Q6) -> 8215 | R7: =SUM(R4:R6) -> 0 | S7: =O7-SUM(P7:R7) -> 1094
B8: AIIA FOIA July 2024 | C8: 45587 | D8: NPD, queried 09/2024 | E8: 2022-2024/7 monthly | F8: https://goaiia.org/aiia-foia-series-updated-i-526e-inventory-statistics-for-july-2024/ | N8: I-526/I-526E filings October 2025-March 2026 (6 months)
B9: AIIA FOIA January 2025 | C9: 45774 | D9: NPD, queried 02/2025 | E9: 2022-2025/1 monthly | F9: https://goaiia.org/aiia-foia-series-updated-i-526e-inventory-statistics-for-january-2025/ | O9: Total | P9: Rural | Q9: High Unemployment | R9: Infrastructure | S9: Other**
B10: USCIS publication | C10: 45939 | E10: 2022-2025/7 monthly receipts | F10: https://www.uscis.gov/tools/reports-and-studies/immigration-and-citizenship-data | N10: CHINA | O10: 1361 | P10: 855 | Q10: 405 | S10: =O10-SUM(P10:R10) -> 101
B11: AIIA FOIA July 2025 | C11: 46044 | E11: 2022-2025/7 monthly receipts, approvals, denials | F11: https://goaiia.org/blog/aiia-foia-series-post-ria-data-july-2025/ | N11: INDIA | O11: 1344 | P11: 776 | Q11: 426 | S11: =O11-SUM(P11:R11) -> 142
N12: Rest of World | O12: 854 | P12: 267 | Q12: 437 | S12: =O12-SUM(P12:R12) -> 150
N13: Total | O13: =SUM(O10:O12) -> 3559 | P13: =SUM(P10:P12) -> 1898 | Q13: =SUM(Q10:Q12) -> 1268 | R13: =SUM(R10:R12) -> 0 | S13: =O13-SUM(P13:R13) -> 393
B14: Summary of Post-RIA Data in USCIS Reports
B16: Form I-526, Immigrant Petition by Standalone Investor and Form I-526E, Immigrant Petition by Regional Center Investor (Fiscal Year 2022 - Fiscal Year 2024) (XLSX, 51.42 KB)
B17: Form I-526, Immigrant Petition by Standalone Investor and Form I-526E, Immigrant Petition by Regional Center Investor (Fiscal Year 2025, Quarter 3) (XLSX, 30.48 KB)
B18: Form I-526, Immigrant Petition by Standalone Investor and Form I-526E, Immigrant Petition by Regional Center Investor (Fiscal Year 2025, Quarter 4) (XLSX, 38.12 KB)
B19: Form I-526, Immigrant Petition by Standalone Investor and Form I-526E, Immigrant Petition by Regional Center Investor (Fiscal Year 2026, Quarter 1) (XLSX, 30.01 KB)
B20: Form I-526, Immigrant Petition by Standalone Investor and Form I-526E, Immigrant Petition by Regional Center Investor (Fiscal Year 2026, Quarter 2) (XLSX, 30.44 KB)
B23: Form | C23: Filing Date | D23: TEA | E23: China | F23: India | G23: All ROW | H23: South Korea | I23: Taiwan | J23: Vietnam | K23: ROW except SK, T, V | M23: Filing Date | N23: (All)
B24: I-526E | C24: 44651 | D24: Infrastructure | E24: 0 | F24: 0 | G24: 0 | H24: 0 | I24: 0 | J24: 0 | K24: 0 | M24: Form | N24: (All)
B25: I-526 | C25: 44681 | D25: High Unemployment Area | E25: 0 | F25: 0 | G25: 1 | H25: 0 | I25: 0 | J25: 0 | K25: 1 | Q25: Total | S25: Investment | Z25: Total 2022-2025
B26: I-526E | C26: 44681 | D26: High Unemployment Area | E26: 0 | F26: 0 | G26: 0 | H26: 0 | I26: 0 | J26: 0 | K26: 0 | M26: Row Labels | N26: Sum of China | O26: Sum of India | P26: Sum of All ROW | S26: 800000 | V26: Investors | W26: Visa Pipeline | Z26: Rural Set Aside | AA26: Unaccommodated as of 2026
B27: I-526 | C27: 44681 | D27: Rural Area | E27: 0 | F27: 1 | G27: 0 | H27: 0 | I27: 0 | J27: 0 | K27: 0 | M27: High Unemployment Area | N27: 3438 | O27: 1806 | P27: 2971 | Q27: =SUM(N27:P27) -> 8215 | S27: =Q27*$S$26 -> 6572000000 | U27: China | V27: =GETPIVOTDATA("Sum of China",$M$26,"TEA","Rural Area") -> 4881 | W27: =V27*2 -> 9762 | X27: China | Z27: 1181 | AA27: =W27-Z27 -> 8581
B28: I-526E | C28: 44681 | D28: Rural Area | E28: 0 | F28: 0 | G28: 0 | H28: 0 | I28: 0 | J28: 0 | K28: 0 | M28: Infrastructure | N28: 0 | O28: 0 | P28: 0 | Q28: =SUM(N28:P28) -> 0 | S28: =Q28*$S$26 -> 0 | U28: India | V28: =GETPIVOTDATA("Sum of India",$M$26,"TEA","Rural Area") -> 2545 | W28: =V28*2 -> 5090 | X28: India | Z28: 833 | AA28: =W28-Z28 -> 4257
B29: I-526 | C29: 44681 | D29: Rural Area and High Unemployment Area | E29: 0 | F29: 0 | G29: 0 | H29: 0 | I29: 0 | J29: 0 | K29: 0 | M29: None | N29: 75 | O29: 45 | P29: 164 | Q29: =SUM(N29:P29) -> 284 | S29: =Q29*$S$26 -> 227200000 | U29: ROW | V29: =GETPIVOTDATA("Sum of All ROW",$M$26,"TEA","Rural Area") -> 1380 | W29: =V29*2 -> 2760 | X29: ROW | Z29: 248 | AA29: =W29-Z29 -> 2512
B30: I-526E | C30: 44681 | D30: Rural Area and High Unemployment Area | E30: 0 | F30: 0 | G30: 0 | H30: 0 | I30: 0 | J30: 0 | K30: 0 | M30: Rural Area | N30: 4881 | O30: 2545 | P30: 1380 | Q30: =SUM(N30:P30) -> 8806 | S30: =Q30*$S$26 -> 7044800000 | U30: Total | V30: =SUM(V27:V29) -> 8806 | W30: =V30*2 -> 17612 | Z30: 2262 | AA30: =W30-Z30 -> 15350
B31: I-526 | C31: 44681 | D31: None | E31: 2 | F31: 2 | G31: 5 | H31: 0 | I31: 0 | J31: 0 | K31: 5 | M31: Rural Area and High Unemployment Area | N31: 120 | O31: 167 | P31: 98 | Q31: =SUM(N31:P31) -> 385 | S31: =Q31*$S$26 -> 308000000
B32: I-526E | C32: 44681 | D32: None | E32: 0 | F32: 0 | G32: 0 | H32: 0 | I32: 0 | J32: 0 | K32: 0 | M32: Unknown | N32: 58 | O32: 56 | P32: 180 | Q32: =SUM(N32:P32) -> 294 | S32: =Q32*$S$26 -> 235200000
B33: I-526E | C33: 44681 | D33: Infrastructure | E33: 0 | F33: 0 | G33: 0 | H33: 0 | I33: 0 | J33: 0 | K33: 0 | M33: Unreserved | N33: 8 | O33: 15 | P33: 108 | Q33: =SUM(N33:P33) -> 131 | S33: =Q33*$S$26 -> 104800000
B34: I-526 | C34: 44712 | D34: High Unemployment Area | E34: 2 | F34: 0 | G34: 0 | H34: 0 | I34: 0 | J34: 0 | K34: 0 | M34: Grand Total | N34: 8580 | O34: 4634 | P34: 4901 | Q34: =SUM(Q27:Q33) -> 18115 | S34: =Q34*$S$26 -> 14492000000
B35: I-526E | C35: 44712 | D35: High Unemployment Area | E35: 0 | F35: 0 | G35: 0 | H35: 0 | I35: 0 | J35: 0 | K35: 0
B36: I-526 | C36: 44712 | D36: Rural Area | E36: 0 | F36: 1 | G36: 0 | H36: 0 | I36: 0 | J36: 0 | K36: 0 | O36: =GETPIVOTDATA("Sum of India",$M$26,"TEA","Unreserved")/GETPIVOTDATA("Sum of India",$M$26) -> 0.0032369443
B37: I-526E | C37: 44712 | D37: Rural Area | E37: 0 | F37: 0 | G37: 0 | H37: 0 | I37: 0 | J37: 0 | K37: 0
B38: I-526 | C38: 44712 | D38: Rural Area and High Unemployment Area | E38: 0 | F38: 0 | G38: 0 | H38: 0 | I38: 0 | J38: 0 | K38: 0
B39: I-526E | C39: 44712 | D39: Rural Area and High Unemployment Area | E39: 0 | F39: 0 | G39: 0 | H39: 0 | I39: 0 | J39: 0 | K39: 0
B40: I-526 | C40: 44712 | D40: None | E40: 9 | F40: 0 | G40: 0 | H40: 0 | I40: 0 | J40: 0 | K40: 0
B41: I-526E | C41: 44712 | D41: None | E41: 0 | F41: 0 | G41: 0 | H41: 0 | I41: 0 | J41: 0 | K41: 0
B42: I-526E | C42: 44712 | D42: Infrastructure | E42: 0 | F42: 0 | G42: 0 | H42: 0 | I42: 0 | J42: 0 | K42: 0
B43: I-526 | C43: 44742 | D43: High Unemployment Area | E43: 0 | F43: 3 | G43: 0 | H43: 0 | I43: 0 | J43: 0 | K43: 0
B44: I-526E | C44: 44742 | D44: High Unemployment Area | E44: 0 | F44: 0 | G44: 0 | H44: 0 | I44: 0 | J44: 0 | K44: 0
B45: I-526 | C45: 44742 | D45: Rural Area | E45: 0 | F45: 0 | G45: 0 | H45: 0 | I45: 0 | J45: 0 | K45: 0
B46: I-526E | C46: 44742 | D46: Rural Area | E46: 0 | F46: 0 | G46: 0 | H46: 0 | I46: 0 | J46: 0 | K46: 0 | U46: Current report -- I-526/I-526E Receipts in Jan 2026 to Mar 2026
B47: I-526 | C47: 44742 | D47: Rural Area and High Unemployment Area | E47: 0 | F47: 0 | G47: 0 | H47: 0 | I47: 0 | J47: 0 | K47: 0 | U47: TEA | V47: China | W47: India | X47: ROW | Y47: Total | Z47: % Total
B48: I-526E | C48: 44742 | D48: Rural Area and High Unemployment Area | E48: 0 | F48: 0 | G48: 0 | H48: 0 | I48: 0 | J48: 0 | K48: 0 | U48: High Unemployment Area | V48: 215 | W48: 209 | X48: 204 | Y48: =SUM(V48:X48) -> 628 | Z48: =Y48/$Y$54 -> 0.35440181
B49: I-526 | C49: 44742 | D49: None | E49: 0 | F49: 1 | G49: 4 | H49: 0 | I49: 0 | J49: 0 | K49: 4 | U49: Infrastructure | V49: 0 | W49: 0 | X49: 0 | Y49: =SUM(V49:X49) -> 0 | Z49: =Y49/$Y$54 -> 0
B50: I-526E | C50: 44742 | D50: None | E50: 0 | F50: 0 | G50: 0 | H50: 0 | I50: 0 | J50: 0 | K50: 0 | U50: Rural Area | V50: 420 | W50: 358 | X50: 124 | Y50: =SUM(V50:X50) -> 902 | Z50: =Y50/$Y$54 -> 0.50902935
B51: I-526E | C51: 44742 | D51: Infrastructure | E51: 0 | F51: 0 | G51: 0 | H51: 0 | I51: 0 | J51: 0 | K51: 0 | U51: Rural Area and High Unemployment Area | V51: 50 | W51: 76 | X51: 27 | Y51: =SUM(V51:X51) -> 153 | Z51: =Y51/$Y$54 -> 0.086343115
B52: I-526 | C52: 44773 | D52: High Unemployment Area | E52: 0 | F52: 0 | G52: 0 | H52: 0 | I52: 0 | J52: 0 | K52: 0 | U52: Unknown | V52: 19 | W52: 19 | X52: 34 | Y52: =SUM(V52:X52) -> 72 | Z52: =Y52/$Y$54 -> 0.040632054
B53: I-526E | C53: 44773 | D53: High Unemployment Area | E53: 0 | F53: 0 | G53: 0 | H53: 0 | I53: 0 | J53: 0 | K53: 0 | U53: Unreserved | V53: 2 | W53: 2 | X53: 13 | Y53: =SUM(V53:X53) -> 17 | Z53: =Y53/$Y$54 -> 0.0095936795
B54: I-526 | C54: 44773 | D54: Rural Area | E54: 0 | F54: 0 | G54: 0 | H54: 0 | I54: 0 | J54: 0 | K54: 0 | U54: Total | V54: =SUM(V48:V53) -> 706 | W54: =SUM(W48:W53) -> 664 | X54: =SUM(X48:X53) -> 402 | Y54: =SUM(Y48:Y53) -> 1772 | Z54: =Y54/$Y$65 -> 1.003966
B55: I-526E | C55: 44773 | D55: Rural Area | E55: 0 | F55: 1 | G55: 0 | H55: 0 | I55: 0 | J55: 0 | K55: 0 | U55: % Total | V55: =V54/$Y$54 -> 0.39841986 | W55: =W54/$Y$54 -> 0.37471783 | X55: =X54/$Y$54 -> 0.2268623 | Y55: =Y54/$Y$54 -> 1
B56: I-526 | C56: 44773 | D56: Rural Area and High Unemployment Area | E56: 0 | F56: 0 | G56: 0 | H56: 0 | I56: 0 | J56: 0 | K56: 0
B57: I-526E | C57: 44773 | D57: Rural Area and High Unemployment Area | E57: 0 | F57: 0 | G57: 0 | H57: 0 | I57: 0 | J57: 0 | K57: 0 | U57: Previous Quarter -- I-526/I-526E Receipts in Oct 2025 to Dec 2025
B58: I-526 | C58: 44773 | D58: None | E58: 3 | F58: 0 | G58: 4 | H58: 0 | I58: 0 | J58: 0 | K58: 4 | U58: TEA | V58: China | W58: India | X58: ROW | Y58: Total | Z58: % Total
B59: I-526E | C59: 44773 | D59: None | E59: 0 | F59: 0 | G59: 0 | H59: 0 | I59: 0 | J59: 0 | K59: 0 | U59: High Unemployment Area | V59: 187 | W59: 213 | X59: 230 | Y59: =SUM(V59:X59) -> 630 | Z59: =Y59/$Y$65 -> 0.35694051
B60: I-526E | C60: 44773 | D60: Infrastructure | E60: 0 | F60: 0 | G60: 0 | H60: 0 | I60: 0 | J60: 0 | K60: 0 | U60: Infrastructure | V60: 0 | W60: 0 | X60: 0 | Y60: =SUM(V60:X60) -> 0 | Z60: =Y60/$Y$65 -> 0
B61: I-526 | C61: 44804 | D61: High Unemployment Area | E61: 0 | F61: 0 | G61: 0 | H61: 0 | I61: 0 | J61: 0 | K61: 0 | U61: Rural Area | V61: 433 | W61: 411 | X61: 144 | Y61: =SUM(V61:X61) -> 988 | Z61: =Y61/$Y$65 -> 0.55977337
B62: I-526E | C62: 44804 | D62: High Unemployment Area | E62: 28 | F62: 11 | G62: 12 | H62: 0 | I62: 6 | J62: 1 | K62: 5 | U62: Rural Area and High Unemployment Area | V62: 26 | W62: 42 | X62: 21 | Y62: =SUM(V62:X62) -> 89 | Z62: =Y62/$Y$65 -> 0.050424929
B63: I-526 | C63: 44804 | D63: Rural Area | E63: 0 | F63: 1 | G63: 0 | H63: 0 | I63: 0 | J63: 0 | K63: 0 | U63: Unknown | V63: 2 | W63: 1 | X63: 38 | Y63: =SUM(V63:X63) -> 41 | Z63: =Y63/$Y$65 -> 0.023229462
B64: I-526E | C64: 44804 | D64: Rural Area | E64: 0 | F64: 5 | G64: 8 | H64: 3 | I64: 5 | J64: 0 | K64: 0 | U64: Unreserved | V64: 1 | W64: 1 | X64: 15 | Y64: =SUM(V64:X64) -> 17 | Z64: =Y64/$Y$65 -> 0.009631728
B65: I-526 | C65: 44804 | D65: Rural Area and High Unemployment Area | E65: 0 | F65: 0 | G65: 0 | H65: 0 | I65: 0 | J65: 0 | K65: 0 | U65: Total | V65: =SUM(V59:V64) -> 649 | W65: =SUM(W59:W64) -> 668 | X65: =SUM(X59:X64) -> 448 | Y65: =SUM(Y59:Y64) -> 1765 | Z65: =Y65/$Y$65 -> 1
B66: I-526E | C66: 44804 | D66: Rural Area and High Unemployment Area | E66: 0 | F66: 0 | G66: 0 | H66: 0 | I66: 0 | J66: 0 | K66: 0 | U66: % Total | V66: =V65/$Y$65 -> 0.36770538 | W66: =W65/$Y$65 -> 0.37847025 | X66: =X65/$Y$65 -> 0.25382436 | Y66: =Y65/$Y$65 -> 1
B67: I-526 | C67: 44804 | D67: None | E67: 1 | F67: 1 | G67: 7 | H67: 0 | I67: 0 | J67: 0 | K67: 7
B68: I-526E | C68: 44804 | D68: None | E68: 0 | F68: 0 | G68: 0 | H68: 0 | I68: 0 | J68: 0 | K68: 0 | U68: Total -- I-526/I-526E Receipts April 2022 to Mar 2026
B69: I-526E | C69: 44804 | D69: Infrastructure | E69: 0 | F69: 0 | G69: 0 | H69: 0 | I69: 0 | J69: 0 | K69: 0 | U69: TEA | V69: China | W69: India | X69: ROW | Y69: Total | Z69: % Total
B70: I-526 | C70: 44834 | D70: High Unemployment Area | E70: 0 | F70: 0 | G70: 0 | H70: 0 | I70: 0 | J70: 0 | K70: 0 | U70: High Unemployment Area | V70: 3438 | W70: 1806 | X70: 2971 | Y70: =SUM(V70:X70) -> 8215 | Z70: =Y70/$Y$77 -> 0.45349158
B71: I-526E | C71: 44834 | D71: High Unemployment Area | E71: 52 | F71: 36 | G71: 99 | H71: 27 | I71: 20 | J71: 18 | K71: 34 | U71: Infrastructure | V71: 0 | W71: 0 | X71: 0 | Y71: =SUM(V71:X71) -> 0 | Z71: =Y71/$Y$77 -> 0
B72: I-526 | C72: 44834 | D72: Rural Area | E72: 0 | F72: 0 | G72: 1 | H72: 0 | I72: 0 | J72: 0 | K72: 1 | U72: None | V72: 75 | W72: 45 | X72: 164 | Y72: =SUM(V72:X72) -> 284 | Z72: =Y72/$Y$77 -> 0.015677615
B73: I-526E | C73: 44834 | D73: Rural Area | E73: 43 | F73: 11 | G73: 12 | H73: 2 | I73: 2 | J73: 3 | K73: 5 | U73: Rural Area | V73: 4881 | W73: 2545 | X73: 1380 | Y73: =SUM(V73:X73) -> 8806 | Z73: =Y73/$Y$77 -> 0.48611648
B74: I-526 | C74: 44834 | D74: Rural Area and High Unemployment Area | E74: 0 | F74: 0 | G74: 0 | H74: 0 | I74: 0 | J74: 0 | K74: 0 | U74: Rural Area and High Unemployment Area | V74: 120 | W74: 167 | X74: 98 | Y74: =SUM(V74:X74) -> 385 | Z74: =Y74/$Y$77 -> 0.021253105
B75: I-526E | C75: 44834 | D75: Rural Area and High Unemployment Area | E75: 1 | F75: 0 | G75: 0 | H75: 0 | I75: 0 | J75: 0 | K75: 0 | U75: Unknown | V75: 58 | W75: 56 | X75: 180 | Y75: =SUM(V75:X75) -> 294 | Z75: =Y75/$Y$77 -> 0.016229644
B76: I-526 | C76: 44834 | D76: None | E76: 3 | F76: 1 | G76: 5 | H76: 0 | I76: 0 | J76: 1 | K76: 4 | U76: Unreserved | V76: 8 | W76: 15 | X76: 108 | Y76: =SUM(V76:X76) -> 131 | Z76: =Y76/$Y$77 -> 0.007231576
B77: I-526E | C77: 44834 | D77: None | E77: 0 | F77: 0 | G77: 1 | H77: 0 | I77: 1 | J77: 0 | K77: 0 | U77: Total | V77: =SUM(V70:V76) -> 8580 | W77: =SUM(W70:W76) -> 4634 | X77: =SUM(X70:X76) -> 4901 | Y77: =SUM(Y70:Y76) -> 18115 | Z77: =Y77/$Y$77 -> 1
B78: I-526E | C78: 44834 | D78: Infrastructure | E78: 0 | F78: 0 | G78: 0 | H78: 0 | I78: 0 | J78: 0 | K78: 0 | U78: % Total | V78: =V77/$Y$77 -> 0.47364063 | W78: =W77/$Y$77 -> 0.2558101 | X78: =X77/$Y$77 -> 0.27054927 | Y78: =Y77/$Y$77 -> 1
B79: I-526 | C79: 44865 | D79: High Unemployment Area | E79: 0 | F79: 1 | G79: 0 | H79: 0 | I79: 0 | J79: 0 | K79: 0
B80: I-526E | C80: 44865 | D80: High Unemployment Area | E80: 13 | F80: 11 | G80: 38 | H80: 3 | I80: 3 | J80: 12 | K80: 20 | U80: Data Source: Immigration and Citizenship Data page at uscis.gov
B81: I-526 | C81: 44865 | D81: Rural Area | E81: 0 | F81: 1 | G81: 0 | H81: 0 | I81: 0 | J81: 0 | K81: 0 | U81: Table summary by: blog.lucidtext.com
B82: I-526E | C82: 44865 | D82: Rural Area | E82: 18 | F82: 4 | G82: 10 | H82: 1 | I82: 1 | J82: 3 | K82: 5
B83: I-526 | C83: 44865 | D83: Rural Area and High Unemployment Area | E83: 0 | F83: 0 | G83: 0 | H83: 0 | I83: 0 | J83: 0 | K83: 0
B84: I-526E | C84: 44865 | D84: Rural Area and High Unemployment Area | E84: 0 | F84: 0 | G84: 1 | H84: 0 | I84: 0 | J84: 0 | K84: 1
B85: I-526 | C85: 44865 | D85: None | E85: 1 | F85: 3 | G85: 4 | H85: 0 | I85: 0 | J85: 1 | K85: 3
B86: I-526E | C86: 44865 | D86: None | E86: 0 | F86: 0 | G86: 0 | H86: 0 | I86: 0 | J86: 0 | K86: 0
B87: I-526E | C87: 44865 | D87: Infrastructure | E87: 0 | F87: 0 | G87: 0 | H87: 0 | I87: 0 | J87: 0 | K87: 0
B88: I-526 | C88: 44895 | D88: High Unemployment Area | E88: 0 | F88: 1 | G88: 0 | H88: 0 | I88: 0 | J88: 0 | K88: 0
B89: I-526E | C89: 44895 | D89: High Unemployment Area | E89: 29 | F89: 17 | G89: 42 | H89: 3 | I89: 8 | J89: 7 | K89: 24
B90: I-526 | C90: 44895 | D90: Rural Area | E90: 2 | F90: 0 | G90: 1 | H90: 0 | I90: 0 | J90: 0 | K90: 1
B91: I-526E | C91: 44895 | D91: Rural Area | E91: 29 | F91: 2 | G91: 6 | H91: 0 | I91: 0 | J91: 0 | K91: 6
B92: I-526 | C92: 44895 | D92: Rural Area and High Unemployment Area | E92: 0 | F92: 0 | G92: 0 | H92: 0 | I92: 0 | J92: 0 | K92: 0
B93: I-526E | C93: 44895 | D93: Rural Area and High Unemployment Area | E93: 0 | F93: 0 | G93: 0 | H93: 0 | I93: 0 | J93: 0 | K93: 0
... B480: I-526E | C480: 46112 | D480: Unknown | E480: 13 | F480: 11 | G480: 18 | H480: 15 | I480: 0 | J480: 0 | K480: 3

Sheet Pre-RIA Data
B1: Pre-RIA EB-5 Backlog Data Collection
B2: This data is relevant to applicants who filed I-526 prior to the EB-5 Reform and Integrity Act (RIA) enacted in March 2022
B5: I-526 Filings by Fiscal Year
B7: Year I-526 filed | C7: Vietnam | D7: Brazil | E7: South Korea | F7: China | G7: Taiwan | H7: India | I7: ROW | J7: Worldwide | K7: Other than China, India | N7: Sources:
B8: FY2013 | C8: 87 | D8: 19 | E8: 102 | F8: 5480 | G8: 91 | H8: 86 | I8: 309 | J8: 6174 | K8: =J8-F8-H8 -> 608 | N8: https://www.uscis.gov/sites/default/files/files/nativedocuments/I-526_Approvals_Denials_and_Receipts_for_Q1_of_FY19.pdf
B9: FY2014 | C9: 127 | D9: 50 | E9: 110 | F9: 9722 | G9: 106 | H9: 99 | I9: 355 | J9: 10569 | K9: =J9-F9-H9 -> 748 | N9: https://www.uscis.gov/sites/default/files/document/data/I-526_accepted_petitions_for_India_in_the_months_October_2018-May_2019.pdf
B10: FY2015 | C10: 170 | D10: 229 | E10: 167 | F10: 13530 | G10: 289 | H10: 239 | I10: 1329 | J10: 15953 | K10: =J10-F10-H10 -> 2184 | L10: =SUM(F8:F10) -> 28732 | N10: https://iiusa.org/blog/analyzing-form-i-526-statistics-by-investors-country-of-chargeability-for-fiscal-year-2017-what-is-new-and-what-it-tells-us/
B11: FY2016 | C11: 143 | D11: 151 | E11: 156 | F11: 10948 | G11: 404 | H11: 354 | I11: 1117 | J11: 13273 | K11: =J11-F11-H11 -> 1971 | N11: https://iiusa.org/wp-content/uploads/2017/08/A-New-Lens-What-the-Lastest-Data-Tells-Us-about-Raising-EB-5-Captial-in-an-Increasingly-Challenging-Marketplace.pdf
B12: FY2017 | C12: 523 | D12: 136 | E12: 215 | F12: 8771 | G12: 182 | H12: 587 | I12: 950 | J12: 11364 | K12: =J12-F12-H12 -> 2006 | N12: https://iiusa.org/wp-content/uploads/2022/04/IIUSA-RCBJ_April2022-update.pdf
B13: FY2018 | C13: 761 | D13: 173 | E13: 371 | F13: 2212 | G13: 255 | H13: 1167 | I13: 1159 | J13: 6098 | K13: =J13-F13-H13 -> 2719 | N13: https://www.galati.law/post/new-data-i-526-receipts-by-month-by-investor-country-of-birth-oct-2019-oct-2020
B14: FY2019 | C14: 395 | D14: 113 | E14: 548 | F14: 522 | G14: 237 | H14: 1027 | I14: =J14-SUM(C14:H14) -> 1352 | J14: 4194 | K14: =J14-F14-H14 -> 2645 | L14: =H14/J14 -> 0.24487363 | N14: https://www.dropbox.com/s/zxkmwye1yr1100t/i526list.pdf?dl=0
B15: FY2020 | C15: 253 | D15: 142 | E15: 421 | F15: 428 | G15: 231 | H15: 935 | I15: 1968 | J15: 4378 | K15: =J15-F15-H15 -> 3015 | N15: I-526 datasets available for purchase from IIUSA for FY1991 to FY2020
B16: FY2021 | H16: 268 | J16: =SUM(C337:C340) -> 814 | N16: https://www.uscis.gov/sites/default/files/files/nativedocuments/I-526_Approvals_Denials_and_Receipts_for_Q1_of_FY19.pdf
B17: FY2022 -- Oct 2021 to March 2022 | F17: 9 | H17: 272 | I17: 315 | J17: =SUM(C341:C342) -> 609 | K17: =J17-F17-H17 -> 328 | N17: 2022-2024 per-country approval rate | O17: https://iiusa.org/blog/iiusa-new-data-analysis-on-the-latest-i-526e-and-i-526-filings-adjudications-and-withdrawals-country-specific-trends-in-eb-5-demand-investment-preferences-case-processing-and-reserved-visa-wait/
F18: =SUM(F8:F12)/SUM(J8:J12) -> 0.84508049 | N18: 2021/2022 data for India estimated based on FOIA results for petitions pending and approved as of June 2023 (FOIA COW2023003820)
B20: I-526 Approval Rate by Country | D20: I-526 approvals as percent total I-526 completions
B21: Year I-526 adjudicated | C21: Vietnam | E21: Korea | F21: China | H21: India | I21: All Except China India | J21: Worldwide average | K21: Number of I-526 Completions
B22: FY2016 | C22: 0.87 | E22: 0.82 | F22: 0.83 | H22: 0.66 | J22: 0.82 | K22: 9367
B23: FY2019 | C23: 0.9 | E23: 0.98 | F23: 0.78 | H23: 0.9 | J23: 0.81 | K23: 4673
B24: FY2020 | C24: 0.88 | E24: 0.91 | F24: 0.54 | H24: 0.9 | J24: 0.75 | K24: 3421
B25: FY2021 | J25: 0.787 | K25: 3048
B26: FY2022 | F26: 0.29 | H26: 0.59 | J26: 0.49 | K26: 1203
B27: FY2023 | F27: 0.29 | H27: 0.76 | J27: 0.598 | K27: 3563
B28: FY2024 Oct-Mar | F28: 0.4 | H28: 0.82 | J28: 0.78 | K28: 2956
B30: I-526 Pending and Applicants in Process
B32: I-526 Inventory at USCIS by Country and I-526 Filing Date
B34: Pre-RIA I-526 Pending as of July 31, 2024 -- Summary | L34: Source: USCIS Response to AIIA FOIA Request
C35: China | D35: India | E35: ROW | F35: Total | L35: I-526, Immigrant Petition by Standalone Investor
B36: Pre-2015 | C36: 6 | D36: 0 | E36: 2 | F36: =SUM(C36:E36) -> 8 | L36: I-526E, Immigrant Petition by Regional Center Investor
B37: 2015 Q1. Oct - Dec 2014 | C37: 1 | D37: 0 | E37: 0 | F37: =SUM(C37:E37) -> 1 | L37: Pending Petitions by Priority Year, Priority Month, and Country of Chargeability
B38: 2015 Q2. Jan - Mar 2015 | C38: 1 | D38: 0 | E38: 0 | F38: =SUM(C38:E38) -> 1 | L38: As of July 31, 2024
B39: 2015 Q3 Apr - Jun 2015 | C39: 3 | D39: 0 | E39: 0 | F39: =SUM(C39:E39) -> 3 | L39: Department of Homeland Security, U.S. Citizenship and Immigration Services, Office of Performance and Quality
B40: 2015 Q4 Jul - Sep 2015 | C40: 28 | D40: 0 | E40: 4 | F40: =SUM(C40:E40) -> 32 | L40: NPD, queried 09/2024, TRK 15578
B41: 2016 Q1 Oct - Dec 2015 | C41: 33 | D41: 0 | E41: 1 | F41: =SUM(C41:E41) -> 34 | L41: https://goaiia.org/aiia-foia-series-pre-ria-i-526-data-as-of-july-2024/
B42: 2016 Q2 Jan - Mar 2016 | C42: 4 | D42: 0 | E42: 0 | F42: =SUM(C42:E42) -> 4
B43: 2016 Q3 April - June 2016 | C43: 20 | D43: 0 | E43: 1 | F43: =SUM(C43:E43) -> 21
B44: 2016 Q4 Jul - Sep 2016 | C44: 79 | D44: 0 | E44: 2 | F44: =SUM(C44:E44) -> 81
B45: 2017 Q1 Oct - Dec 2016 | C45: 87 | D45: 0 | E45: 8 | F45: =SUM(C45:E45) -> 95
B46: 2017 Q2. Jan - Mar 2017 | C46: 94 | D46: 0 | E46: 4 | F46: =SUM(C46:E46) -> 98
B47: 2017 Q3. April - June 2017 | C47: 430 | D47: 1 | E47: 9 | F47: =SUM(C47:E47) -> 440
B48: 2017 Q4 Jul - Sep 2017 | C48: 243 | D48: 0 | E48: 9 | F48: =SUM(C48:E48) -> 252
B49: 2018 Q1 Oct - Dec 2017 | C49: 326 | D49: 1 | E49: 23 | F49: =SUM(C49:E49) -> 350
B50: 2018 Q2. Jan - Mar 2018 | C50: 358 | D50: 0 | E50: 18 | F50: =SUM(C50:E50) -> 376
B51: 2018 Q3. April - June 2018 | C51: 154 | D51: 0 | E51: 4 | F51: =SUM(C51:E51) -> 158
B52: 2018 Q4 Jul - Sep 2018 | C52: 277 | D52: 3 | E52: 22 | F52: =SUM(C52:E52) -> 302 | J52: EB-5 Form I-526 pending as of July 31, 2024with priority dates before April 2022
B53: 2019 Q1 Oct - Dec 2018 | C53: 144 | D53: 1 | E53: 33 | F53: =SUM(C53:E53) -> 178 | H53: =SUM(E36:E53) -> 140 | J53: as of May 3, 2024
B54: 2019 Q2. Jan - Mar 2019 | C54: 99 | D54: 7 | E54: 18 | F54: =SUM(C54:E54) -> 124 | J54: Priority date | K54: 2014 | L54: 2015 | M54: 2016 | N54: 2017 | O54: 2018 | P54: 2019 | Q54: 2020 | R54: 2021 | S54: 2022
B55: 2019 Q3. April - June 2019 | C55: 80 | D55: 3 | E55: 14 | F55: =SUM(C55:E55) -> 97 | J55: China | K55: =SUM(C36:C37) -> 7 | L55: =SUM(C38:C41) -> 65 | M55: =SUM(C42:C45) -> 190 | N55: =SUM(C46:C49) -> 1093 | O55: =SUM(C50:C53) -> 933 | P55: =SUM(C54:C57) -> 645 | Q55: =SUM(C58:C61) -> 17 | R55: =SUM(C62:C65) -> 16 | S55: =C66 -> 8
B56: 2019 Q4 Jul - Sep 2019 | C56: 97 | D56: 9 | E56: 63 | F56: =SUM(C56:E56) -> 169 | J56: India | K56: =SUM(D36:D37) -> 0 | L56: =SUM(D38:D41) -> 0 | M56: =SUM(D42:D45) -> 0 | N56: =SUM(D46:D49) -> 2 | O56: =SUM(D50:D53) -> 4 | P56: =SUM(D54:D57) -> 172 | Q56: =SUM(D58:D61) -> 7 | R56: =SUM(D62:D65) -> 140 | S56: =D66 -> 148
B57: 2020 Q1 Oct - Dec 2019 | C57: 369 | D57: 153 | E57: 386 | F57: =SUM(C57:E57) -> 908 | J57: ROW | K57: =SUM(E36:E37) -> 2 | L57: =SUM(E38:E41) -> 5 | M57: =SUM(E42:E45) -> 11 | N57: =SUM(E46:E49) -> 45 | O57: =SUM(E50:E53) -> 77 | P57: =SUM(E54:E57) -> 481 | Q57: =SUM(E58:E61) -> 46 | R57: =SUM(E62:E65) -> 251 | S57: =E66 -> 131
B58: 2020 Q2 Jan - Mar 2020 | C58: 2 | D58: 3 | E58: 7 | F58: =SUM(C58:E58) -> 12 | J58: Grand Total | K58: =SUM(K55:K57) -> 9 | L58: =SUM(L55:L57) -> 70 | M58: =SUM(M55:M57) -> 201 | N58: =SUM(N55:N57) -> 1140 | O58: =SUM(O55:O57) -> 1014 | P58: =SUM(P55:P57) -> 1298 | Q58: =SUM(Q55:Q57) -> 70 | R58: =SUM(R55:R57) -> 407 | S58: =SUM(S55:S57) -> 287
B59: 2020 Q3 Apr - Jun 2020 | C59: 2 | D59: 0 | E59: 12 | F59: =SUM(C59:E59) -> 14
B60: 2020 Q4 Jul - Sep 2020 | C60: 6 | D60: 2 | E60: 10 | F60: =SUM(C60:E60) -> 18
B61: 2021 Q1 Oct - Dec 2020 | C61: 7 | D61: 2 | E61: 17 | F61: =SUM(C61:E61) -> 26
B62: 2021 Q2 Jan - Mar 2021 | C62: 6 | D62: 6 | E62: 23 | F62: =SUM(C62:E62) -> 35
B63: 2021 Q3 Apr - Jun 2021 | C63: 9 | D63: 90 | E63: 164 | F63: =SUM(C63:E63) -> 263
B64: 2021 Q4 Jul - Sep 2021 | C64: 0 | D64: 19 | E64: 14 | F64: =SUM(C64:E64) -> 33
B65: 2022 Q1 Oct - Dec 2021 | C65: 1 | D65: 25 | E65: 50 | F65: =SUM(C65:E65) -> 76
B66: 2022 Q2 Jan - Mar 2022 | C66: 8 | D66: 148 | E66: 131 | F66: =SUM(C66:E66) -> 287
B68: Total | C68: =SUM(C36:C66) -> 2974 | D68: =SUM(D36:D66) -> 473 | E68: =SUM(E36:E66) -> 1049 | F68: =SUM(F36:F66) -> 4496
B71: Pending I-526 Inventory as of December 13, 2020
C72: Number of I-526 Pending as of December 13, 2020
B73: Fiscal Year of Filing | C73: Vietnam | D73: Brazil | E73: South Korea | F73: China | G73: Taiwan | H73: India | I73: Other Countries | J73: All Countries | N73: Source: USCIS Response to FOIA request COW2020000203 by Suzane Lazicki
B74: 2012 | C74: =SUM(C353:C361) -> 1 | D74: =SUM(D353:D361) -> 0 | E74: =SUM(E353:E361) -> 1 | F74: =SUM(F353:F361) -> 14 | G74: =SUM(G353:G361) -> 0 | H74: =SUM(H353:H361) -> 0 | I74: =SUM(I353:I361) -> 2 | J74: =SUM(J353:J361) -> 18
B75: 2013 | C75: =SUM(C362:C373) -> 0 | D75: =SUM(D362:D373) -> 0 | E75: =SUM(E362:E373) -> 0 | F75: =SUM(F362:F373) -> 4 | G75: =SUM(G362:G373) -> 0 | H75: =SUM(H362:H373) -> 0 | I75: =SUM(I362:I373) -> 0 | J75: =SUM(J362:J373) -> 4
B76: 2014 | C76: =SUM(C374:C385) -> 0 | D76: =SUM(D374:D385) -> 0 | E76: =SUM(E374:E385) -> 0 | F76: =SUM(F374:F385) -> 49 | G76: =SUM(G374:G385) -> 0 | H76: =SUM(H374:H385) -> 0 | I76: =SUM(I374:I385) -> 4 | J76: =SUM(J374:J385) -> 53
B77: 2015 | C77: =SUM(C386:C397) -> 0 | D77: =SUM(D386:D397) -> 3 | E77: =SUM(E386:E397) -> 0 | F77: =SUM(F386:F397) -> 223 | G77: =SUM(G386:G397) -> 0 | H77: =SUM(H386:H397) -> 0 | I77: =SUM(I386:I397) -> 50 | J77: =SUM(J386:J397) -> 276
B78: 2016 | C78: =SUM(C398:C409) -> 47 | D78: =SUM(D398:D409) -> 11 | E78: =SUM(E398:E409) -> 0 | F78: =SUM(F398:F409) -> 875 | G78: =SUM(G398:G409) -> 9 | H78: =SUM(H398:H409) -> 14 | I78: =SUM(I398:I409) -> 60 | J78: =SUM(J398:J409) -> 1016
B79: 2017 | C79: =SUM(C410:C421) -> 138 | D79: =SUM(D410:D421) -> 17 | E79: =SUM(E410:E421) -> 8 | F79: =SUM(F410:F421) -> 1798 | G79: =SUM(G410:G421) -> 41 | H79: =SUM(H410:H421) -> 95 | I79: =SUM(I410:I421) -> 208 | J79: =SUM(J410:J421) -> 2305
B80: 2018 | C80: =SUM(C422:C433) -> 371 | D80: =SUM(D422:D433) -> 49 | E80: =SUM(E422:E433) -> 113 | F80: =SUM(F422:F433) -> 1386 | G80: =SUM(G422:G433) -> 117 | H80: =SUM(H422:H433) -> 423 | I80: =SUM(I422:I433) -> 476 | J80: =SUM(J422:J433) -> 2935
B81: 2019 | C81: =SUM(C434:C445) -> 378 | D81: =SUM(D434:D445) -> 91 | E81: =SUM(E434:E445) -> 520 | F81: =SUM(F434:F445) -> 491 | G81: =SUM(G434:G445) -> 217 | H81: =SUM(H434:H445) -> 896 | I81: =SUM(I434:I445) -> 1066 | J81: =SUM(J434:J445) -> 3659
B82: 2020 | C82: =SUM(C446:C457) -> 253 | D82: =SUM(D446:D457) -> 131 | E82: =SUM(E446:E457) -> 407 | F82: =SUM(F446:F457) -> 426 | G82: =SUM(G446:G457) -> 227 | H82: =SUM(H446:H457) -> 898 | I82: =SUM(I446:I457) -> 1599 | J82: =SUM(J446:J457) -> 3941
B83: 2021 | C83: =SUM(C458:C459) -> 0 | D83: =SUM(D458:D459) -> 0 | E83: =SUM(E458:E459) -> 3 | F83: =SUM(F458:F459) -> 0 | G83: =SUM(G458:G459) -> 0 | H83: =SUM(H458:H459) -> 0 | I83: =SUM(I458:I459) -> 11 | J83: =SUM(J458:J459) -> 14
B84: Total as of 12/13/2020 | C84: =SUM(C74:C83) -> 1188 | D84: =SUM(D74:D83) -> 302 | E84: =SUM(E74:E83) -> 1052 | F84: =SUM(F74:F83) -> 5266 | G84: =SUM(G74:G83) -> 611 | H84: =SUM(H74:H83) -> 2326 | I84: =SUM(I74:I83) -> 3476 | J84: =SUM(J74:J83) -> 14221 | K84: =J84-F84 -> 8955
C85: 0.254 | D85: 0.3 | E85: 0.38 | F85: 0.369 | G85: 0.37 | H85: 0.443 | I85: 0.36 | J85: 0.36
B86: Pending I-526 as of November 2021
C87: Vietnam | D87: Brazil | E87: South Korea | F87: China | G87: Taiwan | H87: India | I87: Other Countries | J87: All Countries | N87: Source: | O87: Slide 8
B88: Total as of 11/2021 | C88: 1006 | F88: 4941 | H88: 2103 | I88: 5108 | J88: 13158 | K88: =J88-F88 -> 8217 | O88: https://iiusa.org/wp-content/uploads/2022/04/Session-4b_Numbers-Talk-What-the-Latest-EB-5-Data-is-Telling-Us.pdf
B90: Pending I-526 Inventory as of March 2022
C91: Vietnam | D91: Brazil | E91: South Korea | F91: China | G91: Taiwan | H91: India | I91: Other Countries | J91: All Countries | N91: Source: FOIA request by AIIA
B92: Total as of 3/2022 | C92: 1028 | E92: 1010 | F92: 4823 | G92: 579 | H92: 2175 | I92: 3506 | J92: 13203 | K92: =J92-F92 -> 8380 | O92: https://goaiia.org/aiia-foia-series-pending-i526-i829-by-country/
B94: Total Pre-RIA I-526 Adjudicated FY2022-FY2024 | F94: China | H94: India | I94: ROW | J94: All | N94: Source: FOIA request by IIUSA
B95: FY2022 | F95: 263 | H95: 295 | O95: https://iiusa.org/blog/iiusa-new-data-analysis-on-the-latest-i-526e-and-i-526-filings-adjudications-and-withdrawals-country-specific-trends-in-eb-5-demand-investment-preferences-case-processing-and-reserved-visa-wait/
B96: FY2023 | F96: 659 | H96: 740
B97: FY2024 to June | F97: 1090 | H97: 776
B98: Total | F98: =SUM(F95:F97) -> 2012 | H98: =SUM(H95:H97) -> 1811
B100: Estimated pending inventory as of June 30, 2024 | F100: =F92-F98 -> 2811 | H100: =H92-H98 -> 364 | I100: =J100-H100-F100 -> 1842 | J100: 5017
I101: Percent of 2024 I-526 approvals sent to DOS as of August 2024 | J101: 0.47
B102: Most recent USCIS Official I-526 inventory report | J102: All Countries | N102: Source
B103: as of 9/30/2023 | J103: 9527
B104: as of 12/31/2023 | J104: 8539
B105: as of 6/30/2025 | I105: Total pending I-526 inventory | J105: 1248 | O105: https://www.uscis.gov/sites/default/files/document/data/quarterly_all_forms_fy2024_q1.xlsx
I106: Number of I-526 completions in most recent quarter | J106: 680 | L106: =J105/J106 -> 1.8352941 | O106: https://www.uscis.gov/sites/default/files/document/data/net_backlog_frontlog_fy2024_q1.xlsx
I107: Number of I-526 approvals in most recent quarter | J107: 368
I108: Net backlog: inventory less any customer induced delays (i.e. RFE, intent to deny, etc.) and visa unavailable cases | J108: 100
B110: Backlog at NVC | N110: Sources:
N111: 41944 | O111: http://immigrationroad.com/documents/DOS-Consular-Processing-Inventory_20141101.pdf https://www.bakerdonelson.com/files/Uploads/Documents/Divine%20The%20Realities.pdf
B112: EB-5 Applicants Registered at the National Visa Center | N112: 42309 | O112: http://www.ilw.com/immigrationdaily/news/2016,0111-AnnualReport.pdf https://www.bakerdonelson.com/files/Uploads/Documents/Divine%20The%20Realities.pdf
C113: As of Nov. 2014 | D113: As of Nov. 2015 | E113: As of Nov 2016 | F113: As of Nov 2017 | G113: As of Nov 2018 | H113: As of Nov 2019 | I113: as of Nov 2020 | J113: of Nov 2021 | K113: as of Nov 2022 | L113: of Nov 2023 | M113: as of 5/16/2024 | N113: 42675 | O113: https://www.dropbox.com/s/72n9vn52fnyg7fm/WaitingListItem.pdf?dl=0 (Used to be at https://travel.state.gov/content/dam/visas/Statistics/Immigrant-Statistics/WaitingListItem.pdf)
B114: China-mainland born | C114: 5169 | D114: 15830 | E114: 22910 | F114: 26725 | G114: 33957 | H114: 33167 | I114: 45749 | J114: 44357 | K114: 38874 | L114: 33676 | M114: 31627 | N114: 43040 | O114: https://travel.state.gov/content/dam/visas/Statistics/Immigrant-Statistics/WaitingList/WaitingListItem_2017.pdf
...

Sheet VB Log
B1: Visa Bulletin Log
B2: Log of EB-5 entries in monthly Visa Bulletins since May 2015
B4: DOS | C4: https://travel.state.gov/content/travel/en/legal/visa-law0/visa-bulletin.html
B5: USCIS | C5: https://www.uscis.gov/visabulletininfo
B7: Log of Visa Bulletin Updates
B8: Visa Bulletin Date | C8: China | E8: Vietnam | I8: Visa Bulletin Note
C9: Chart A | D9: Chart B | E9: Chart A | F9: Chart B
B10: 41244 | I10: Employment Fifth: Current* *The following advisory is based strictly on the current demand situation. Since demand patterns can (and sometimes do) change over time, this should be considered a worst case scenario at this point. It appears likely that a cut-off date will need to be established for the China Employment Fifth preference category at some point during second half of fiscal year 2013. Such action would be delayed as long as possible, since while number use may be excessive over a 1 to 5 month period, it could average out to an acceptable level over a longer (e.g., 4 to 9 month) period. This would be the first time a cut-off date has been established in this category, which is why readers are being provided with the maximum amount of advance notice regarding the possibility.
B11: 41699 | I11: Employment Fifth: Current The above projections for the Family and Employment categories are for what is likely to happen during each of the next several months based on current applicant demand patterns. Readers should never assume that recent trends in cut-off date movements are guaranteed for the future, or that "corrective" action will not be required at some point in an effort to maintain number use within the applicable annual limits. The determination of the actual monthly cut-off dates is subject to fluctuations in applicant demand and a number of other variables. Unless indicated, those categories with a "Current" projection will remain so for the foreseeable future.
B12: 42036 | I12: Employment Fifth: Current - for most countries. The expected increase in China-mainland born demand would require the establishment of a cut-off date for such applicants no later than the summer months. The category will remain "Current" for all other countries for the foreseeable future.
B13: 42095 | I13: D. VISA AVAILABILITY - CHINA-mainland born: Employment Fifth Preference: Item D of the February Visa Bulletin advised readers that the expected increase in demand would require the establishment of a cut-off date during the summer to hold number use within the annual numerical limit. The establishment of that date can be expected no later than June.
B14: 42125 | C14: 41395
B15: 42156 | C15: 41395
B16: 42186 | C16: 41518
B17: 42217 | C17: 41518
B18: 42248 | C18: 41539
B19: 42278 | C19: 41555
B20: 42309 | C20: 41600
B21: 42339 | C21: 41623
B22: 42370 | C22: 41647
B23: 42401 | C23: 41654
B24: 42430 | C24: 41661
B25: 42461 | C25: 41671
... B45: 43070 | C45: 41835
B46: 43101 | C46: 41842 | D46: 41913
B47: 43132 | C47: 41842 | D47: 41883 | J47: F. VISA AVAILABILITY IN THE COMING MONTHS …. Employment Fifth: The category will remain “Current” for most countries. China-mainland born: Little if any forward movement. Vietnam: Will become subject to a final action date no later than April. The China-mainland born and Vietnam Employment Fifth preference dates would be the same.
B48: 43160 | C48: 41842 | D48: 41883 | J48: E. VISA AVAILABILITY IN THE COMING MONTHS: Continued heavy applicant demand is expected to result in the Vietnam Employment Fifth preference category reaching the per-country annual limit during March. Once this happens the category will become subject to a final action date, and visa availability for the remainder of FY-2018 will be dependent upon the extent to which otherwise unused numbers are available.
B49: 43191 | C49: 41842 | D49: 41883 | J49: F. DELAY IN OVERSUBSCRIPTION OF THE VIETNAM EMPLOYMENT FIFTH PREFERENCE CATEGORY: Continued heavy applicant demand had been expected to result in the Vietnam Employment Fifth preference (EB-5) category reaching the per-country annual limit during March. However, the return of unused February EB-5 numbers during the past few days has been much higher than had been expected. This appears to be a direct result of the continuing resolution signed on December 22, 2017 extending the immigrant investor pilot program until January 19, 2018, and the subsequent extension until February 9, 2018. Uncertainty over category extension greatly delayed the scheduling of February appointments, which would normally have occurred in early January. As a result, many applicants did not have sufficient advance notice to enable them to appear for their February interview, which could have been expected to result in the use of visa numbers. The oversubscription of this category will definitely occur for May.
B50: 43221 | C50: 41842 | D50: 41883 | E50: 41842
B51: 43252 | C51: 41852 | D51: 41883 | E51: 41852
B52: 43282 | C52: 41852 | D52: 41913 | E52: 41852
B53: 43313 | C53: 41852 | D53: 41913 | E53: 41852
B54: 43344 | C54: 41859 | D54: 41913 | E54: 41859
B55: 43374 | C55: 41866 | D55: 41913 | E55: 42370
B56: 43405 | C56: 41866 | D56: 41913 | E56: 42401
B57: 43435 | C57: 41873 | D57: 41913 | E57: 42491
B58: 43466 | C58: 41883 | D58: 41913 | E58: 42522
B59: 43497 | C59: 41883 | D59: 41913 | E59: 42536 | J59: Employment Fifth: The category will remain “Current” for most countries. China-mainland born: Up to one week. Vietnam: Up to three weeks. The above final action date projections for the Family and Employment categories indicate what is likely to happen on a monthly basis through May. The determination of the actual monthly final action dates is subject to fluctuations in applicant demand and a number of other variables. It is also important to remember that by no means has every applicant with a priority date earlier than a prevailing final action date been processed for final visa action, with applicants often processing at their own initiative and convenience.
B60: 43525 | C60: 41890 | D60: 41913 | E60: 42566
B61: 43556 | C61: 41897 | D61: 41920 | E61: 42604
B62: 43586 | C62: 41904 | D62: 41927 | E62: 42635
B63: 43617 | C63: 41913 | D63: 41944 | E63: 42644 | J63: E. EMPLOYMENT-BASED FIFTH PREFERENCE VISA AVAILABILITY India: Continued heavy applicant demand is expected to result in the India Employment Fifth preference (E5) category approaching the per-country annual limit during July. This is likely to result in the imposition of a July final action date, and that date will be sometime in 2017. Then for August, India will become subject to the same final action date which applies to China-mainland born Employment Fifth preference applicants for the remainder of the fiscal year. Such action will only be temporary with the E5 date for India most likely advancing to the summer or fall of 2017 for October, the first month of fiscal year 2020.
B65: Visa Bulletin Date | C65: China | E65: Vietnam | G65: India | I65: Adjustment of Status uses… | J65: Visa Bulletin Note
C66: Chart A | D66: Chart B | E66: Chart A | F66: Chart B | G66: Chart A | H66: Chart B
B67: 43647 | C67: 41913 | D67: 41944 | E67: 42644 | F67: C | G67: 42856 | H67: C | I67: Chart A
B68: 43678 | C68: 41927 | D68: 41958 | E68: 41927 | F68: C | G68: 41927 | H68: C | I68: Chart A
B69: 43709 | C69: 41934 | D69: 41965 | E69: 41934 | F69: C | G69: 42979 | H69: C | I69: Chart A
B70: 43739 | C70: 41934 | D70: 42005 | E70: 42658 | F70: C | G70: 43061 | H70: C | I70: Chart B
B71: 43770 | C71: 41944 | D71: 42005 | E71: 42689 | F71: C | G71: 43077 | H71: C | I71: Chart B
B72: 43800 | C72: 41958 | D72: 42005 | E72: 42705 | F72: C | G72: 43101 | H72: C | I72: Chart B
B73: 43831 | C73: 41965 | D73: 42139 | E73: 42712 | F73: C | G73: 43221 | H73: C | I73: Chart B
B74: 43862 | C74: 41974 | D74: 42139 | E74: 42719 | F74: C | G74: 43344 | H74: C | I74: Chart B | J74: [Guangzhou stopped issuing visas 2/2020]
B75: 43891 | C75: 42139 | D75: 42353 | E75: 42750 | F75: C | G75: 43395 | H75: C | I75: Chart B
B76: 43922 | C76: 42139 | D76: 42353 | E76: 42774 | F76: C | G76: 43466 | H76: C | I76: Chart A
B77: 43952 | C77: 42186 | D77: 42353 | E77: 42826 | F77: C | G77: 43739 | H77: C | I77: Chart A
B78: 43983 | C78: 42200 | D78: 42353 | E78: 42847 | F78: C | G78: 43831 | H78: C | I78: Chart A
B79: 44013 | C79: 42207 | D79: 42353 | E79: 42870 | F79: C | G79: C | H79: C | I79: Chart A
B80: 44044 | C80: 42231 | D80: 42353 | E80: 42938 | F80: C | G80: C | H80: C | I80: Chart A
B81: 44075 | C81: 42231 | D81: 42353 | E81: 42948 | F81: C | G81: C | H81: C | I81: Chart A
B82: 44105 | C82: 42231 | D82: 42353 | E82: 42948 | F82: C | G82: C | H82: C | I82: Chart B
B83: 44136 | C83: 42231 | D83: 42353 | E83: 42962 | F83: C | G83: C | H83: C | I83: Chart B
B84: 44166 | C84: 42231 | D84: 42353 | E84: 42979 | F84: C | G84: C | H84: C | I84: Chart B
B85: 44197 | C85: 42231 | D85: 42353 | E85: 42993 | F85: C | G85: C | H85: C | I85: Chart A
B86: 44228 | C86: 42231 | D86: 42353 | E86: 43009 | F86: C | G86: C | H86: C | I86: Chart A | J86: EMPLOYMENT-based categories (potential monthly movement): Employment Fifth: The category will remain “Current” for most countries China: No forward movement Vietnam: Up to three weeks The above final action date projections for the Family and Employment categories indicate what is likely to happen on a monthly basis through May.
B87: 44256 | C87: 42231 | D87: 42353 | E87: 43030 | F87: C | G87: C | H87: C | I87: Chart A
B88: 44287 | C88: 42231 | D88: 42353 | E88: 43084 | F88: C | G88: C | H88: C | I88: Chart A | J88: @TravelGov will begin hosting "Chats with Charlie" on our YouTube channel (https://www.youtube.com/user/TravelGov) to discuss information provided in the monthly Visa Bulletin. The first chat is scheduled to take place on March 17, 2021 at 1:00 pm EST to discuss the April Visa Bulletin.
B89: 44317 | C89: 42231 | D89: 42353 | E89: 43146 | F89: C | G89: C | H89: C | I89: Chart A
B90: 44348 | C90: 42262 | D90: 42353 | E90: 43205 | F90: C | G90: C | H90: C | I90: Chart A
B91: 44378 | C91: 42316 | D91: 42353 | E91: 43922 | F91: C | G91: C | H91: C | I91: Chart A
B92: 44409 | C92: 42323 | D92: 42353 | E92: C | F92: C | G92: C | H92: C | I92: Chart A
B93: 44440 | C93: 42330 | D93: 42353 | E93: C | F93: C | G93: C | H93: C | I93: Chart A
B94: 44470 | C94: 42330 | D94: 42353 | E94: C | F94: C | G94: C | H94: C | I94: Chart B except RC EB-5 (USCIS will not accept any new employment-based fifth preference adjustment of status applications based on the Regional Center Program until that program is reauthorized. ) | J94: F. VISA AVAILABILITY IN THE COMING MONTHS: The final action date projections for the Family and Employment categories indicate what is likely to happen on a monthly basis through January. Employment Fifth: Current for most countries; China: No forward movement
B95: 44501 | C95: 42330 | D95: 42353 | E95: C | F95: C | G95: C | H95: C | J95: F. EXPLANATION OF THE NUMERICAL CONTROL SYSTEM, ANNUAL AND PER-COUNTRY LIMITS WHAT CAUSES THE ESTABLISHMENT OF FINAL ACTION DATES? The Visa Office (VO) subdivides the annual preference and foreign state limitations specified in the Immigration and Nationality Act (INA) into twelve monthly allotments. The totals of documentarily complete applicants that have been reported to VO are compared each month with the numbers available for the next regular allotment and numbers are allocated to reported applicants in order of their priority dates (the oldest dates first). - If there are enough visa numbers available in a particular category to satisfy all reported documentarily complete demand, the category is considered “Current.” For example, if the Employment First preference monthly target is 5,000 and there are only 3,000 applicants, the category is considered “Current.” - Whenever the total number of documentarily complete applicants in a category exceeds the supply of numbers available for allotment for the upcoming month, the category is considered “oversubscribed”, and a visa availability final action date is established. The final action date is the priority date of the first documentarily complete applicant who could not be accommodated for the use of a visa number. For example, if the Employment First preference monthly target is 5,000 and there are 8,000 applicants, a final action date would be established so that only 5,000 numbers would be used, and the final action date would be the priority date of the 5,001st applicant. Applicants entitled to immigrant status become documentarily complete at their own initiative and convenience and upon the completion of various processing requirements. Therefore, it is extremely important to remember that by no means has every applicant with a priority date earlier than a prevailing final action date been processed for final visa action. On the contrary, visa allotments are made only based on the total applicants reported documentarily complete each month and in consideration of other variables. Demand for visa numbers can fluctuate from one month to another with an inevitable impact on final action dates, an important fact to remember as processing continues to return to normal pre-COVID levels. Annual Family-sponsored and Employment-based limit: Section 201 of the INA sets an annual minimum Family-sponsored preference limit of 226,000, while the worldwide annual level for Employment-based preference immigrants is at least 140,000. Unused numbers from the previous year’s annual limits are considered in the calculation of these annual limits. Per-country limit: The annual per-country limitation of 7% is a cap, which visa issuances to any single country may not exceed. Applicants compete for visas primarily on a worldwide basis. The per-country limitation serves to avoid monopolization of virtually all the annual limitation by applicants from only a few countries. This limitation is not a quota to which any particular country is entitled, however. Applicability of Section 202(a)(5): INA Section 202(a)(5), added by the American Competitiveness Act in the 21st Century, removed the per-country limit on Employment-based immigrants in any calendar quarter in which applicant demand for numbers in one or more Employment-based preferences is less than the total of such numbers available. In recent years, the application of Section 202(a)(5) has allowed countries such as China – mainland born and India to utilize large amounts of Employment-based preference numbers, which otherwise would have gone unused. Such numbers are provided strictly in priority date order without regard to the foreign state chargeability, and the same final action date applies to any country benefiting from this provision. Applicability of Section 202(e): When visa demand by documentarily complete applicants from a particular country exceeds the amount of numbers available under the annual numerical limitation, that country is considered to be oversubscribed. Oversubscription may require the establishment of an earlier final action date than that which applies to a particular visa category on a worldwide basis. The prorating of numbers for an oversubscribed country follows the same percentages specified for the division of the worldwide annual limitation among the preferences. (Note that visa availability final action dates for oversubscribed areas may not be later than worldwide final action dates, if any, for the respective preferences.)
B96: 44531 | C96: C | D96: 42353 | E96: C | F96: C | G96: C | H96: C | J96: F. CHINA-MAINLAND BORN EMPLOYMENT-BASED FIFTH PREFERENCE C5 AND T5 NON-REGIONAL CENTER VISA CATEGORIES BECOME “CURRENT” FOR DECEMBER These categories have become “Current” for December; however if China-mainland born number use were to materialize at a level which could potentially jeopardize visa availability under the overall FY-2022 Employment-based Fifth preference annual limit it would then be necessary to once again impose a final action date.
B97: 44562 | C97: C | D97: 42353 | E97: C | F97: C | G97: C | H97: C | J97: If there is legislative action extending this category for January, the final action dates would immediately become “Current” for January for all countries except China-mainland born I5 and R5, which would be subject to a November 22, 2015 final action date.
B98: 44593 | C98: C | D98: 42353 | E98: C | F98: C | G98: C | H98: C
B99: 44621 | C99: C | D99: 42353 | E99: C | F99: C | G99: C | H99: C | J99: D. EXPIRATION OF THE EMPLOYMENT-BASED FIFTH PREFERENCE I5 AND R5 REGIONAL CENTER VISA CATEGORIES Division O, Title 1, Section 104 of the Consolidated Appropriations Act, 2021 extended the immigrant investor pilot program until June 30, 2021. No I5 or R5 visas may be issued overseas, or final action taken on adjustment of status cases after June 30, 2021. The final action dates for the I5 and R5 categories have been listed as “Unavailable” for March. If there is legislative action extending this category for March, the final action dates would immediately become “Current” for March for all countries except China-mainland born I5 and R5, which would be subject to a November 22, 2015 final action date. It may also become necessary to establish a China-mainland born final action date and application filing date for the C5 and T5 categories as early as April to keep number use within the maximum allowed under the FY-2022 annual limits. In addition, if sufficient demand materializes in the Employment-based Fifth Preference category, corrective action may need to be taken in the India Employment-based Second Preference category, which would have utilized any otherwise unused numbers from the Employment-based Fifth Preference.
B100: 44652 | C100: C | D100: 42353 | E100: C | F100: C | G100: C | H100: C | J100: The Consolidated Appropriations Act, 2022, which reauthorizes and reforms the EB-5 Immigrant Investor Regional Center Program, was signed by the President of the United States on March 15, 2022. Certain Regional Center Program aspects of this legislation go into effect 60 days after the date of the enactment of this Act. More information will be published in coming editions of the Visa Bulletin.
B102: China Visa Bulletin EB-5 | E102: India Visa Bulletin EB-5
C103: Chart A | D103: Chart B | E103: Chart A | F103: Chart B | I103: Adjustment of Status uses… | J103: Visa Bulletin Note
C104: Unreserved | D104: Unreserved | E104: Unreserved | F104: Unreserved
B105: 44682 | C105: 42330 | D105: 42353 | E105: C | F105: C | J105: C category specifically for China direct. Fifth: Employment Creation: 7.1% of the worldwide level, of which 32% are reserved as follows: 20% reserved for qualified immigrants who invest in a rural area; 10% reserved for qualified immigrants who invest in a high unemployment area; and 2% reserved for qualified immigrants who invest in infrastructure projects. The remaining 68% are unreserved and are allotted for all other qualified immigrants.
B106: 44713 | C106: 42330 | D106: 42360 | E106: C | F106: C | J106: It has become necessary to establish a final action date and application filing date for C5 and T5 China-mainland born because sufficient demand has materialized as readers were cautioned was a possibility in Item D of the May 2022 Visa Bulletin. China-mainland born C5 and T5 applicants are subject to a 22NOV15 final action date and an application filing date of 15DEC15.
B107: 44743 | C107: 42330 | D107: 42360 | E107: C | F107: C
B108: 44774 | C108: 42330 | D108: 42360 | E108: C | F108: C
B109: 44805 | C109: 42330 | D109: 42370 | E109: C | F109: C | J109: D. AVAILABILITY OF EMPLOYMENT-BASED VISAS DURING SEPTEMBER There has been a steady increase in both USCIS and Department of State demand patterns for employment-based visas during the fiscal year. As a result, most employment-based preference category limits and/or the overall employment-based preference limit for FY 2022 are expected to be reached during September. If at any time an annual limit were reached, it would be necessary to immediately make the preference category “unavailable”, and no further requests for numbers would be honored.
B110: 44835 | C110: 42085 | D110: 42370 | E110: 43777 | F110: 43807 | I110: Chart B | J110: E. RETROGRESSION OF CHINA-MAINLAND BORN FINAL ACTION DATE AND IMPOSITION OF INDIA FINAL ACTION DATE IN THE EMPLOYMENT-BASED FIFTH PREFERENCE UNRESERVED CATEGORIES (INCLUDING C5, T5, I5, AND R5) It was necessary to retrogress the final action date for the China-mainland born Employment-Based Fifth Preference unreserved categories due to heavy demand for numbers, primarily for visa issuances abroad. In addition, sufficient India demand has materialized in the Employment-Based Fifth Preference unreserved categories to require the imposition of a final action date for October. Heavy China-mainland born and India demand along with lower visa number availability for FY-2023 as compared to FY-2021 and FY-2022 has made these corrective actions necessary to keep number use within the maximum allowed under the FY-2023 annual limits. The situation will be continually monitored, and any necessary adjustments made accordingly.
B111: 44866 | C111: 42085 | D111: 42370 | E111: 43777 | F111: 43807 | I111: Chart B
B112: 44896 | C112: 42085 | D112: 42370 | E112: 43777 | F112: 43807 | I112: Chart B
B113: 44927 | C113: 42085 | D113: 42370 | E113: 43777 | F113: 43807 | I113: Chart B
B114: 44958 | C114: 42085 | D114: 42370 | E114: 43777 | F114: 43807 | I114: Chart B
B115: 44986 | C115: 42193 | D115: 42370 | E115: 43252 | F115: 43807 | I115: Chart B
B116: 45017 | C116: 42193 | D116: 42370 | E116: 43252 | F116: 43807 | I116: Chart A
B117: 45047 | C117: 42255 | D117: 42370 | E117: 43252 | F117: 43807 | I117: Chart A
B118: 45078 | C118: 42255 | D118: 42370 | E118: 42826 | F118: 43807 | I118: Chart A | J118: F. . RETROGRESSION IN THE EMPLOYMENT-BASED FIFTH PREFERENCE (EB-5) FOR INDIA As readers were informed was possible in Item F of the May 2023 Visa Bulletin, it has become necessary to retrogress the EB-5 final action date for India effective in June. India’s number use in the family and employment preference categories for FY-2023 is subject to prorating under INA 202(e). Number use has been consistently robust throughout the fiscal year in the family and employment preference categories, and it has been determined that India is approaching its prorated limit for EB-5 numbers. Thus, applicants from India are subject to a final action date of 01APR17. This situation will be continually monitored, and any necessary adjustments will be made accordingly.
B119: 45108 | C119: 42255 | D119: 42370 | E119: 42826 | F119: 43807 | I119: Chart A
B120: 45139 | C120: 42255 | D120: 42370 | E120: 42826 | F120: 43807 | I120: Chart A
B121: 45170 | C121: 42255 | D121: 42370 | E121: 42826 | F121: 43807 | I121: Chart A | J121: Employment-based number use by both USCIS and Department of State has been steady during the fiscal year. As a result, most employment-based preference category limits and/or the overall employment-based preference limit for FY 2023 are expected to be reached during September.
B122: 45200 | C122: 42278 | D122: 42736 | E122: 43449 | F122: 44652 | I122: Chart B | J122: These provisions apply at present to the following oversubscribed chargeability areas: CHINA-mainland born, INDIA, MEXICO, and PHILIPPINES. E. EMPLOYMENT-BASED VISA AVAILABILITY FOR FY-2024 Final action dates across most employment-based visa categories have advanced, reflecting new visa numbers available for FY-2024. Date advancements reflect an intention to keep visa issuance within quarterly limits in accordance with INA sections 201(a)(2) and 203(g), with potential date advancements throughout the fiscal year. However, actual date movements will be dependent on visa demand and issuance patterns throughout FY-2024.
B123: 45231 | C123: 42278 | D123: 42736 | E123: 43449 | F123: 44652 | I123: Chart B
...

Sheet Notes
A1: Notes of major updates or revisions to the model
A3: Date | B3: Change
A4: 45726 | B4: Based on the April 2025 Visa Bulletin, revised the estimated allocation of FY2025 visas down for China and up for ROW
A5: 45788 | B5: Completely revised the model based on monthly I-526/I-526E demand data through January 2025 (replacing estimates based on data as of July 2024)
A6: 45796 | B6: Revised the HU and Rural tab presentations, and hid the Pre-RIA detail tabs pending new data
A7: 45800 | B7: Fixed the match parameter in the Xlookup formula on the HU and Rural tabs
A8: 45803 | B8: Added all-time visa issuance data to the Progress tab, and added Visa Supply tab
A9: 45840 | B9: Added FY2025 Q2 data to the Progress tab, and changed the HU tab scenario to help model apparently rising demand since January 2025
A10: 45852 | B10: Based on the August 2025 Visa Bulletin, revised the estimated allocation of FY2025 visas up for China and down for ROW
A11: 45852 | B11: Revised the Unreserved tab and Visa Supply tab based on reports of actual visa issuance in FY2024 and January to May 2025
A12: 45943 | B12: Completely revised the model based on I-526/I-526E demand data through June 2025 (replacing estimates based on data as of January 2025), and replaced range of scenarios with simplistic best-case worst-case scenarios.
A13: 45943 | B13: Incorporated tabs previously saved in the Key EB5 Backlog Data file
A14: 45958 | B14: Added the 5YR Analysis tab to help model scenarios for demand and visa issuance before 2030
A15: 46043 | B15: Changed the Overview tab (aiming to better capture the impact of to-date visa issuance), added a new Forecast tab to replace the previous Rural, HUA, Scenario, and Unreserved tabs (aiming for a tidier presentation), added data to the Progress tab
... A19: 46238 | B19: Updated with USCIS data through March 2026.
